Workbook

Sheet KPI
A1: STORE
A2: Category | B2: ITEM | C2: TARGET | D2: CONTRIBUTION | E2: CARA PENILAIAN
A3: Sales Achievement | B3: Net Sales | C3: Tier 2 | D3: 0.4 | E3: Tercapai Tier 2
A4: Sales Achievement | B4: AVG Transactions | C4: 55000 | D4: 0.1 | E4: Net Sales AVG
A5: Sales Achievement | B5: Large Attach Rate | C5: 0.65 | D5: 0.05 | E5: Rasio Large 65% dari seluruh cup yang terjual
A6: Sales Achievement | B6: Oatmilk Attach Rate | C6: 0.05 | D6: 0.05 | E6: Rasio Oatmilk 5% dari seluruh minuman dengan modifier oatmilk
A7: Sales Achievement | B7: Snack Platter Attach Rate | C7: 0.1 | D7: 0.05 | E7: Rasio Snack Platter 10% dari seluruh snack yang terjual
A8: Sales Achievement | B8: Bundling Asik Attach Rate | C8: 0.05 | D8: 0.05 | E8: Rasio Bundling Asik 5% dari Transaksi selama periode
A9: Quality & Compliance | B9: Audit | C9: 0.9 | D9: 0.15 | E9: APD
A10: Quality & Compliance | B10: Mistery Shopper | C10: 1 | D10: 0.05 | E10: Mistery Shopper
A11: Quality & Compliance | B11: Complain | C11: 0.001 | D11: 0.1 | E11: Rasio komplain maksimal 0.10%
A15: STORE MANAGER
A16: CATEGORY | B16: ITEM | C16: TARGET | D16: CONTRIBUTION | E16: CARA PENILAIAN
A17: Sales Execution & Control | B17: Daily Target Briefing & Shift Brief | C17: 1 | D17: 0.05 | E17: Video ke DM
A18: Sales Execution & Control | B18: Monitoring AVG Transaction & Attach Rate | C18: 1 | D18: 0.05 | E18: Buat Laporan Setiap Hari ke DM
A19: Sales Execution & Control | B19: Achievement Sales KPI Store | C19: 1 | D19: 0.4 | E19: Target Sales Daily Tercapai
A20: Cost & Inventory Control | B20: HPP Control | C20: 0.47 | D20: 0.05 | E20: HPP Finance
A21: Cost & Inventory Control | B21: Waste & Spoil Monitoring | C21: 1 | D21: 0.025 | E21: LOG Lengkap
A22: Cost & Inventory Control | B22: Stock Accuracy & FIFO | C22: 1 | D22: 0.025 | E22: Audit DM Mingguan
A23: Cost & Inventory Control | B23: Opex | C23: 0.03 | D23: 0.025 | E23: Deviasi vs Budget
A24: Team Management & Coaching | B24: Coaching LOG Staff | C24: 0.5 | D24: 0.05 | E24: Coaching 1-1
A25: Team Management & Coaching | B25: Training Execution | C25: 1 | D25: 0.05 | E25: Training by Modul
A26: Team Management & Coaching | B26: Staff Discipline & Attendance | C26: 1 | D26: 0.025 | E26: Sesuai SOP HR
A27: Quality & Compliance | B27: Audit Score | C27: 0.9 | D27: 0.1 | E27: Sesuai SOP Audit
A28: Quality & Compliance | B28: SOP & Cleanliness | C28: 1 | D28: 0.05 | E28: Audit DM Mingguan
A29: Quality & Compliance | B29: Retention | C29: 0.05 | D29: 0.05 | E29: Staff yang resign
A30: Customer Handling | B30: Complain Handling SLA | C30: 3x24 Jam | D30: 0.05 | E30: Admin CS
A33: DISTRICT MANAGER
A34: CATEGORY | B34: ITEM | C34: TARGET | D34: CONTRIBUTION | E34: CARA PENILAIAN
A35: Store Performance Governance | B35: % Store Achieve KPI Sales | C35: 1 | D35: 0.4 | E35: KPI Store
A36: Store Performance Governance | B36: AVG Sales & Attach Rate District | C36: 1 | D36: 0.1 | E36: vs Target
A37: Head Store Effectiveness | B37: % Head Store KPI Achievement | C37: 1 | D37: 0.1 | E37: KPI Head Store
A38: Head Store Effectiveness | B38: Head Store Coaching | C38: 1 | D38: 0.05 | E38: Coaching LOG
A39: Head Store Effectiveness | B39: Head Store Discipline & Compliance | C39: 1 | D39: 0.05 | E39: Major Issue
A40: Operational Control & Risk | B40: AVG HPP District | C40: 0.475 | D40: 0.05 | E40: HPP Finance
A41: Operational Control & Risk | B41: Audit Pass Rate | C41: 0.9 | D41: 0.05 | E41: Audit
A42: Operational Control & Risk | B42: Complaint Closure SLA | C42: 3x24Jam | D42: 0.05 | E42: <SLA
A43: Execution & Discipline | B43: Store Visit Coverage | C43: 1 | D43: 0.1 | E43: Visit Log
A44: Execution & Discipline | B44: Action Plan Closure | C44: 1 | D44: 0.05 | E44: Head Store Follow UP
A47: AREA MANAGER
A48: Category | B48: ITEM | C48: TARGET | D48: CONTRIBUTION | E48: CARA PENILAIAN
A49: Store Performance Governance | B49: % Store Achieve KPI Sales | C49: 1 | D49: 0.4 | E49: KPI Store
A50: Store Performance Governance | B50: AVG Sales Index Area | C50: 60000 | D50: 0.1 | E50: Net Sales + AVG
A51: District Manager Effectiveness | B51: % District Manager KPI Achievement | C51: 1 | D51: 0.1 | E51: KPI District Manager
A52: District Manager Effectiveness | B52: Coaching & Review District Manager | C52: 1 | D52: 0.05 | E52: Coaching LOG
A53: Operational Control & Risk | B53: AVG HPP Area | C53: 0.475 | D53: 0.05 | E53: HPP Finance
A54: Operational Control & Risk | B54: Audit Compliance Area | C54: 0.9 | D54: 0.05 | E54: Audit
A55: Operational Control & Risk | B55: Major Issue Closure Rate | C55: 1 | D55: 0.05 | E55: Complain & Audit
A56: Execution & Discipline | B56: Store Visit Coverage | C56: 1 | D56: 0.1 | E56: Visit Log
A57: Execution & Discipline | B57: Action Plan Closure | C57: 1 | D57: 0.05 | E57: District Manager Follow UP
A58: Execution & Discipline | B58: Reporting Accuracy & On-Time | C58: 1 | D58: 0.05 | E58: Weekly & Monthly

Sheet Jan
B1: Store | C1: Net Sales | D1: AVG | E1: Large | F1: Oatside | G1: Snack Platter | H1: B. Asik | I1: Audit | J1: M. Shopper | K1: Complain | L1: Total | N1: Orang | O1: Score
A2: Nadine | B2: Kranggan | C2: {=iferror(LET( kode, B2, actual, XLOOKUP(kode, Sales!A:A, Sales!C:C), target, XLOOKUP(kode, Sales!A:A, Sales!B:B), ratio, actual/target, skor, IFS( ratio>1, 5, ratio>=0.975, 4, ratio>=0.95, 3, ratio>=0.9, 2, TRUE, 1 ), skor ),0)} -> 4 | D2: {=iferror(LET( kode, B2, actual, XLOOKUP(kode, AVG!A:A, AVG!C:C), target, XLOOKUP(kode, AVG!A:A, AVG!B:B), ratio, actual/target, skor, IFS( ratio>1, 5, ratio>=0.975, 4, ratio>=0.95, 3, ratio>=0.9, 2, TRUE, 1 ), skor ),0)} -> 5 | E2: {=iferror(LET( kode, B2, large, XLOOKUP(kode, Large!A:A, Large!C:C), small, XLOOKUP(kode, Large!A:A, Large!B:B), ratio, large/(large+small), skor, IFS( ratio<0.45, 1, ratio<=0.5, 2, ratio<=0.55, 3, ratio<=0.6, 4, TRUE, 5 ), skor ),0)} -> 4 | F2: {=iferror(LET( kode, B2, oatmilk, XLOOKUP(kode, Oatside!A:A, Oatside!C:C), drink, XLOOKUP(kode, Oatside!A:A, Oatside!B:B), ratio, oatmilk/drink, skor, IFS( ratio>5%, 5, ratio>=4%, 4, ratio>=3%, 3, ratio>=2%, 2, TRUE, 1 ), skor ),0)} -> 5 | G2: {=iferror(LET( kode, B2, actual, XLOOKUP(kode, 'Snack Platter'!A:A, 'Snack Platter'!C:C), target, XLOOKUP(kode, 'Snack Platter'!A:A, 'Snack Platter'!B:B), ratio, actual/target, skor, IFS( ratio>10%, 5, ratio>=7.5%, 4, ratio>=5%, 3, ratio>=2.5%, 2, TRUE, 1 ), skor ),0)} -> 3 | H2: {=iferror(LET( kode, B2, actual, XLOOKUP(kode, 'Bundling Asik'!A:A, 'Bundling Asik'!C:C), target, XLOOKUP(kode, 'Bundling Asik'!A:A, 'Bundling Asik'!B:B), ratio, actual/target, skor, IFS( ratio>5%, 5, ratio>=4%, 4, ratio>=3%, 3, ratio>=2%, 2, TRUE, 1 ), skor ),0)} -> 5 | I2: {=iferror(LET( kode, B2, ratio, XLOOKUP(kode, Audit!A:A, Audit!B:B), skor, IFS( ratio>90, 5, ratio>=85, 4, ratio>=80, 3, ratio>=75, 2, TRUE, 1 ), skor ),0)} -> 5 | J2: {=iferror(LET( kode, B2, ratio, XLOOKUP(kode, 'Mistery Shopper'!A:A, 'Mistery Shopper'!B:B), skor, IFS( ratio>90%, 5, ratio>=85%, 4, ratio>=80%, 3, ratio>=75%, 2, TRUE, 1 ), skor ),0)} -> 5 | K2: {=iferror(LET( kode, B2, actual, XLOOKUP(kode, Complain!A:A, Complain!C:C), target, XLOOKUP(kode, Complain!A:A, Complain!B:B), ratio, actual/target, skor, IFS( ratio>=0.16%, 1, ratio>=0.15%, 2, ratio>=0.125%, 3, ratio>=0.1%, 4, TRUE, 5 ), skor ),0)} -> 5 | L2: =LET( nilai, C2:K2, bobot, {0.4,0.1,0.05,0.05,0.05,0.05,0.15,0.05,0.1}, SUMPRODUCT(nilai,bobot) )/5 -> 0.89 | N2: Risti | O2: =averageif(A:A,N2,L:L) -> 0.688
A3: Nadine | B3: Kota Wisata | C3: {=iferror(LET( kode, B3, actual, XLOOKUP(kode, Sales!A:A, Sales!C:C), target, XLOOKUP(kode, Sales!A:A, Sales!B:B), ratio, actual/target, skor, IFS( ratio>1, 5, ratio>=0.975, 4, ratio>=0.95, 3, ratio>=0.9, 2, TRUE, 1 ), skor ),0)} -> 5 | D3: {=iferror(LET( kode, B3, actual, XLOOKUP(kode, AVG!A:A, AVG!C:C), target, XLOOKUP(kode, AVG!A:A, AVG!B:B), ratio, actual/target, skor, IFS( ratio>1, 5, ratio>=0.975, 4, ratio>=0.95, 3, ratio>=0.9, 2, TRUE, 1 ), skor ),0)} -> 5 | E3: {=iferror(LET( kode, B3, large, XLOOKUP(kode, Large!A:A, Large!C:C), small, XLOOKUP(kode, Large!A:A, Large!B:B), ratio, large/(large+small), skor, IFS( ratio<0.45, 1, ratio<=0.5, 2, ratio<=0.55, 3, ratio<=0.6, 4, TRUE, 5 ), skor ),0)} -> 5 | F3: {=iferror(LET( kode, B3, oatmilk, XLOOKUP(kode, Oatside!A:A, Oatside!C:C), drink, XLOOKUP(kode, Oatside!A:A, Oatside!B:B), ratio, oatmilk/drink, skor, IFS( ratio>5%, 5, ratio>=4%, 4, ratio>=3%, 3, ratio>=2%, 2, TRUE, 1 ), skor ),0)} -> 5 | G3: {=iferror(LET( kode, B3, actual, XLOOKUP(kode, 'Snack Platter'!A:A, 'Snack Platter'!C:C), target, XLOOKUP(kode, 'Snack Platter'!A:A, 'Snack Platter'!B:B), ratio, actual/target, skor, IFS( ratio>10%, 5, ratio>=7.5%, 4, ratio>=5%, 3, ratio>=2.5%, 2, TRUE, 1 ), skor ),0)} -> 4 | H3: {=iferror(LET( kode, B3, actual, XLOOKUP(kode, 'Bundling Asik'!A:A, 'Bundling Asik'!C:C), target, XLOOKUP(kode, 'Bundling Asik'!A:A, 'Bundling Asik'!B:B), ratio, actual/target, skor, IFS( ratio>5%, 5, ratio>=4%, 4, ratio>=3%, 3, ratio>=2%, 2, TRUE, 1 ), skor ),0)} -> 4 | I3: {=iferror(LET( kode, B3, ratio, XLOOKUP(kode, Audit!A:A, Audit!B:B), skor, IFS( ratio>90, 5, ratio>=85, 4, ratio>=80, 3, ratio>=75, 2, TRUE, 1 ), skor ),0)} -> 4 | J3: {=iferror(LET( kode, B3, ratio, XLOOKUP(kode, 'Mistery Shopper'!A:A, 'Mistery Shopper'!B:B), skor, IFS( ratio>90%, 5, ratio>=85%, 4, ratio>=80%, 3, ratio>=75%, 2, TRUE, 1 ), skor ),0)} -> 5 | K3: {=iferror(LET( kode, B3, actual, XLOOKUP(kode, Complain!A:A, Complain!C:C), target, XLOOKUP(kode, Complain!A:A, Complain!B:B), ratio, actual/target, skor, IFS( ratio>=0.16%, 1, ratio>=0.15%, 2, ratio>=0.125%, 3, ratio>=0.1%, 4, TRUE, 5 ), skor ),0)} -> 1 | L3: =LET( nilai, C3:K3, bobot, {0.4,0.1,0.05,0.05,0.05,0.05,0.15,0.05,0.1}, SUMPRODUCT(nilai,bobot) )/5 -> 0.87 | N3: Nadine | O3: =averageif(A:A,N3,L:L) -> 0.682
A4: Risti | B4: Metro | C4: {=iferror(LET( kode, B4, actual, XLOOKUP(kode, Sales!A:A, Sales!C:C), target, XLOOKUP(kode, Sales!A:A, Sales!B:B), ratio, actual/target, skor, IFS( ratio>1, 5, ratio>=0.975, 4, ratio>=0.95, 3, ratio>=0.9, 2, TRUE, 1 ), skor ),0)} -> 5 | D4: {=iferror(LET( kode, B4, actual, XLOOKUP(kode, AVG!A:A, AVG!C:C), target, XLOOKUP(kode, AVG!A:A, AVG!B:B), ratio, actual/target, skor, IFS( ratio>1, 5, ratio>=0.975, 4, ratio>=0.95, 3, ratio>=0.9, 2, TRUE, 1 ), skor ),0)} -> 4 | E4: {=iferror(LET( kode, B4, large, XLOOKUP(kode, Large!A:A, Large!C:C), small, XLOOKUP(kode, Large!A:A, Large!B:B), ratio, large/(large+small), skor, IFS( ratio<0.45, 1, ratio<=0.5, 2, ratio<=0.55, 3, ratio<=0.6, 4, TRUE, 5 ), skor ),0)} -> 1 | F4: {=iferror(LET( kode, B4, oatmilk, XLOOKUP(kode, Oatside!A:A, Oatside!C:C), drink, XLOOKUP(kode, Oatside!A:A, Oatside!B:B), ratio, oatmilk/drink, skor, IFS( ratio>5%, 5, ratio>=4%, 4, ratio>=3%, 3, ratio>=2%, 2, TRUE, 1 ), skor ),0)} -> 5 | G4: {=iferror(LET( kode, B4, actual, XLOOKUP(kode, 'Snack Platter'!A:A, 'Snack Platter'!C:C), target, XLOOKUP(kode, 'Snack Platter'!A:A, 'Snack Platter'!B:B), ratio, actual/target, skor, IFS( ratio>10%, 5, ratio>=7.5%, 4, ratio>=5%, 3, ratio>=2.5%, 2, TRUE, 1 ), skor ),0)} -> 2 | H4: {=iferror(LET( kode, B4, actual, XLOOKUP(kode, 'Bundling Asik'!A:A, 'Bundling Asik'!C:C), target, XLOOKUP(kode, 'Bundling Asik'!A:A, 'Bundling Asik'!B:B), ratio, actual/target, skor, IFS( ratio>5%, 5, ratio>=4%, 4, ratio>=3%, 3, ratio>=2%, 2, TRUE, 1 ), skor ),0)} -> 2 | I4: {=iferror(LET( kode, B4, ratio, XLOOKUP(kode, Audit!A:A, Audit!B:B), skor, IFS( ratio>90, 5, ratio>=85, 4, ratio>=80, 3, ratio>=75, 2, TRUE, 1 ), skor ),0)} -> 4 | J4: {=iferror(LET( kode, B4, ratio, XLOOKUP(kode, 'Mistery Shopper'!A:A, 'Mistery Shopper'!B:B), skor, IFS( ratio>90%, 5, ratio>=85%, 4, ratio>=80%, 3, ratio>=75%, 2, TRUE, 1 ), skor ),0)} -> 5 | K4: {=iferror(LET( kode, B4, actual, XLOOKUP(kode, Complain!A:A, Complain!C:C), target, XLOOKUP(kode, Complain!A:A, Complain!B:B), ratio, actual/target, skor, IFS( ratio>=0.16%, 1, ratio>=0.15%, 2, ratio>=0.125%, 3, ratio>=0.1%, 4, TRUE, 5 ), skor ),0)} -> 5 | L4: =LET( nilai, C4:K4, bobot, {0.4,0.1,0.05,0.05,0.05,0.05,0.15,0.05,0.1}, SUMPRODUCT(nilai,bobot) )/5 -> 0.85 | N4: Sohib | O4: =averageif(A:A,N4,L:L) -> 0.625
A5: Risti | B5: Kiara Artha | C5: {=iferror(LET( kode, B5, actual, XLOOKUP(kode, Sales!A:A, Sales!C:C), target, XLOOKUP(kode, Sales!A:A, Sales!B:B), ratio, actual/target, skor, IFS( ratio>1, 5, ratio>=0.975, 4, ratio>=0.95, 3, ratio>=0.9, 2, TRUE, 1 ), skor ),0)} -> 5 | D5: {=iferror(LET( kode, B5, actual, XLOOKUP(kode, AVG!A:A, AVG!C:C), target, XLOOKUP(kode, AVG!A:A, AVG!B:B), ratio, actual/target, skor, IFS( ratio>1, 5, ratio>=0.975, 4, ratio>=0.95, 3, ratio>=0.9, 2, TRUE, 1 ), skor ),0)} -> 4 | E5: {=iferror(LET( kode, B5, large, XLOOKUP(kode, Large!A:A, Large!C:C), small, XLOOKUP(kode, Large!A:A, Large!B:B), ratio, large/(large+small), skor, IFS( ratio<0.45, 1, ratio<=0.5, 2, ratio<=0.55, 3, ratio<=0.6, 4, TRUE, 5 ), skor ),0)} -> 1 | F5: {=iferror(LET( kode, B5, oatmilk, XLOOKUP(kode, Oatside!A:A, Oatside!C:C), drink, XLOOKUP(kode, Oatside!A:A, Oatside!B:B), ratio, oatmilk/drink, skor, IFS( ratio>5%, 5, ratio>=4%, 4, ratio>=3%, 3, ratio>=2%, 2, TRUE, 1 ), skor ),0)} -> 5 | G5: {=iferror(LET( kode, B5, actual, XLOOKUP(kode, 'Snack Platter'!A:A, 'Snack Platter'!C:C), target, XLOOKUP(kode, 'Snack Platter'!A:A, 'Snack Platter'!B:B), ratio, actual/target, skor, IFS( ratio>10%, 5, ratio>=7.5%, 4, ratio>=5%, 3, ratio>=2.5%, 2, TRUE, 1 ), skor ),0)} -> 1 | H5: {=iferror(LET( kode, B5, actual, XLOOKUP(kode, 'Bundling Asik'!A:A, 'Bundling Asik'!C:C), target, XLOOKUP(kode, 'Bundling Asik'!A:A, 'Bundling Asik'!B:B), ratio, actual/target, skor, IFS( ratio>5%, 5, ratio>=4%, 4, ratio>=3%, 3, ratio>=2%, 2, TRUE, 1 ), skor ),0)} -> 2 | I5: {=iferror(LET( kode, B5, ratio, XLOOKUP(kode, Audit!A:A, Audit!B:B), skor, IFS( ratio>90, 5, ratio>=85, 4, ratio>=80, 3, ratio>=75, 2, TRUE, 1 ), skor ),0)} -> 4 | J5: {=iferror(LET( kode, B5, ratio, XLOOKUP(kode, 'Mistery Shopper'!A:A, 'Mistery Shopper'!B:B), skor, IFS( ratio>90%, 5, ratio>=85%, 4, ratio>=80%, 3, ratio>=75%, 2, TRUE, 1 ), skor ),0)} -> 5 | K5: {=iferror(LET( kode, B5, actual, XLOOKUP(kode, Complain!A:A, Complain!C:C), target, XLOOKUP(kode, Complain!A:A, Complain!B:B), ratio, actual/target, skor, IFS( ratio>=0.16%, 1, ratio>=0.15%, 2, ratio>=0.125%, 3, ratio>=0.1%, 4, TRUE, 5 ), skor ),0)} -> 5 | L5: =LET( nilai, C5:K5, bobot, {0.4,0.1,0.05,0.05,0.05,0.05,0.15,0.05,0.1}, SUMPRODUCT(nilai,bobot) )/5 -> 0.84 | N5: Bagas | O5: =averageif(A:A,N5,L:L) -> 0.5075
A6: Sohib | B6: Cimahi | C6: {=iferror(LET( kode, B6, actual, XLOOKUP(kode, Sales!A:A, Sales!C:C), target, XLOOKUP(kode, Sales!A:A, Sales!B:B), ratio, actual/target, skor, IFS( ratio>1, 5, ratio>=0.975, 4, ratio>=0.95, 3, ratio>=0.9, 2, TRUE, 1 ), skor ),0)} -> 4 | D6: {=iferror(LET( kode, B6, actual, XLOOKUP(kode, AVG!A:A, AVG!C:C), target, XLOOKUP(kode, AVG!A:A, AVG!B:B), ratio, actual/target, skor, IFS( ratio>1, 5, ratio>=0.975, 4, ratio>=0.95, 3, ratio>=0.9, 2, TRUE, 1 ), skor ),0)} -> 5 | E6: {=iferror(LET( kode, B6, large, XLOOKUP(kode, Large!A:A, Large!C:C), small, XLOOKUP(kode, Large!A:A, Large!B:B), ratio, large/(large+small), skor, IFS( ratio<0.45, 1, ratio<=0.5, 2, ratio<=0.55, 3, ratio<=0.6, 4, TRUE, 5 ), skor ),0)} -> 1 | F6: {=iferror(LET( kode, B6, oatmilk, XLOOKUP(kode, Oatside!A:A, Oatside!C:C), drink, XLOOKUP(kode, Oatside!A:A, Oatside!B:B), ratio, oatmilk/drink, skor, IFS( ratio>5%, 5, ratio>=4%, 4, ratio>=3%, 3, ratio>=2%, 2, TRUE, 1 ), skor ),0)} -> 5 | G6: {=iferror(LET( kode, B6, actual, XLOOKUP(kode, 'Snack Platter'!A:A, 'Snack Platter'!C:C), target, XLOOKUP(kode, 'Snack Platter'!A:A, 'Snack Platter'!B:B), ratio, actual/target, skor, IFS( ratio>10%, 5, ratio>=7.5%, 4, ratio>=5%, 3, ratio>=2.5%, 2, TRUE, 1 ), skor ),0)} -> 2 | H6: {=iferror(LET( kode, B6, actual, XLOOKUP(kode, 'Bundling Asik'!A:A, 'Bundling Asik'!C:C), target, XLOOKUP(kode, 'Bundling Asik'!A:A, 'Bundling Asik'!B:B), ratio, actual/target, skor, IFS( ratio>5%, 5, ratio>=4%, 4, ratio>=3%, 3, ratio>=2%, 2, TRUE, 1 ), skor ),0)} -> 1 | I6: {=iferror(LET( kode, B6, ratio, XLOOKUP(kode, Audit!A:A, Audit!B:B), skor, IFS( ratio>90, 5, ratio>=85, 4, ratio>=80, 3, ratio>=75, 2, TRUE, 1 ), skor ),0)} -> 3 | J6: {=iferror(LET( kode, B6, ratio, XLOOKUP(kode, 'Mistery Shopper'!A:A, 'Mistery Shopper'!B:B), skor, IFS( ratio>90%, 5, ratio>=85%, 4, ratio>=80%, 3, ratio>=75%, 2, TRUE, 1 ), skor ),0)} -> 5 | K6: {=iferror(LET( kode, B6, actual, XLOOKUP(kode, Complain!A:A, Complain!C:C), target, XLOOKUP(kode, Complain!A:A, Complain!B:B), ratio, actual/target, skor, IFS( ratio>=0.16%, 1, ratio>=0.15%, 2, ratio>=0.125%, 3, ratio>=0.1%, 4, TRUE, 5 ), skor ),0)} -> 5 | L6: =LET( nilai, C6:K6, bobot, {0.4,0.1,0.05,0.05,0.05,0.05,0.15,0.05,0.1}, SUMPRODUCT(nilai,bobot) )/5 -> 0.75 | N6: Ryan | O6: =averageif(A:A,N6,L:L) -> 0.455
A7: Risti | B7: Ujung Berung | C7: {=iferror(LET( kode, B7, actual, XLOOKUP(kode, Sales!A:A, Sales!C:C), target, XLOOKUP(kode, Sales!A:A, Sales!B:B), ratio, actual/target, skor, IFS( ratio>1, 5, ratio>=0.975, 4, ratio>=0.95, 3, ratio>=0.9, 2, TRUE, 1 ), skor ),0)} -> 3 | D7: {=iferror(LET( kode, B7, actual, XLOOKUP(kode, AVG!A:A, AVG!C:C), target, XLOOKUP(kode, AVG!A:A, AVG!B:B), ratio, actual/target, skor, IFS( ratio>1, 5, ratio>=0.975, 4, ratio>=0.95, 3, ratio>=0.9, 2, TRUE, 1 ), skor ),0)} -> 5 | E7: {=iferror(LET( kode, B7, large, XLOOKUP(kode, Large!A:A, Large!C:C), small, XLOOKUP(kode, Large!A:A, Large!B:B), ratio, large/(large+small), skor, IFS( ratio<0.45, 1, ratio<=0.5, 2, ratio<=0.55, 3, ratio<=0.6, 4, TRUE, 5 ), skor ),0)} -> 2 | F7: {=iferror(LET( kode, B7, oatmilk, XLOOKUP(kode, Oatside!A:A, Oatside!C:C), drink, XLOOKUP(kode, Oatside!A:A, Oatside!B:B), ratio, oatmilk/drink, skor, IFS( ratio>5%, 5, ratio>=4%, 4, ratio>=3%, 3, ratio>=2%, 2, TRUE, 1 ), skor ),0)} -> 5 | G7: {=iferror(LET( kode, B7, actual, XLOOKUP(kode, 'Snack Platter'!A:A, 'Snack Platter'!C:C), target, XLOOKUP(kode, 'Snack Platter'!A:A, 'Snack Platter'!B:B), ratio, actual/target, skor, IFS( ratio>10%, 5, ratio>=7.5%, 4, ratio>=5%, 3, ratio>=2.5%, 2, TRUE, 1 ), skor ),0)} -> 2 | H7: {=iferror(LET( kode, B7, actual, XLOOKUP(kode, 'Bundling Asik'!A:A, 'Bundling Asik'!C:C), target, XLOOKUP(kode, 'Bundling Asik'!A:A, 'Bundling Asik'!B:B), ratio, actual/target, skor, IFS( ratio>5%, 5, ratio>=4%, 4, ratio>=3%, 3, ratio>=2%, 2, TRUE, 1 ), skor ),0)} -> 2 | I7: {=iferror(LET( kode, B7, ratio, XLOOKUP(kode, Audit!A:A, Audit!B:B), skor, IFS( ratio>90, 5, ratio>=85, 4, ratio>=80, 3, ratio>=75, 2, TRUE, 1 ), skor ),0)} -> 4 | J7: {=iferror(LET( kode, B7, ratio, XLOOKUP(kode, 'Mistery Shopper'!A:A, 'Mistery Shopper'!B:B), skor, IFS( ratio>90%, 5, ratio>=85%, 4, ratio>=80%, 3, ratio>=75%, 2, TRUE, 1 ), skor ),0)} -> 5 | K7: {=iferror(LET( kode, B7, actual, XLOOKUP(kode, Complain!A:A, Complain!C:C), target, XLOOKUP(kode, Complain!A:A, Complain!B:B), ratio, actual/target, skor, IFS( ratio>=0.16%, 1, ratio>=0.15%, 2, ratio>=0.125%, 3, ratio>=0.1%, 4, TRUE, 5 ), skor ),0)} -> 3 | L7: =LET( nilai, C7:K7, bobot, {0.4,0.1,0.05,0.05,0.05,0.05,0.15,0.05,0.1}, SUMPRODUCT(nilai,bobot) )/5 -> 0.68 | N7: Ismail | O7: =averageif(A:A,N7,L:L) -> 0.325
A8: Sohib | B8: Peta | C8: {=iferror(LET( kode, B8, actual, XLOOKUP(kode, Sales!A:A, Sales!C:C), target, XLOOKUP(kode, Sales!A:A, Sales!B:B), ratio, actual/target, skor, IFS( ratio>1, 5, ratio>=0.975, 4, ratio>=0.95, 3, ratio>=0.9, 2, TRUE, 1 ), skor ),0)} -> 3 | D8: {=iferror(LET( kode, B8, actual, XLOOKUP(kode, AVG!A:A, AVG!C:C), target, XLOOKUP(kode, AVG!A:A, AVG!B:B), ratio, actual/target, skor, IFS( ratio>1, 5, ratio>=0.975, 4, ratio>=0.95, 3, ratio>=0.9, 2, TRUE, 1 ), skor ),0)} -> 4 | E8: {=iferror(LET( kode, B8, large, XLOOKUP(kode, Large!A:A, Large!C:C), small, XLOOKUP(kode, Large!A:A, Large!B:B), ratio, large/(large+small), skor, IFS( ratio<0.45, 1, ratio<=0.5, 2, ratio<=0.55, 3, ratio<=0.6, 4, TRUE, 5 ), skor ),0)} -> 1 | F8: {=iferror(LET( kode, B8, oatmilk, XLOOKUP(kode, Oatside!A:A, Oatside!C:C), drink, XLOOKUP(kode, Oatside!A:A, Oatside!B:B), ratio, oatmilk/drink, skor, IFS( ratio>5%, 5, ratio>=4%, 4, ratio>=3%, 3, ratio>=2%, 2, TRUE, 1 ), skor ),0)} -> 5 | G8: {=iferror(LET( kode, B8, actual, XLOOKUP(kode, 'Snack Platter'!A:A, 'Snack Platter'!C:C), target, XLOOKUP(kode, 'Snack Platter'!A:A, 'Snack Platter'!B:B), ratio, actual/target, skor, IFS( ratio>10%, 5, ratio>=7.5%, 4, ratio>=5%, 3, ratio>=2.5%, 2, TRUE, 1 ), skor ),0)} -> 2 | H8: {=iferror(LET( kode, B8, actual, XLOOKUP(kode, 'Bundling Asik'!A:A, 'Bundling Asik'!C:C), target, XLOOKUP(kode, 'Bundling Asik'!A:A, 'Bundling Asik'!B:B), ratio, actual/target, skor, IFS( ratio>5%, 5, ratio>=4%, 4, ratio>=3%, 3, ratio>=2%, 2, TRUE, 1 ), skor ),0)} -> 1 | I8: {=iferror(LET( kode, B8, ratio, XLOOKUP(kode, Audit!A:A, Audit!B:B), skor, IFS( ratio>90, 5, ratio>=85, 4, ratio>=80, 3, ratio>=75, 2, TRUE, 1 ), skor ),0)} -> 4 | J8: {=iferror(LET( kode, B8, ratio, XLOOKUP(kode, 'Mistery Shopper'!A:A, 'Mistery Shopper'!B:B), skor, IFS( ratio>90%, 5, ratio>=85%, 4, ratio>=80%, 3, ratio>=75%, 2, TRUE, 1 ), skor ),0)} -> 5 | K8: {=iferror(LET( kode, B8, actual, XLOOKUP(kode, Complain!A:A, Complain!C:C), target, XLOOKUP(kode, Complain!A:A, Complain!B:B), ratio, actual/target, skor, IFS( ratio>=0.16%, 1, ratio>=0.15%, 2, ratio>=0.125%, 3, ratio>=0.1%, 4, TRUE, 5 ), skor ),0)} -> 5 | L8: =LET( nilai, C8:K8, bobot, {0.4,0.1,0.05,0.05,0.05,0.05,0.15,0.05,0.1}, SUMPRODUCT(nilai,bobot) )/5 -> 0.68
A9: Bagas | B9: Kalimalang | C9: {=iferror(LET( kode, B9, actual, XLOOKUP(kode, Sales!A:A, Sales!C:C), target, XLOOKUP(kode, Sales!A:A, Sales!B:B), ratio, actual/target, skor, IFS( ratio>1, 5, ratio>=0.975, 4, ratio>=0.95, 3, ratio>=0.9, 2, TRUE, 1 ), skor ),0)} -> 4 | D9: {=iferror(LET( kode, B9, actual, XLOOKUP(kode, AVG!A:A, AVG!C:C), target, XLOOKUP(kode, AVG!A:A, AVG!B:B), ratio, actual/target, skor, IFS( ratio>1, 5, ratio>=0.975, 4, ratio>=0.95, 3, ratio>=0.9, 2, TRUE, 1 ), skor ),0)} -> 5 | E9: {=iferror(LET( kode, B9, large, XLOOKUP(kode, Large!A:A, Large!C:C), small, XLOOKUP(kode, Large!A:A, Large!B:B), ratio, large/(large+small), skor, IFS( ratio<0.45, 1, ratio<=0.5, 2, ratio<=0.55, 3, ratio<=0.6, 4, TRUE, 5 ), skor ),0)} -> 1 | F9: {=iferror(LET( kode, B9, oatmilk, XLOOKUP(kode, Oatside!A:A, Oatside!C:C), drink, XLOOKUP(kode, Oatside!A:A, Oatside!B:B), ratio, oatmilk/drink, skor, IFS( ratio>5%, 5, ratio>=4%, 4, ratio>=3%, 3, ratio>=2%, 2, TRUE, 1 ), skor ),0)} -> 1 | G9: {=iferror(LET( kode, B9, actual, XLOOKUP(kode, 'Snack Platter'!A:A, 'Snack Platter'!C:C), target, XLOOKUP(kode, 'Snack Platter'!A:A, 'Snack Platter'!B:B), ratio, actual/target, skor, IFS( ratio>10%, 5, ratio>=7.5%, 4, ratio>=5%, 3, ratio>=2.5%, 2, TRUE, 1 ), skor ),0)} -> 1 | H9: {=iferror(LET( kode, B9, actual, XLOOKUP(kode, 'Bundling Asik'!A:A, 'Bundling Asik'!C:C), target, XLOOKUP(kode, 'Bundling Asik'!A:A, 'Bundling Asik'!B:B), ratio, actual/target, skor, IFS( ratio>5%, 5, ratio>=4%, 4, ratio>=3%, 3, ratio>=2%, 2, TRUE, 1 ), skor ),0)} -> 1 | I9: {=iferror(LET( kode, B9, ratio, XLOOKUP(kode, Audit!A:A, Audit!B:B), skor, IFS( ratio>90, 5, ratio>=85, 4, ratio>=80, 3, ratio>=75, 2, TRUE, 1 ), skor ),0)} -> 3 | J9: {=iferror(LET( kode, B9, ratio, XLOOKUP(kode, 'Mistery Shopper'!A:A, 'Mistery Shopper'!B:B), skor, IFS( ratio>90%, 5, ratio>=85%, 4, ratio>=80%, 3, ratio>=75%, 2, TRUE, 1 ), skor ),0)} -> 5 | K9: {=iferror(LET( kode, B9, actual, XLOOKUP(kode, Complain!A:A, Complain!C:C), target, XLOOKUP(kode, Complain!A:A, Complain!B:B), ratio, actual/target, skor, IFS( ratio>=0.16%, 1, ratio>=0.15%, 2, ratio>=0.125%, 3, ratio>=0.1%, 4, TRUE, 5 ), skor ),0)} -> 4 | L9: =LET( nilai, C9:K9, bobot, {0.4,0.1,0.05,0.05,0.05,0.05,0.15,0.05,0.1}, SUMPRODUCT(nilai,bobot) )/5 -> 0.68
A10: Ryan | B10: Ciledug | C10: {=iferror(LET( kode, B10, actual, XLOOKUP(kode, Sales!A:A, Sales!C:C), target, XLOOKUP(kode, Sales!A:A, Sales!B:B), ratio, actual/target, skor, IFS( ratio>1, 5, ratio>=0.975, 4, ratio>=0.95, 3, ratio>=0.9, 2, TRUE, 1 ), skor ),0)} -> 4 | D10: {=iferror(LET( kode, B10, actual, XLOOKUP(kode, AVG!A:A, AVG!C:C), target, XLOOKUP(kode, AVG!A:A, AVG!B:B), ratio, actual/target, skor, IFS( ratio>1, 5, ratio>=0.975, 4, ratio>=0.95, 3, ratio>=0.9, 2, TRUE, 1 ), skor ),0)} -> 5 | E10: {=iferror(LET( kode, B10, large, XLOOKUP(kode, Large!A:A, Large!C:C), small, XLOOKUP(kode, Large!A:A, Large!B:B), ratio, large/(large+small), skor, IFS( ratio<0.45, 1, ratio<=0.5, 2, ratio<=0.55, 3, ratio<=0.6, 4, TRUE, 5 ), skor ),0)} -> 1 | F10: {=iferror(LET( kode, B10, oatmilk, XLOOKUP(kode, Oatside!A:A, Oatside!C:C), drink, XLOOKUP(kode, Oatside!A:A, Oatside!B:B), ratio, oatmilk/drink, skor, IFS( ratio>5%, 5, ratio>=4%, 4, ratio>=3%, 3, ratio>=2%, 2, TRUE, 1 ), skor ),0)} -> 1 | G10: {=iferror(LET( kode, B10, actual, XLOOKUP(kode, 'Snack Platter'!A:A, 'Snack Platter'!C:C), target, XLOOKUP(kode, 'Snack Platter'!A:A, 'Snack Platter'!B:B), ratio, actual/target, skor, IFS( ratio>10%, 5, ratio>=7.5%, 4, ratio>=5%, 3, ratio>=2.5%, 2, TRUE, 1 ), skor ),0)} -> 1 | H10: {=iferror(LET( kode, B10, actual, XLOOKUP(kode, 'Bundling Asik'!A:A, 'Bundling Asik'!C:C), target, XLOOKUP(kode, 'Bundling Asik'!A:A, 'Bundling Asik'!B:B), ratio, actual/target, skor, IFS( ratio>5%, 5, ratio>=4%, 4, ratio>=3%, 3, ratio>=2%, 2, TRUE, 1 ), skor ),0)} -> 1 | I10: {=iferror(LET( kode, B10, ratio, XLOOKUP(kode, Audit!A:A, Audit!B:B), skor, IFS( ratio>90, 5, ratio>=85, 4, ratio>=80, 3, ratio>=75, 2, TRUE, 1 ), skor ),0)} -> 2 | J10: {=iferror(LET( kode, B10, ratio, XLOOKUP(kode, 'Mistery Shopper'!A:A, 'Mistery Shopper'!B:B), skor, IFS( ratio>90%, 5, ratio>=85%, 4, ratio>=80%, 3, ratio>=75%, 2, TRUE, 1 ), skor ),0)} -> 5 | K10: {=iferror(LET( kode, B10, actual, XLOOKUP(kode, Complain!A:A, Complain!C:C), target, XLOOKUP(kode, Complain!A:A, Complain!B:B), ratio, actual/target, skor, IFS( ratio>=0.16%, 1, ratio>=0.15%, 2, ratio>=0.125%, 3, ratio>=0.1%, 4, TRUE, 5 ), skor ),0)} -> 5 | L10: =LET( nilai, C10:K10, bobot, {0.4,0.1,0.05,0.05,0.05,0.05,0.15,0.05,0.1}, SUMPRODUCT(nilai,bobot) )/5 -> 0.67
A11: Sohib | B11: Melong | C11: {=iferror(LET( kode, B11, actual, XLOOKUP(kode, Sales!A:A, Sales!C:C), target, XLOOKUP(kode, Sales!A:A, Sales!B:B), ratio, actual/target, skor, IFS( ratio>1, 5, ratio>=0.975, 4, ratio>=0.95, 3, ratio>=0.9, 2, TRUE, 1 ), skor ),0)} -> 4 | D11: {=iferror(LET( kode, B11, actual, XLOOKUP(kode, AVG!A:A, AVG!C:C), target, XLOOKUP(kode, AVG!A:A, AVG!B:B), ratio, actual/target, skor, IFS( ratio>1, 5, ratio>=0.975, 4, ratio>=0.95, 3, ratio>=0.9, 2, TRUE, 1 ), skor ),0)} -> 1 | E11: {=iferror(LET( kode, B11, large, XLOOKUP(kode, Large!A:A, Large!C:C), small, XLOOKUP(kode, Large!A:A, Large!B:B), ratio, large/(large+small), skor, IFS( ratio<0.45, 1, ratio<=0.5, 2, ratio<=0.55, 3, ratio<=0.6, 4, TRUE, 5 ), skor ),0)} -> 1 | F11: {=iferror(LET( kode, B11, oatmilk, XLOOKUP(kode, Oatside!A:A, Oatside!C:C), drink, XLOOKUP(kode, Oatside!A:A, Oatside!B:B), ratio, oatmilk/drink, skor, IFS( ratio>5%, 5, ratio>=4%, 4, ratio>=3%, 3, ratio>=2%, 2, TRUE, 1 ), skor ),0)} -> 5 | G11: {=iferror(LET( kode, B11, actual, XLOOKUP(kode, 'Snack Platter'!A:A, 'Snack Platter'!C:C), target, XLOOKUP(kode, 'Snack Platter'!A:A, 'Snack Platter'!B:B), ratio, actual/target, skor, IFS( ratio>10%, 5, ratio>=7.5%, 4, ratio>=5%, 3, ratio>=2.5%, 2, TRUE, 1 ), skor ),0)} -> 1 | H11: {=iferror(LET( kode, B11, actual, XLOOKUP(kode, 'Bundling Asik'!A:A, 'Bundling Asik'!C:C), target, XLOOKUP(kode, 'Bundling Asik'!A:A, 'Bundling Asik'!B:B), ratio, actual/target, skor, IFS( ratio>5%, 5, ratio>=4%, 4, ratio>=3%, 3, ratio>=2%, 2, TRUE, 1 ), skor ),0)} -> 1 | I11: {=iferror(LET( kode, B11, ratio, XLOOKUP(kode, Audit!A:A, Audit!B:B), skor, IFS( ratio>90, 5, ratio>=85, 4, ratio>=80, 3, ratio>=75, 2, TRUE, 1 ), skor ),0)} -> 3 | J11: {=iferror(LET( kode, B11, ratio, XLOOKUP(kode, 'Mistery Shopper'!A:A, 'Mistery Shopper'!B:B), skor, IFS( ratio>90%, 5, ratio>=85%, 4, ratio>=80%, 3, ratio>=75%, 2, TRUE, 1 ), skor ),0)} -> 5 | K11: {=iferror(LET( kode, B11, actual, XLOOKUP(kode, Complain!A:A, Complain!C:C), target, XLOOKUP(kode, Complain!A:A, Complain!B:B), ratio, actual/target, skor, IFS( ratio>=0.16%, 1, ratio>=0.15%, 2, ratio>=0.125%, 3, ratio>=0.1%, 4, TRUE, 5 ), skor ),0)} -> 5 | L11: =LET( nilai, C11:K11, bobot, {0.4,0.1,0.05,0.05,0.05,0.05,0.15,0.05,0.1}, SUMPRODUCT(nilai,bobot) )/5 -> 0.66
A12: Bagas | B12: Lebak Bulus | C12: {=iferror(LET( kode, B12, actual, XLOOKUP(kode, Sales!A:A, Sales!C:C), target, XLOOKUP(kode, Sales!A:A, Sales!B:B), ratio, actual/target, skor, IFS( ratio>1, 5, ratio>=0.975, 4, ratio>=0.95, 3, ratio>=0.9, 2, TRUE, 1 ), skor ),0)} -> 3 | D12: {=iferror(LET( kode, B12, actual, XLOOKUP(kode, AVG!A:A, AVG!C:C), target, XLOOKUP(kode, AVG!A:A, AVG!B:B), ratio, actual/target, skor, IFS( ratio>1, 5, ratio>=0.975, 4, ratio>=0.95, 3, ratio>=0.9, 2, TRUE, 1 ), skor ),0)} -> 2 | E12: {=iferror(LET( kode, B12, large, XLOOKUP(kode, Large!A:A, Large!C:C), small, XLOOKUP(kode, Large!A:A, Large!B:B), ratio, large/(large+small), skor, IFS( ratio<0.45, 1, ratio<=0.5, 2, ratio<=0.55, 3, ratio<=0.6, 4, TRUE, 5 ), skor ),0)} -> 2 | F12: {=iferror(LET( kode, B12, oatmilk, XLOOKUP(kode, Oatside!A:A, Oatside!C:C), drink, XLOOKUP(kode, Oatside!A:A, Oatside!B:B), ratio, oatmilk/drink, skor, IFS( ratio>5%, 5, ratio>=4%, 4, ratio>=3%, 3, ratio>=2%, 2, TRUE, 1 ), skor ),0)} -> 5 | G12: {=iferror(LET( kode, B12, actual, XLOOKUP(kode, 'Snack Platter'!A:A, 'Snack Platter'!C:C), target, XLOOKUP(kode, 'Snack Platter'!A:A, 'Snack Platter'!B:B), ratio, actual/target, skor, IFS( ratio>10%, 5, ratio>=7.5%, 4, ratio>=5%, 3, ratio>=2.5%, 2, TRUE, 1 ), skor ),0)} -> 1 | H12: {=iferror(LET( kode, B12, actual, XLOOKUP(kode, 'Bundling Asik'!A:A, 'Bundling Asik'!C:C), target, XLOOKUP(kode, 'Bundling Asik'!A:A, 'Bundling Asik'!B:B), ratio, actual/target, skor, IFS( ratio>5%, 5, ratio>=4%, 4, ratio>=3%, 3, ratio>=2%, 2, TRUE, 1 ), skor ),0)} -> 1 | I12: {=iferror(LET( kode, B12, ratio, XLOOKUP(kode, Audit!A:A, Audit!B:B), skor, IFS( ratio>90, 5, ratio>=85, 4, ratio>=80, 3, ratio>=75, 2, TRUE, 1 ), skor ),0)} -> 3 | J12: {=iferror(LET( kode, B12, ratio, XLOOKUP(kode, 'Mistery Shopper'!A:A, 'Mistery Shopper'!B:B), skor, IFS( ratio>90%, 5, ratio>=85%, 4, ratio>=80%, 3, ratio>=75%, 2, TRUE, 1 ), skor ),0)} -> 5 | K12: {=iferror(LET( kode, B12, actual, XLOOKUP(kode, Complain!A:A, Complain!C:C), target, XLOOKUP(kode, Complain!A:A, Complain!B:B), ratio, actual/target, skor, IFS( ratio>=0.16%, 1, ratio>=0.15%, 2, ratio>=0.125%, 3, ratio>=0.1%, 4, TRUE, 5 ), skor ),0)} -> 5 | L12: =LET( nilai, C12:K12, bobot, {0.4,0.1,0.05,0.05,0.05,0.05,0.15,0.05,0.1}, SUMPRODUCT(nilai,bobot) )/5 -> 0.61
A13: Nadine | B13: Pekayon | C13: {=iferror(LET( kode, B13, actual, XLOOKUP(kode, Sales!A:A, Sales!C:C), target, XLOOKUP(kode, Sales!A:A, Sales!B:B), ratio, actual/target, skor, IFS( ratio>1, 5, ratio>=0.975, 4, ratio>=0.95, 3, ratio>=0.9, 2, TRUE, 1 ), skor ),0)} -> 2 | D13: {=iferror(LET( kode, B13, actual, XLOOKUP(kode, AVG!A:A, AVG!C:C), target, XLOOKUP(kode, AVG!A:A, AVG!B:B), ratio, actual/target, skor, IFS( ratio>1, 5, ratio>=0.975, 4, ratio>=0.95, 3, ratio>=0.9, 2, TRUE, 1 ), skor ),0)} -> 5 | E13: {=iferror(LET( kode, B13, large, XLOOKUP(kode, Large!A:A, Large!C:C), small, XLOOKUP(kode, Large!A:A, Large!B:B), ratio, large/(large+small), skor, IFS( ratio<0.45, 1, ratio<=0.5, 2, ratio<=0.55, 3, ratio<=0.6, 4, TRUE, 5 ), skor ),0)} -> 2 | F13: {=iferror(LET( kode, B13, oatmilk, XLOOKUP(kode, Oatside!A:A, Oatside!C:C), drink, XLOOKUP(kode, Oatside!A:A, Oatside!B:B), ratio, oatmilk/drink, skor, IFS( ratio>5%, 5, ratio>=4%, 4, ratio>=3%, 3, ratio>=2%, 2, TRUE, 1 ), skor ),0)} -> 1 | G13: {=iferror(LET( kode, B13, actual, XLOOKUP(kode, 'Snack Platter'!A:A, 'Snack Platter'!C:C), target, XLOOKUP(kode, 'Snack Platter'!A:A, 'Snack Platter'!B:B), ratio, actual/target, skor, IFS( ratio>10%, 5, ratio>=7.5%, 4, ratio>=5%, 3, ratio>=2.5%, 2, TRUE, 1 ), skor ),0)} -> 2 | H13: {=iferror(LET( kode, B13, actual, XLOOKUP(kode, 'Bundling Asik'!A:A, 'Bundling Asik'!C:C), target, XLOOKUP(kode, 'Bundling Asik'!A:A, 'Bundling Asik'!B:B), ratio, actual/target, skor, IFS( ratio>5%, 5, ratio>=4%, 4, ratio>=3%, 3, ratio>=2%, 2, TRUE, 1 ), skor ),0)} -> 2 | I13: {=iferror(LET( kode, B13, ratio, XLOOKUP(kode, Audit!A:A, Audit!B:B), skor, IFS( ratio>90, 5, ratio>=85, 4, ratio>=80, 3, ratio>=75, 2, TRUE, 1 ), skor ),0)} -> 3 | J13: {=iferror(LET( kode, B13, ratio, XLOOKUP(kode, 'Mistery Shopper'!A:A, 'Mistery Shopper'!B:B), skor, IFS( ratio>90%, 5, ratio>=85%, 4, ratio>=80%, 3, ratio>=75%, 2, TRUE, 1 ), skor ),0)} -> 5 | K13: {=iferror(LET( kode, B13, actual, XLOOKUP(kode, Complain!A:A, Complain!C:C), target, XLOOKUP(kode, Complain!A:A, Complain!B:B), ratio, actual/target, skor, IFS( ratio>=0.16%, 1, ratio>=0.15%, 2, ratio>=0.125%, 3, ratio>=0.1%, 4, TRUE, 5 ), skor ),0)} -> 5 | L13: =LET( nilai, C13:K13, bobot, {0.4,0.1,0.05,0.05,0.05,0.05,0.15,0.05,0.1}, SUMPRODUCT(nilai,bobot) )/5 -> 0.57
A14: Bagas | B14: Setu Cipayung | C14: {=iferror(LET( kode, B14, actual, XLOOKUP(kode, Sales!A:A, Sales!C:C), target, XLOOKUP(kode, Sales!A:A, Sales!B:B), ratio, actual/target, skor, IFS( ratio>1, 5, ratio>=0.975, 4, ratio>=0.95, 3, ratio>=0.9, 2, TRUE, 1 ), skor ),0)} -> 2 | D14: {=iferror(LET( kode, B14, actual, XLOOKUP(kode, AVG!A:A, AVG!C:C), target, XLOOKUP(kode, AVG!A:A, AVG!B:B), ratio, actual/target, skor, IFS( ratio>1, 5, ratio>=0.975, 4, ratio>=0.95, 3, ratio>=0.9, 2, TRUE, 1 ), skor ),0)} -> 4 | E14: {=iferror(LET( kode, B14, large, XLOOKUP(kode, Large!A:A, Large!C:C), small, XLOOKUP(kode, Large!A:A, Large!B:B), ratio, large/(large+small), skor, IFS( ratio<0.45, 1, ratio<=0.5, 2, ratio<=0.55, 3, ratio<=0.6, 4, TRUE, 5 ), skor ),0)} -> 1 | F14: {=iferror(LET( kode, B14, oatmilk, XLOOKUP(kode, Oatside!A:A, Oatside!C:C), drink, XLOOKUP(kode, Oatside!A:A, Oatside!B:B), ratio, oatmilk/drink, skor, IFS( ratio>5%, 5, ratio>=4%, 4, ratio>=3%, 3, ratio>=2%, 2, TRUE, 1 ), skor ),0)} -> 4 | G14: {=iferror(LET( kode, B14, actual, XLOOKUP(kode, 'Snack Platter'!A:A, 'Snack Platter'!C:C), target, XLOOKUP(kode, 'Snack Platter'!A:A, 'Snack Platter'!B:B), ratio, actual/target, skor, IFS( ratio>10%, 5, ratio>=7.5%, 4, ratio>=5%, 3, ratio>=2.5%, 2, TRUE, 1 ), skor ),0)} -> 2 | H14: {=iferror(LET( kode, B14, actual, XLOOKUP(kode, 'Bundling Asik'!A:A, 'Bundling Asik'!C:C), target, XLOOKUP(kode, 'Bundling Asik'!A:A, 'Bundling Asik'!B:B), ratio, actual/target, skor, IFS( ratio>5%, 5, ratio>=4%, 4, ratio>=3%, 3, ratio>=2%, 2, TRUE, 1 ), skor ),0)} -> 1 | I14: {=iferror(LET( kode, B14, ratio, XLOOKUP(kode, Audit!A:A, Audit!B:B), skor, IFS( ratio>90, 5, ratio>=85, 4, ratio>=80, 3, ratio>=75, 2, TRUE, 1 ), skor ),0)} -> 3 | J14: {=iferror(LET( kode, B14, ratio, XLOOKUP(kode, 'Mistery Shopper'!A:A, 'Mistery Shopper'!B:B), skor, IFS( ratio>90%, 5, ratio>=85%, 4, ratio>=80%, 3, ratio>=75%, 2, TRUE, 1 ), skor ),0)} -> 5 | K14: {=iferror(LET( kode, B14, actual, XLOOKUP(kode, Complain!A:A, Complain!C:C), target, XLOOKUP(kode, Complain!A:A, Complain!B:B), ratio, actual/target, skor, IFS( ratio>=0.16%, 1, ratio>=0.15%, 2, ratio>=0.125%, 3, ratio>=0.1%, 4, TRUE, 5 ), skor ),0)} -> 5 | L14: =LET( nilai, C14:K14, bobot, {0.4,0.1,0.05,0.05,0.05,0.05,0.15,0.05,0.1}, SUMPRODUCT(nilai,bobot) )/5 -> 0.56
A15: Nadine | B15: Lenteng Agung | C15: {=iferror(LET( kode, B15, actual, XLOOKUP(kode, Sales!A:A, Sales!C:C), target, XLOOKUP(kode, Sales!A:A, Sales!B:B), ratio, actual/target, skor, IFS( ratio>1, 5, ratio>=0.975, 4, ratio>=0.95, 3, ratio>=0.9, 2, TRUE, 1 ), skor ),0)} -> 2 | D15: {=iferror(LET( kode, B15, actual, XLOOKUP(kode, AVG!A:A, AVG!C:C), target, XLOOKUP(kode, AVG!A:A, AVG!B:B), ratio, actual/target, skor, IFS( ratio>1, 5, ratio>=0.975, 4, ratio>=0.95, 3, ratio>=0.9, 2, TRUE, 1 ), skor ),0)} -> 2 | E15: {=iferror(LET( kode, B15, large, XLOOKUP(kode, Large!A:A, Large!C:C), small, XLOOKUP(kode, Large!A:A, Large!B:B), ratio, large/(large+small), skor, IFS( ratio<0.45, 1, ratio<=0.5, 2, ratio<=0.55, 3, ratio<=0.6, 4, TRUE, 5 ), skor ),0)} -> 1 | F15: {=iferror(LET( kode, B15, oatmilk, XLOOKUP(kode, Oatside!A:A, Oatside!C:C), drink, XLOOKUP(kode, Oatside!A:A, Oatside!B:B), ratio, oatmilk/drink, skor, IFS( ratio>5%, 5, ratio>=4%, 4, ratio>=3%, 3, ratio>=2%, 2, TRUE, 1 ), skor ),0)} -> 5 | G15: {=iferror(LET( kode, B15, actual, XLOOKUP(kode, 'Snack Platter'!A:A, 'Snack Platter'!C:C), target, XLOOKUP(kode, 'Snack Platter'!A:A, 'Snack Platter'!B:B), ratio, actual/target, skor, IFS( ratio>10%, 5, ratio>=7.5%, 4, ratio>=5%, 3, ratio>=2.5%, 2, TRUE, 1 ), skor ),0)} -> 2 | H15: {=iferror(LET( kode, B15, actual, XLOOKUP(kode, 'Bundling Asik'!A:A, 'Bundling Asik'!C:C), target, XLOOKUP(kode, 'Bundling Asik'!A:A, 'Bundling Asik'!B:B), ratio, actual/target, skor, IFS( ratio>5%, 5, ratio>=4%, 4, ratio>=3%, 3, ratio>=2%, 2, TRUE, 1 ), skor ),0)} -> 1 | I15: {=iferror(LET( kode, B15, ratio, XLOOKUP(kode, Audit!A:A, Audit!B:B), skor, IFS( ratio>90, 5, ratio>=85, 4, ratio>=80, 3, ratio>=75, 2, TRUE, 1 ), skor ),0)} -> 4 | J15: {=iferror(LET( kode, B15, ratio, XLOOKUP(kode, 'Mistery Shopper'!A:A, 'Mistery Shopper'!B:B), skor, IFS( ratio>90%, 5, ratio>=85%, 4, ratio>=80%, 3, ratio>=75%, 2, TRUE, 1 ), skor ),0)} -> 5 | K15: {=iferror(LET( kode, B15, actual, XLOOKUP(kode, Complain!A:A, Complain!C:C), target, XLOOKUP(kode, Complain!A:A, Complain!B:B), ratio, actual/target, skor, IFS( ratio>=0.16%, 1, ratio>=0.15%, 2, ratio>=0.125%, 3, ratio>=0.1%, 4, TRUE, 5 ), skor ),0)} -> 5 | L15: =LET( nilai, C15:K15, bobot, {0.4,0.1,0.05,0.05,0.05,0.05,0.15,0.05,0.1}, SUMPRODUCT(nilai,bobot) )/5 -> 0.56
A16: Risti | B16: Jatinangor | C16: {=iferror(LET( kode, B16, actual, XLOOKUP(kode, Sales!A:A, Sales!C:C), target, XLOOKUP(kode, Sales!A:A, Sales!B:B), ratio, actual/target, skor, IFS( ratio>1, 5, ratio>=0.975, 4, ratio>=0.95, 3, ratio>=0.9, 2, TRUE, 1 ), skor ),0)} -> 1 | D16: {=iferror(LET( kode, B16, actual, XLOOKUP(kode, AVG!A:A, AVG!C:C), target, XLOOKUP(kode, AVG!A:A, AVG!B:B), ratio, actual/target, skor, IFS( ratio>1, 5, ratio>=0.975, 4, ratio>=0.95, 3, ratio>=0.9, 2, TRUE, 1 ), skor ),0)} -> 5 | E16: {=iferror(LET( kode, B16, large, XLOOKUP(kode, Large!A:A, Large!C:C), small, XLOOKUP(kode, Large!A:A, Large!B:B), ratio, large/(large+small), skor, IFS( ratio<0.45, 1, ratio<=0.5, 2, ratio<=0.55, 3, ratio<=0.6, 4, TRUE, 5 ), skor ),0)} -> 1 | F16: {=iferror(LET( kode, B16, oatmilk, XLOOKUP(kode, Oatside!A:A, Oatside!C:C), drink, XLOOKUP(kode, Oatside!A:A, Oatside!B:B), ratio, oatmilk/drink, skor, IFS( ratio>5%, 5, ratio>=4%, 4, ratio>=3%, 3, ratio>=2%, 2, TRUE, 1 ), skor ),0)} -> 5 | G16: {=iferror(LET( kode, B16, actual, XLOOKUP(kode, 'Snack Platter'!A:A, 'Snack Platter'!C:C), target, XLOOKUP(kode, 'Snack Platter'!A:A, 'Snack Platter'!B:B), ratio, actual/target, skor, IFS( ratio>10%, 5, ratio>=7.5%, 4, ratio>=5%, 3, ratio>=2.5%, 2, TRUE, 1 ), skor ),0)} -> 2 | H16: {=iferror(LET( kode, B16, actual, XLOOKUP(kode, 'Bundling Asik'!A:A, 'Bundling Asik'!C:C), target, XLOOKUP(kode, 'Bundling Asik'!A:A, 'Bundling Asik'!B:B), ratio, actual/target, skor, IFS( ratio>5%, 5, ratio>=4%, 4, ratio>=3%, 3, ratio>=2%, 2, TRUE, 1 ), skor ),0)} -> 2 | I16: {=iferror(LET( kode, B16, ratio, XLOOKUP(kode, Audit!A:A, Audit!B:B), skor, IFS( ratio>90, 5, ratio>=85, 4, ratio>=80, 3, ratio>=75, 2, TRUE, 1 ), skor ),0)} -> 4 | J16: {=iferror(LET( kode, B16, ratio, XLOOKUP(kode, 'Mistery Shopper'!A:A, 'Mistery Shopper'!B:B), skor, IFS( ratio>90%, 5, ratio>=85%, 4, ratio>=80%, 3, ratio>=75%, 2, TRUE, 1 ), skor ),0)} -> 5 | K16: {=iferror(LET( kode, B16, actual, XLOOKUP(kode, Complain!A:A, Complain!C:C), target, XLOOKUP(kode, Complain!A:A, Complain!B:B), ratio, actual/target, skor, IFS( ratio>=0.16%, 1, ratio>=0.15%, 2, ratio>=0.125%, 3, ratio>=0.1%, 4, TRUE, 5 ), skor ),0)} -> 5 | L16: =LET( nilai, C16:K16, bobot, {0.4,0.1,0.05,0.05,0.05,0.05,0.15,0.05,0.1}, SUMPRODUCT(nilai,bobot) )/5 -> 0.55
A17: Bagas | B17: Pengumben | C17: {=iferror(LET( kode, B17, actual, XLOOKUP(kode, Sales!A:A, Sales!C:C), target, XLOOKUP(kode, Sales!A:A, Sales!B:B), ratio, actual/target, skor, IFS( ratio>1, 5, ratio>=0.975, 4, ratio>=0.95, 3, ratio>=0.9, 2, TRUE, 1 ), skor ),0)} -> 1 | D17: {=iferror(LET( kode, B17, actual, XLOOKUP(kode, AVG!A:A, AVG!C:C), target, XLOOKUP(kode, AVG!A:A, AVG!B:B), ratio, actual/target, skor, IFS( ratio>1, 5, ratio>=0.975, 4, ratio>=0.95, 3, ratio>=0.9, 2, TRUE, 1 ), skor ),0)} -> 5 | E17: {=iferror(LET( kode, B17, large, XLOOKUP(kode, Large!A:A, Large!C:C), small, XLOOKUP(kode, Large!A:A, Large!B:B), ratio, large/(large+small), skor, IFS( ratio<0.45, 1, ratio<=0.5, 2, ratio<=0.55, 3, ratio<=0.6, 4, TRUE, 5 ), skor ),0)} -> 2 | F17: {=iferror(LET( kode, B17, oatmilk, XLOOKUP(kode, Oatside!A:A, Oatside!C:C), drink, XLOOKUP(kode, Oatside!A:A, Oatside!B:B), ratio, oatmilk/drink, skor, IFS( ratio>5%, 5, ratio>=4%, 4, ratio>=3%, 3, ratio>=2%, 2, TRUE, 1 ), skor ),0)} -> 5 | G17: {=iferror(LET( kode, B17, actual, XLOOKUP(kode, 'Snack Platter'!A:A, 'Snack Platter'!C:C), target, XLOOKUP(kode, 'Snack Platter'!A:A, 'Snack Platter'!B:B), ratio, actual/target, skor, IFS( ratio>10%, 5, ratio>=7.5%, 4, ratio>=5%, 3, ratio>=2.5%, 2, TRUE, 1 ), skor ),0)} -> 2 | H17: {=iferror(LET( kode, B17, actual, XLOOKUP(kode, 'Bundling Asik'!A:A, 'Bundling Asik'!C:C), target, XLOOKUP(kode, 'Bundling Asik'!A:A, 'Bundling Asik'!B:B), ratio, actual/target, skor, IFS( ratio>5%, 5, ratio>=4%, 4, ratio>=3%, 3, ratio>=2%, 2, TRUE, 1 ), skor ),0)} -> 1 | I17: {=iferror(LET( kode, B17, ratio, XLOOKUP(kode, Audit!A:A, Audit!B:B), skor, IFS( ratio>90, 5, ratio>=85, 4, ratio>=80, 3, ratio>=75, 2, TRUE, 1 ), skor ),0)} -> 4 | J17: {=iferror(LET( kode, B17, ratio, XLOOKUP(kode, 'Mistery Shopper'!A:A, 'Mistery Shopper'!B:B), skor, IFS( ratio>90%, 5, ratio>=85%, 4, ratio>=80%, 3, ratio>=75%, 2, TRUE, 1 ), skor ),0)} -> 5 | K17: {=iferror(LET( kode, B17, actual, XLOOKUP(kode, Complain!A:A, Complain!C:C), target, XLOOKUP(kode, Complain!A:A, Complain!B:B), ratio, actual/target, skor, IFS( ratio>=0.16%, 1, ratio>=0.15%, 2, ratio>=0.125%, 3, ratio>=0.1%, 4, TRUE, 5 ), skor ),0)} -> 4 | L17: =LET( nilai, C17:K17, bobot, {0.4,0.1,0.05,0.05,0.05,0.05,0.15,0.05,0.1}, SUMPRODUCT(nilai,bobot) )/5 -> 0.53
A18: Nadine | B18: Margonda | C18: {=iferror(LET( kode, B18, actual, XLOOKUP(kode, Sales!A:A, Sales!C:C), target, XLOOKUP(kode, Sales!A:A, Sales!B:B), ratio, actual/target, skor, IFS( ratio>1, 5, ratio>=0.975, 4, ratio>=0.95, 3, ratio>=0.9, 2, TRUE, 1 ), skor ),0)} -> 2 | D18: {=iferror(LET( kode, B18, actual, XLOOKUP(kode, AVG!A:A, AVG!C:C), target, XLOOKUP(kode, AVG!A:A, AVG!B:B), ratio, actual/target, skor, IFS( ratio>1, 5, ratio>=0.975, 4, ratio>=0.95, 3, ratio>=0.9, 2, TRUE, 1 ), skor ),0)} -> 2 | E18: {=iferror(LET( kode, B18, large, XLOOKUP(kode, Large!A:A, Large!C:C), small, XLOOKUP(kode, Large!A:A, Large!B:B), ratio, large/(large+small), skor, IFS( ratio<0.45, 1, ratio<=0.5, 2, ratio<=0.55, 3, ratio<=0.6, 4, TRUE, 5 ), skor ),0)} -> 1 | F18: {=iferror(LET( kode, B18, oatmilk, XLOOKUP(kode, Oatside!A:A, Oatside!C:C), drink, XLOOKUP(kode, Oatside!A:A, Oatside!B:B), ratio, oatmilk/drink, skor, IFS( ratio>5%, 5, ratio>=4%, 4, ratio>=3%, 3, ratio>=2%, 2, TRUE, 1 ), skor ),0)} -> 3 | G18: {=iferror(LET( kode, B18, actual, XLOOKUP(kode, 'Snack Platter'!A:A, 'Snack Platter'!C:C), target, XLOOKUP(kode, 'Snack Platter'!A:A, 'Snack Platter'!B:B), ratio, actual/target, skor, IFS( ratio>10%, 5, ratio>=7.5%, 4, ratio>=5%, 3, ratio>=2.5%, 2, TRUE, 1 ), skor ),0)} -> 2 | H18: {=iferror(LET( kode, B18, actual, XLOOKUP(kode, 'Bundling Asik'!A:A, 'Bundling Asik'!C:C), target, XLOOKUP(kode, 'Bundling Asik'!A:A, 'Bundling Asik'!B:B), ratio, actual/target, skor, IFS( ratio>5%, 5, ratio>=4%, 4, ratio>=3%, 3, ratio>=2%, 2, TRUE, 1 ), skor ),0)} -> 2 | I18: {=iferror(LET( kode, B18, ratio, XLOOKUP(kode, Audit!A:A, Audit!B:B), skor, IFS( ratio>90, 5, ratio>=85, 4, ratio>=80, 3, ratio>=75, 2, TRUE, 1 ), skor ),0)} -> 3 | J18: {=iferror(LET( kode, B18, ratio, XLOOKUP(kode, 'Mistery Shopper'!A:A, 'Mistery Shopper'!B:B), skor, IFS( ratio>90%, 5, ratio>=85%, 4, ratio>=80%, 3, ratio>=75%, 2, TRUE, 1 ), skor ),0)} -> 5 | K18: {=iferror(LET( kode, B18, actual, XLOOKUP(kode, Complain!A:A, Complain!C:C), target, XLOOKUP(kode, Complain!A:A, Complain!B:B), ratio, actual/target, skor, IFS( ratio>=0.16%, 1, ratio>=0.15%, 2, ratio>=0.125%, 3, ratio>=0.1%, 4, TRUE, 5 ), skor ),0)} -> 5 | L18: =LET( nilai, C18:K18, bobot, {0.4,0.1,0.05,0.05,0.05,0.05,0.15,0.05,0.1}, SUMPRODUCT(nilai,bobot) )/5 -> 0.52
A19: Risti | B19: Buah Batu | C19: {=iferror(LET( kode, B19, actual, XLOOKUP(kode, Sales!A:A, Sales!C:C), target, XLOOKUP(kode, Sales!A:A, Sales!B:B), ratio, actual/target, skor, IFS( ratio>1, 5, ratio>=0.975, 4, ratio>=0.95, 3, ratio>=0.9, 2, TRUE, 1 ), skor ),0)} -> 2 | D19: {=iferror(LET( kode, B19, actual, XLOOKUP(kode, AVG!A:A, AVG!C:C), target, XLOOKUP(kode, AVG!A:A, AVG!B:B), ratio, actual/target, skor, IFS( ratio>1, 5, ratio>=0.975, 4, ratio>=0.95, 3, ratio>=0.9, 2, TRUE, 1 ), skor ),0)} -> 5 | E19: {=iferror(LET( kode, B19, large, XLOOKUP(kode, Large!A:A, Large!C:C), small, XLOOKUP(kode, Large!A:A, Large!B:B), ratio, large/(large+small), skor, IFS( ratio<0.45, 1, ratio<=0.5, 2, ratio<=0.55, 3, ratio<=0.6, 4, TRUE, 5 ), skor ),0)} -> 1 | F19: {=iferror(LET( kode, B19, oatmilk, XLOOKUP(kode, Oatside!A:A, Oatside!C:C), drink, XLOOKUP(kode, Oatside!A:A, Oatside!B:B), ratio, oatmilk/drink, skor, IFS( ratio>5%, 5, ratio>=4%, 4, ratio>=3%, 3, ratio>=2%, 2, TRUE, 1 ), skor ),0)} -> 5 | G19: {=iferror(LET( kode, B19, actual, XLOOKUP(kode, 'Snack Platter'!A:A, 'Snack Platter'!C:C), target, XLOOKUP(kode, 'Snack Platter'!A:A, 'Snack Platter'!B:B), ratio, actual/target, skor, IFS( ratio>10%, 5, ratio>=7.5%, 4, ratio>=5%, 3, ratio>=2.5%, 2, TRUE, 1 ), skor ),0)} -> 1 | H19: {=iferror(LET( kode, B19, actual, XLOOKUP(kode, 'Bundling Asik'!A:A, 'Bundling Asik'!C:C), target, XLOOKUP(kode, 'Bundling Asik'!A:A, 'Bundling Asik'!B:B), ratio, actual/target, skor, IFS( ratio>5%, 5, ratio>=4%, 4, ratio>=3%, 3, ratio>=2%, 2, TRUE, 1 ), skor ),0)} -> 1 | I19: {=iferror(LET( kode, B19, ratio, XLOOKUP(kode, Audit!A:A, Audit!B:B), skor, IFS( ratio>90, 5, ratio>=85, 4, ratio>=80, 3, ratio>=75, 2, TRUE, 1 ), skor ),0)} -> 1 | J19: {=iferror(LET( kode, B19, ratio, XLOOKUP(kode, 'Mistery Shopper'!A:A, 'Mistery Shopper'!B:B), skor, IFS( ratio>90%, 5, ratio>=85%, 4, ratio>=80%, 3, ratio>=75%, 2, TRUE, 1 ), skor ),0)} -> 5 | K19: {=iferror(LET( kode, B19, actual, XLOOKUP(kode, Complain!A:A, Complain!C:C), target, XLOOKUP(kode, Complain!A:A, Complain!B:B), ratio, actual/target, skor, IFS( ratio>=0.16%, 1, ratio>=0.15%, 2, ratio>=0.125%, 3, ratio>=0.1%, 4, TRUE, 5 ), skor ),0)} -> 5 | L19: =LET( nilai, C19:K19, bobot, {0.4,0.1,0.05,0.05,0.05,0.05,0.15,0.05,0.1}, SUMPRODUCT(nilai,bobot) )/5 -> 0.52
... A31: Ismail | B31: Citraland | C31: {=iferror(LET( kode, B31, actual, XLOOKUP(kode, Sales!A:A, Sales!C:C), target, XLOOKUP(kode, Sales!A:A, Sales!B:B), ratio, actual/target, skor, IFS( ratio>1, 5, ratio>=0.975, 4, ratio>=0.95, 3, ratio>=0.9, 2, TRUE, 1 ), skor ),0)} -> 1 | D31: {=iferror(LET( kode, B31, actual, XLOOKUP(kode, AVG!A:A, AVG!C:C), target, XLOOKUP(kode, AVG!A:A, AVG!B:B), ratio, actual/target, skor, IFS( ratio>1, 5, ratio>=0.975, 4, ratio>=0.95, 3, ratio>=0.9, 2, TRUE, 1 ), skor ),0)} -> 1 | E31: {=iferror(LET( kode, B31, large, XLOOKUP(kode, Large!A:A, Large!C:C), small, XLOOKUP(kode, Large!A:A, Large!B:B), ratio, large/(large+small), skor, IFS( ratio<0.45, 1, ratio<=0.5, 2, ratio<=0.55, 3, ratio<=0.6, 4, TRUE, 5 ), skor ),0)} -> 1 | F31: {=iferror(LET( kode, B31, oatmilk, XLOOKUP(kode, Oatside!A:A, Oatside!C:C), drink, XLOOKUP(kode, Oatside!A:A, Oatside!B:B), ratio, oatmilk/drink, skor, IFS( ratio>5%, 5, ratio>=4%, 4, ratio>=3%, 3, ratio>=2%, 2, TRUE, 1 ), skor ),0)} -> 1 | G31: {=iferror(LET( kode, B31, actual, XLOOKUP(kode, 'Snack Platter'!A:A, 'Snack Platter'!C:C), target, XLOOKUP(kode, 'Snack Platter'!A:A, 'Snack Platter'!B:B), ratio, actual/target, skor, IFS( ratio>10%, 5, ratio>=7.5%, 4, ratio>=5%, 3, ratio>=2.5%, 2, TRUE, 1 ), skor ),0)} -> 1 | H31: {=iferror(LET( kode, B31, actual, XLOOKUP(kode, 'Bundling Asik'!A:A, 'Bundling Asik'!C:C), target, XLOOKUP(kode, 'Bundling Asik'!A:A, 'Bundling Asik'!B:B), ratio, actual/target, skor, IFS( ratio>5%, 5, ratio>=4%, 4, ratio>=3%, 3, ratio>=2%, 2, TRUE, 1 ), skor ),0)} -> 1 | I31: {=iferror(LET( kode, B31, ratio, XLOOKUP(kode, Audit!A:A, Audit!B:B), skor, IFS( ratio>90, 5, ratio>=85, 4, ratio>=80, 3, ratio>=75, 2, TRUE, 1 ), skor ),0)} -> 1 | J31: {=iferror(LET( kode, B31, ratio, XLOOKUP(kode, 'Mistery Shopper'!A:A, 'Mistery Shopper'!B:B), skor, IFS( ratio>90%, 5, ratio>=85%, 4, ratio>=80%, 3, ratio>=75%, 2, TRUE, 1 ), skor ),0)} -> 5 | K31: {=iferror(LET( kode, B31, actual, XLOOKUP(kode, Complain!A:A, Complain!C:C), target, XLOOKUP(kode, Complain!A:A, Complain!B:B), ratio, actual/target, skor, IFS( ratio>=0.16%, 1, ratio>=0.15%, 2, ratio>=0.125%, 3, ratio>=0.1%, 4, TRUE, 5 ), skor ),0)} -> 4 | L31: =LET( nilai, C31:K31, bobot, {0.4,0.1,0.05,0.05,0.05,0.05,0.15,0.05,0.1}, SUMPRODUCT(nilai,bobot) )/5 -> 0.3

Sheet Feb
B1: Store | C1: Net Sales | D1: AVG | E1: Large | F1: Oatside | G1: Add On Telur | H1: B. Asik | I1: Audit | J1: M. Shopper | K1: Complain | L1: Total | N1: Orang | O1: Score
A2: Risti | B2: Ujung Berung | C2: {=iferror(LET(kode, B2, actual, XLOOKUP(kode, Sales!A:A, Sales!E:E),target, XLOOKUP(kode, Sales!A:A, Sales!D:D),ratio, actual/target,skor, IFS(ratio>1, 5,ratio>=0.975, 4,ratio>=0.95, 3,ratio>=0.9, 2,TRUE, 1),skor),0)} -> 5 | D2: {=iferror(LET( kode, B2, actual, XLOOKUP(kode, AVG!A:A, AVG!E:E), target, XLOOKUP(kode, AVG!A:A, AVG!D:D), ratio, actual/target, skor, IFS( ratio>1, 5, ratio>=0.975, 4, ratio>=0.95, 3, ratio>=0.9, 2, TRUE, 1 ), skor ),0)} -> 5 | E2: {=iferror(LET( kode, B2, large, XLOOKUP(kode, Large!A:A, Large!E:E), small, XLOOKUP(kode, Large!A:A, Large!D:D), ratio, large/(large+small), skor, IFS( ratio<0.45, 1, ratio<=0.5, 2, ratio<=0.55, 3, ratio<=0.6, 4, TRUE, 5 ), skor ),0)} -> 2 | F2: {=iferror(LET( kode, B2, oatmilk, XLOOKUP(kode, Oatside!A:A, Oatside!E:E), drink, XLOOKUP(kode, Oatside!A:A, Oatside!D:D), ratio, oatmilk/drink, skor, IFS( ratio>5%, 5, ratio>=4%, 4, ratio>=3%, 3, ratio>=2%, 2, TRUE, 1 ), skor ),0)} -> 5 | G2: {=iferror(LET( kode, B2, actual, XLOOKUP(kode, 'Snack Platter'!A:A, 'Snack Platter'!E:E), target, XLOOKUP(kode, 'Snack Platter'!A:A, 'Snack Platter'!D:D), ratio, actual/target, skor, IFS( ratio>10%, 5, ratio>=7.5%, 4, ratio>=5%, 3, ratio>=2.5%, 2, TRUE, 1 ), skor ),0)} -> 5 | H2: {=iferror(LET( kode, B2, actual, XLOOKUP(kode, 'Bundling Asik'!A:A, 'Bundling Asik'!E:E), target, XLOOKUP(kode, 'Bundling Asik'!A:A, 'Bundling Asik'!D:D), ratio, actual/target, skor, IFS( ratio>5%, 5, ratio>=4%, 4, ratio>=3%, 3, ratio>=2%, 2, TRUE, 1 ), skor ),0)} -> 3 | I2: {=iferror(LET( kode, B2, ratio, XLOOKUP(kode, Audit!A:A, Audit!C:C), skor, IFS( ratio>90, 5, ratio>=85, 4, ratio>=80, 3, ratio>=75, 2, TRUE, 1 ), skor ),0)} -> 4 | J2: {=iferror(LET( kode, B2, ratio, XLOOKUP(kode, 'Mistery Shopper'!A:A, 'Mistery Shopper'!C:C), skor, IFS( ratio>90%, 5, ratio>=85%, 4, ratio>=80%, 3, ratio>=75%, 2, TRUE, 1 ), skor ),0)} -> 5 | K2: {=iferror(LET( kode, B2, actual, XLOOKUP(kode, Complain!A:A, Complain!E:E), target, XLOOKUP(kode, Complain!A:A, Complain!D:D), ratio, actual/target, skor, IFS( ratio>=0.16%, 1, ratio>=0.15%, 2, ratio>=0.125%, 3, ratio>=0.1%, 4, TRUE, 5 ), skor ),0)} -> 5 | L2: =LET( nilai, C2:K2, bobot, {0.4,0.1,0.05,0.05,0.05,0.05,0.15,0.05,0.1}, SUMPRODUCT(nilai,bobot) )/5 -> 0.92 | N2: Risti | O2: =averageif(A:A,N2,L:L) -> 0.696
A3: Sohib | B3: Cimahi | C3: {=iferror(LET(kode, B3, actual, XLOOKUP(kode, Sales!A:A, Sales!E:E),target, XLOOKUP(kode, Sales!A:A, Sales!D:D),ratio, actual/target,skor, IFS(ratio>1, 5,ratio>=0.975, 4,ratio>=0.95, 3,ratio>=0.9, 2,TRUE, 1),skor),0)} -> 5 | D3: {=iferror(LET( kode, B3, actual, XLOOKUP(kode, AVG!A:A, AVG!E:E), target, XLOOKUP(kode, AVG!A:A, AVG!D:D), ratio, actual/target, skor, IFS( ratio>1, 5, ratio>=0.975, 4, ratio>=0.95, 3, ratio>=0.9, 2, TRUE, 1 ), skor ),0)} -> 5 | E3: {=iferror(LET( kode, B3, large, XLOOKUP(kode, Large!A:A, Large!E:E), small, XLOOKUP(kode, Large!A:A, Large!D:D), ratio, large/(large+small), skor, IFS( ratio<0.45, 1, ratio<=0.5, 2, ratio<=0.55, 3, ratio<=0.6, 4, TRUE, 5 ), skor ),0)} -> 1 | F3: {=iferror(LET( kode, B3, oatmilk, XLOOKUP(kode, Oatside!A:A, Oatside!E:E), drink, XLOOKUP(kode, Oatside!A:A, Oatside!D:D), ratio, oatmilk/drink, skor, IFS( ratio>5%, 5, ratio>=4%, 4, ratio>=3%, 3, ratio>=2%, 2, TRUE, 1 ), skor ),0)} -> 5 | G3: {=iferror(LET( kode, B3, actual, XLOOKUP(kode, 'Snack Platter'!A:A, 'Snack Platter'!E:E), target, XLOOKUP(kode, 'Snack Platter'!A:A, 'Snack Platter'!D:D), ratio, actual/target, skor, IFS( ratio>10%, 5, ratio>=7.5%, 4, ratio>=5%, 3, ratio>=2.5%, 2, TRUE, 1 ), skor ),0)} -> 2 | H3: {=iferror(LET( kode, B3, actual, XLOOKUP(kode, 'Bundling Asik'!A:A, 'Bundling Asik'!E:E), target, XLOOKUP(kode, 'Bundling Asik'!A:A, 'Bundling Asik'!D:D), ratio, actual/target, skor, IFS( ratio>5%, 5, ratio>=4%, 4, ratio>=3%, 3, ratio>=2%, 2, TRUE, 1 ), skor ),0)} -> 2 | I3: {=iferror(LET( kode, B3, ratio, XLOOKUP(kode, Audit!A:A, Audit!C:C), skor, IFS( ratio>90, 5, ratio>=85, 4, ratio>=80, 3, ratio>=75, 2, TRUE, 1 ), skor ),0)} -> 4 | J3: {=iferror(LET( kode, B3, ratio, XLOOKUP(kode, 'Mistery Shopper'!A:A, 'Mistery Shopper'!C:C), skor, IFS( ratio>90%, 5, ratio>=85%, 4, ratio>=80%, 3, ratio>=75%, 2, TRUE, 1 ), skor ),0)} -> 5 | K3: {=iferror(LET( kode, B3, actual, XLOOKUP(kode, Complain!A:A, Complain!E:E), target, XLOOKUP(kode, Complain!A:A, Complain!D:D), ratio, actual/target, skor, IFS( ratio>=0.16%, 1, ratio>=0.15%, 2, ratio>=0.125%, 3, ratio>=0.1%, 4, TRUE, 5 ), skor ),0)} -> 5 | L3: =LET( nilai, C3:K3, bobot, {0.4,0.1,0.05,0.05,0.05,0.05,0.15,0.05,0.1}, SUMPRODUCT(nilai,bobot) )/5 -> 0.87 | N3: Nadine | O3: =averageif(A:A,N3,L:L) -> 0.676
A4: Nadine | B4: Lenteng Agung | C4: {=iferror(LET(kode, B4, actual, XLOOKUP(kode, Sales!A:A, Sales!E:E),target, XLOOKUP(kode, Sales!A:A, Sales!D:D),ratio, actual/target,skor, IFS(ratio>1, 5,ratio>=0.975, 4,ratio>=0.95, 3,ratio>=0.9, 2,TRUE, 1),skor),0)} -> 4 | D4: {=iferror(LET( kode, B4, actual, XLOOKUP(kode, AVG!A:A, AVG!E:E), target, XLOOKUP(kode, AVG!A:A, AVG!D:D), ratio, actual/target, skor, IFS( ratio>1, 5, ratio>=0.975, 4, ratio>=0.95, 3, ratio>=0.9, 2, TRUE, 1 ), skor ),0)} -> 3 | E4: {=iferror(LET( kode, B4, large, XLOOKUP(kode, Large!A:A, Large!E:E), small, XLOOKUP(kode, Large!A:A, Large!D:D), ratio, large/(large+small), skor, IFS( ratio<0.45, 1, ratio<=0.5, 2, ratio<=0.55, 3, ratio<=0.6, 4, TRUE, 5 ), skor ),0)} -> 5 | F4: {=iferror(LET( kode, B4, oatmilk, XLOOKUP(kode, Oatside!A:A, Oatside!E:E), drink, XLOOKUP(kode, Oatside!A:A, Oatside!D:D), ratio, oatmilk/drink, skor, IFS( ratio>5%, 5, ratio>=4%, 4, ratio>=3%, 3, ratio>=2%, 2, TRUE, 1 ), skor ),0)} -> 5 | G4: {=iferror(LET( kode, B4, actual, XLOOKUP(kode, 'Snack Platter'!A:A, 'Snack Platter'!E:E), target, XLOOKUP(kode, 'Snack Platter'!A:A, 'Snack Platter'!D:D), ratio, actual/target, skor, IFS( ratio>10%, 5, ratio>=7.5%, 4, ratio>=5%, 3, ratio>=2.5%, 2, TRUE, 1 ), skor ),0)} -> 5 | H4: {=iferror(LET( kode, B4, actual, XLOOKUP(kode, 'Bundling Asik'!A:A, 'Bundling Asik'!E:E), target, XLOOKUP(kode, 'Bundling Asik'!A:A, 'Bundling Asik'!D:D), ratio, actual/target, skor, IFS( ratio>5%, 5, ratio>=4%, 4, ratio>=3%, 3, ratio>=2%, 2, TRUE, 1 ), skor ),0)} -> 3 | I4: {=iferror(LET( kode, B4, ratio, XLOOKUP(kode, Audit!A:A, Audit!C:C), skor, IFS( ratio>90, 5, ratio>=85, 4, ratio>=80, 3, ratio>=75, 2, TRUE, 1 ), skor ),0)} -> 5 | J4: {=iferror(LET( kode, B4, ratio, XLOOKUP(kode, 'Mistery Shopper'!A:A, 'Mistery Shopper'!C:C), skor, IFS( ratio>90%, 5, ratio>=85%, 4, ratio>=80%, 3, ratio>=75%, 2, TRUE, 1 ), skor ),0)} -> 5 | K4: {=iferror(LET( kode, B4, actual, XLOOKUP(kode, Complain!A:A, Complain!E:E), target, XLOOKUP(kode, Complain!A:A, Complain!D:D), ratio, actual/target, skor, IFS( ratio>=0.16%, 1, ratio>=0.15%, 2, ratio>=0.125%, 3, ratio>=0.1%, 4, TRUE, 5 ), skor ),0)} -> 5 | L4: =LET( nilai, C4:K4, bobot, {0.4,0.1,0.05,0.05,0.05,0.05,0.15,0.05,0.1}, SUMPRODUCT(nilai,bobot) )/5 -> 0.86 | N4: Sohib | O4: =averageif(A:A,N4,L:L) -> 0.6875
A5: Risti | B5: Metro | C5: {=iferror(LET(kode, B5, actual, XLOOKUP(kode, Sales!A:A, Sales!E:E),target, XLOOKUP(kode, Sales!A:A, Sales!D:D),ratio, actual/target,skor, IFS(ratio>1, 5,ratio>=0.975, 4,ratio>=0.95, 3,ratio>=0.9, 2,TRUE, 1),skor),0)} -> 5 | D5: {=iferror(LET( kode, B5, actual, XLOOKUP(kode, AVG!A:A, AVG!E:E), target, XLOOKUP(kode, AVG!A:A, AVG!D:D), ratio, actual/target, skor, IFS( ratio>1, 5, ratio>=0.975, 4, ratio>=0.95, 3, ratio>=0.9, 2, TRUE, 1 ), skor ),0)} -> 2 | E5: {=iferror(LET( kode, B5, large, XLOOKUP(kode, Large!A:A, Large!E:E), small, XLOOKUP(kode, Large!A:A, Large!D:D), ratio, large/(large+small), skor, IFS( ratio<0.45, 1, ratio<=0.5, 2, ratio<=0.55, 3, ratio<=0.6, 4, TRUE, 5 ), skor ),0)} -> 1 | F5: {=iferror(LET( kode, B5, oatmilk, XLOOKUP(kode, Oatside!A:A, Oatside!E:E), drink, XLOOKUP(kode, Oatside!A:A, Oatside!D:D), ratio, oatmilk/drink, skor, IFS( ratio>5%, 5, ratio>=4%, 4, ratio>=3%, 3, ratio>=2%, 2, TRUE, 1 ), skor ),0)} -> 5 | G5: {=iferror(LET( kode, B5, actual, XLOOKUP(kode, 'Snack Platter'!A:A, 'Snack Platter'!E:E), target, XLOOKUP(kode, 'Snack Platter'!A:A, 'Snack Platter'!D:D), ratio, actual/target, skor, IFS( ratio>10%, 5, ratio>=7.5%, 4, ratio>=5%, 3, ratio>=2.5%, 2, TRUE, 1 ), skor ),0)} -> 2 | H5: {=iferror(LET( kode, B5, actual, XLOOKUP(kode, 'Bundling Asik'!A:A, 'Bundling Asik'!E:E), target, XLOOKUP(kode, 'Bundling Asik'!A:A, 'Bundling Asik'!D:D), ratio, actual/target, skor, IFS( ratio>5%, 5, ratio>=4%, 4, ratio>=3%, 3, ratio>=2%, 2, TRUE, 1 ), skor ),0)} -> 3 | I5: {=iferror(LET( kode, B5, ratio, XLOOKUP(kode, Audit!A:A, Audit!C:C), skor, IFS( ratio>90, 5, ratio>=85, 4, ratio>=80, 3, ratio>=75, 2, TRUE, 1 ), skor ),0)} -> 4 | J5: {=iferror(LET( kode, B5, ratio, XLOOKUP(kode, 'Mistery Shopper'!A:A, 'Mistery Shopper'!C:C), skor, IFS( ratio>90%, 5, ratio>=85%, 4, ratio>=80%, 3, ratio>=75%, 2, TRUE, 1 ), skor ),0)} -> 5 | K5: {=iferror(LET( kode, B5, actual, XLOOKUP(kode, Complain!A:A, Complain!E:E), target, XLOOKUP(kode, Complain!A:A, Complain!D:D), ratio, actual/target, skor, IFS( ratio>=0.16%, 1, ratio>=0.15%, 2, ratio>=0.125%, 3, ratio>=0.1%, 4, TRUE, 5 ), skor ),0)} -> 5 | L5: =LET( nilai, C5:K5, bobot, {0.4,0.1,0.05,0.05,0.05,0.05,0.15,0.05,0.1}, SUMPRODUCT(nilai,bobot) )/5 -> 0.82 | N5: Bagas | O5: =averageif(A:A,N5,L:L) -> 0.455
A6: Nadine | B6: Margonda | C6: {=iferror(LET(kode, B6, actual, XLOOKUP(kode, Sales!A:A, Sales!E:E),target, XLOOKUP(kode, Sales!A:A, Sales!D:D),ratio, actual/target,skor, IFS(ratio>1, 5,ratio>=0.975, 4,ratio>=0.95, 3,ratio>=0.9, 2,TRUE, 1),skor),0)} -> 4 | D6: {=iferror(LET( kode, B6, actual, XLOOKUP(kode, AVG!A:A, AVG!E:E), target, XLOOKUP(kode, AVG!A:A, AVG!D:D), ratio, actual/target, skor, IFS( ratio>1, 5, ratio>=0.975, 4, ratio>=0.95, 3, ratio>=0.9, 2, TRUE, 1 ), skor ),0)} -> 4 | E6: {=iferror(LET( kode, B6, large, XLOOKUP(kode, Large!A:A, Large!E:E), small, XLOOKUP(kode, Large!A:A, Large!D:D), ratio, large/(large+small), skor, IFS( ratio<0.45, 1, ratio<=0.5, 2, ratio<=0.55, 3, ratio<=0.6, 4, TRUE, 5 ), skor ),0)} -> 1 | F6: {=iferror(LET( kode, B6, oatmilk, XLOOKUP(kode, Oatside!A:A, Oatside!E:E), drink, XLOOKUP(kode, Oatside!A:A, Oatside!D:D), ratio, oatmilk/drink, skor, IFS( ratio>5%, 5, ratio>=4%, 4, ratio>=3%, 3, ratio>=2%, 2, TRUE, 1 ), skor ),0)} -> 5 | G6: {=iferror(LET( kode, B6, actual, XLOOKUP(kode, 'Snack Platter'!A:A, 'Snack Platter'!E:E), target, XLOOKUP(kode, 'Snack Platter'!A:A, 'Snack Platter'!D:D), ratio, actual/target, skor, IFS( ratio>10%, 5, ratio>=7.5%, 4, ratio>=5%, 3, ratio>=2.5%, 2, TRUE, 1 ), skor ),0)} -> 3 | H6: {=iferror(LET( kode, B6, actual, XLOOKUP(kode, 'Bundling Asik'!A:A, 'Bundling Asik'!E:E), target, XLOOKUP(kode, 'Bundling Asik'!A:A, 'Bundling Asik'!D:D), ratio, actual/target, skor, IFS( ratio>5%, 5, ratio>=4%, 4, ratio>=3%, 3, ratio>=2%, 2, TRUE, 1 ), skor ),0)} -> 5 | I6: {=iferror(LET( kode, B6, ratio, XLOOKUP(kode, Audit!A:A, Audit!C:C), skor, IFS( ratio>90, 5, ratio>=85, 4, ratio>=80, 3, ratio>=75, 2, TRUE, 1 ), skor ),0)} -> 3 | J6: {=iferror(LET( kode, B6, ratio, XLOOKUP(kode, 'Mistery Shopper'!A:A, 'Mistery Shopper'!C:C), skor, IFS( ratio>90%, 5, ratio>=85%, 4, ratio>=80%, 3, ratio>=75%, 2, TRUE, 1 ), skor ),0)} -> 5 | K6: {=iferror(LET( kode, B6, actual, XLOOKUP(kode, Complain!A:A, Complain!E:E), target, XLOOKUP(kode, Complain!A:A, Complain!D:D), ratio, actual/target, skor, IFS( ratio>=0.16%, 1, ratio>=0.15%, 2, ratio>=0.125%, 3, ratio>=0.1%, 4, TRUE, 5 ), skor ),0)} -> 5 | L6: =LET( nilai, C6:K6, bobot, {0.4,0.1,0.05,0.05,0.05,0.05,0.15,0.05,0.1}, SUMPRODUCT(nilai,bobot) )/5 -> 0.78 | N6: Ryan | O6: =averageif(A:A,N6,L:L) -> 0.43
A7: Sohib | B7: Melong | C7: {=iferror(LET(kode, B7, actual, XLOOKUP(kode, Sales!A:A, Sales!E:E),target, XLOOKUP(kode, Sales!A:A, Sales!D:D),ratio, actual/target,skor, IFS(ratio>1, 5,ratio>=0.975, 4,ratio>=0.95, 3,ratio>=0.9, 2,TRUE, 1),skor),0)} -> 5 | D7: {=iferror(LET( kode, B7, actual, XLOOKUP(kode, AVG!A:A, AVG!E:E), target, XLOOKUP(kode, AVG!A:A, AVG!D:D), ratio, actual/target, skor, IFS( ratio>1, 5, ratio>=0.975, 4, ratio>=0.95, 3, ratio>=0.9, 2, TRUE, 1 ), skor ),0)} -> 1 | E7: {=iferror(LET( kode, B7, large, XLOOKUP(kode, Large!A:A, Large!E:E), small, XLOOKUP(kode, Large!A:A, Large!D:D), ratio, large/(large+small), skor, IFS( ratio<0.45, 1, ratio<=0.5, 2, ratio<=0.55, 3, ratio<=0.6, 4, TRUE, 5 ), skor ),0)} -> 1 | F7: {=iferror(LET( kode, B7, oatmilk, XLOOKUP(kode, Oatside!A:A, Oatside!E:E), drink, XLOOKUP(kode, Oatside!A:A, Oatside!D:D), ratio, oatmilk/drink, skor, IFS( ratio>5%, 5, ratio>=4%, 4, ratio>=3%, 3, ratio>=2%, 2, TRUE, 1 ), skor ),0)} -> 5 | G7: {=iferror(LET( kode, B7, actual, XLOOKUP(kode, 'Snack Platter'!A:A, 'Snack Platter'!E:E), target, XLOOKUP(kode, 'Snack Platter'!A:A, 'Snack Platter'!D:D), ratio, actual/target, skor, IFS( ratio>10%, 5, ratio>=7.5%, 4, ratio>=5%, 3, ratio>=2.5%, 2, TRUE, 1 ), skor ),0)} -> 1 | H7: {=iferror(LET( kode, B7, actual, XLOOKUP(kode, 'Bundling Asik'!A:A, 'Bundling Asik'!E:E), target, XLOOKUP(kode, 'Bundling Asik'!A:A, 'Bundling Asik'!D:D), ratio, actual/target, skor, IFS( ratio>5%, 5, ratio>=4%, 4, ratio>=3%, 3, ratio>=2%, 2, TRUE, 1 ), skor ),0)} -> 4 | I7: {=iferror(LET( kode, B7, ratio, XLOOKUP(kode, Audit!A:A, Audit!C:C), skor, IFS( ratio>90, 5, ratio>=85, 4, ratio>=80, 3, ratio>=75, 2, TRUE, 1 ), skor ),0)} -> 3 | J7: {=iferror(LET( kode, B7, ratio, XLOOKUP(kode, 'Mistery Shopper'!A:A, 'Mistery Shopper'!C:C), skor, IFS( ratio>90%, 5, ratio>=85%, 4, ratio>=80%, 3, ratio>=75%, 2, TRUE, 1 ), skor ),0)} -> 5 | K7: {=iferror(LET( kode, B7, actual, XLOOKUP(kode, Complain!A:A, Complain!E:E), target, XLOOKUP(kode, Complain!A:A, Complain!D:D), ratio, actual/target, skor, IFS( ratio>=0.16%, 1, ratio>=0.15%, 2, ratio>=0.125%, 3, ratio>=0.1%, 4, TRUE, 5 ), skor ),0)} -> 5 | L7: =LET( nilai, C7:K7, bobot, {0.4,0.1,0.05,0.05,0.05,0.05,0.15,0.05,0.1}, SUMPRODUCT(nilai,bobot) )/5 -> 0.77 | N7: Ismail | O7: =averageif(A:A,N7,L:L) -> 0.385
A8: Nadine | B8: Kranggan | C8: {=iferror(LET(kode, B8, actual, XLOOKUP(kode, Sales!A:A, Sales!E:E),target, XLOOKUP(kode, Sales!A:A, Sales!D:D),ratio, actual/target,skor, IFS(ratio>1, 5,ratio>=0.975, 4,ratio>=0.95, 3,ratio>=0.9, 2,TRUE, 1),skor),0)} -> 1 | D8: {=iferror(LET( kode, B8, actual, XLOOKUP(kode, AVG!A:A, AVG!E:E), target, XLOOKUP(kode, AVG!A:A, AVG!D:D), ratio, actual/target, skor, IFS( ratio>1, 5, ratio>=0.975, 4, ratio>=0.95, 3, ratio>=0.9, 2, TRUE, 1 ), skor ),0)} -> 5 | E8: {=iferror(LET( kode, B8, large, XLOOKUP(kode, Large!A:A, Large!E:E), small, XLOOKUP(kode, Large!A:A, Large!D:D), ratio, large/(large+small), skor, IFS( ratio<0.45, 1, ratio<=0.5, 2, ratio<=0.55, 3, ratio<=0.6, 4, TRUE, 5 ), skor ),0)} -> 5 | F8: {=iferror(LET( kode, B8, oatmilk, XLOOKUP(kode, Oatside!A:A, Oatside!E:E), drink, XLOOKUP(kode, Oatside!A:A, Oatside!D:D), ratio, oatmilk/drink, skor, IFS( ratio>5%, 5, ratio>=4%, 4, ratio>=3%, 3, ratio>=2%, 2, TRUE, 1 ), skor ),0)} -> 5 | G8: {=iferror(LET( kode, B8, actual, XLOOKUP(kode, 'Snack Platter'!A:A, 'Snack Platter'!E:E), target, XLOOKUP(kode, 'Snack Platter'!A:A, 'Snack Platter'!D:D), ratio, actual/target, skor, IFS( ratio>10%, 5, ratio>=7.5%, 4, ratio>=5%, 3, ratio>=2.5%, 2, TRUE, 1 ), skor ),0)} -> 5 | H8: {=iferror(LET( kode, B8, actual, XLOOKUP(kode, 'Bundling Asik'!A:A, 'Bundling Asik'!E:E), target, XLOOKUP(kode, 'Bundling Asik'!A:A, 'Bundling Asik'!D:D), ratio, actual/target, skor, IFS( ratio>5%, 5, ratio>=4%, 4, ratio>=3%, 3, ratio>=2%, 2, TRUE, 1 ), skor ),0)} -> 4 | I8: {=iferror(LET( kode, B8, ratio, XLOOKUP(kode, Audit!A:A, Audit!C:C), skor, IFS( ratio>90, 5, ratio>=85, 4, ratio>=80, 3, ratio>=75, 2, TRUE, 1 ), skor ),0)} -> 4 | J8: {=iferror(LET( kode, B8, ratio, XLOOKUP(kode, 'Mistery Shopper'!A:A, 'Mistery Shopper'!C:C), skor, IFS( ratio>90%, 5, ratio>=85%, 4, ratio>=80%, 3, ratio>=75%, 2, TRUE, 1 ), skor ),0)} -> 5 | K8: {=iferror(LET( kode, B8, actual, XLOOKUP(kode, Complain!A:A, Complain!E:E), target, XLOOKUP(kode, Complain!A:A, Complain!D:D), ratio, actual/target, skor, IFS( ratio>=0.16%, 1, ratio>=0.15%, 2, ratio>=0.125%, 3, ratio>=0.1%, 4, TRUE, 5 ), skor ),0)} -> 5 | L8: =LET( nilai, C8:K8, bobot, {0.4,0.1,0.05,0.05,0.05,0.05,0.15,0.05,0.1}, SUMPRODUCT(nilai,bobot) )/5 -> 0.64
A9: Risti | B9: Kiara Artha | C9: {=iferror(LET(kode, B9, actual, XLOOKUP(kode, Sales!A:A, Sales!E:E),target, XLOOKUP(kode, Sales!A:A, Sales!D:D),ratio, actual/target,skor, IFS(ratio>1, 5,ratio>=0.975, 4,ratio>=0.95, 3,ratio>=0.9, 2,TRUE, 1),skor),0)} -> 2 | D9: {=iferror(LET( kode, B9, actual, XLOOKUP(kode, AVG!A:A, AVG!E:E), target, XLOOKUP(kode, AVG!A:A, AVG!D:D), ratio, actual/target, skor, IFS( ratio>1, 5, ratio>=0.975, 4, ratio>=0.95, 3, ratio>=0.9, 2, TRUE, 1 ), skor ),0)} -> 4 | E9: {=iferror(LET( kode, B9, large, XLOOKUP(kode, Large!A:A, Large!E:E), small, XLOOKUP(kode, Large!A:A, Large!D:D), ratio, large/(large+small), skor, IFS( ratio<0.45, 1, ratio<=0.5, 2, ratio<=0.55, 3, ratio<=0.6, 4, TRUE, 5 ), skor ),0)} -> 1 | F9: {=iferror(LET( kode, B9, oatmilk, XLOOKUP(kode, Oatside!A:A, Oatside!E:E), drink, XLOOKUP(kode, Oatside!A:A, Oatside!D:D), ratio, oatmilk/drink, skor, IFS( ratio>5%, 5, ratio>=4%, 4, ratio>=3%, 3, ratio>=2%, 2, TRUE, 1 ), skor ),0)} -> 5 | G9: {=iferror(LET( kode, B9, actual, XLOOKUP(kode, 'Snack Platter'!A:A, 'Snack Platter'!E:E), target, XLOOKUP(kode, 'Snack Platter'!A:A, 'Snack Platter'!D:D), ratio, actual/target, skor, IFS( ratio>10%, 5, ratio>=7.5%, 4, ratio>=5%, 3, ratio>=2.5%, 2, TRUE, 1 ), skor ),0)} -> 3 | H9: {=iferror(LET( kode, B9, actual, XLOOKUP(kode, 'Bundling Asik'!A:A, 'Bundling Asik'!E:E), target, XLOOKUP(kode, 'Bundling Asik'!A:A, 'Bundling Asik'!D:D), ratio, actual/target, skor, IFS( ratio>5%, 5, ratio>=4%, 4, ratio>=3%, 3, ratio>=2%, 2, TRUE, 1 ), skor ),0)} -> 3 | I9: {=iferror(LET( kode, B9, ratio, XLOOKUP(kode, Audit!A:A, Audit!C:C), skor, IFS( ratio>90, 5, ratio>=85, 4, ratio>=80, 3, ratio>=75, 2, TRUE, 1 ), skor ),0)} -> 4 | J9: {=iferror(LET( kode, B9, ratio, XLOOKUP(kode, 'Mistery Shopper'!A:A, 'Mistery Shopper'!C:C), skor, IFS( ratio>90%, 5, ratio>=85%, 4, ratio>=80%, 3, ratio>=75%, 2, TRUE, 1 ), skor ),0)} -> 5 | K9: {=iferror(LET( kode, B9, actual, XLOOKUP(kode, Complain!A:A, Complain!E:E), target, XLOOKUP(kode, Complain!A:A, Complain!D:D), ratio, actual/target, skor, IFS( ratio>=0.16%, 1, ratio>=0.15%, 2, ratio>=0.125%, 3, ratio>=0.1%, 4, TRUE, 5 ), skor ),0)} -> 5 | L9: =LET( nilai, C9:K9, bobot, {0.4,0.1,0.05,0.05,0.05,0.05,0.15,0.05,0.1}, SUMPRODUCT(nilai,bobot) )/5 -> 0.63
A10: Sohib | B10: Peta | C10: {=iferror(LET(kode, B10, actual, XLOOKUP(kode, Sales!A:A, Sales!E:E),target, XLOOKUP(kode, Sales!A:A, Sales!D:D),ratio, actual/target,skor, IFS(ratio>1, 5,ratio>=0.975, 4,ratio>=0.95, 3,ratio>=0.9, 2,TRUE, 1),skor),0)} -> 2 | D10: {=iferror(LET( kode, B10, actual, XLOOKUP(kode, AVG!A:A, AVG!E:E), target, XLOOKUP(kode, AVG!A:A, AVG!D:D), ratio, actual/target, skor, IFS( ratio>1, 5, ratio>=0.975, 4, ratio>=0.95, 3, ratio>=0.9, 2, TRUE, 1 ), skor ),0)} -> 5 | E10: {=iferror(LET( kode, B10, large, XLOOKUP(kode, Large!A:A, Large!E:E), small, XLOOKUP(kode, Large!A:A, Large!D:D), ratio, large/(large+small), skor, IFS( ratio<0.45, 1, ratio<=0.5, 2, ratio<=0.55, 3, ratio<=0.6, 4, TRUE, 5 ), skor ),0)} -> 1 | F10: {=iferror(LET( kode, B10, oatmilk, XLOOKUP(kode, Oatside!A:A, Oatside!E:E), drink, XLOOKUP(kode, Oatside!A:A, Oatside!D:D), ratio, oatmilk/drink, skor, IFS( ratio>5%, 5, ratio>=4%, 4, ratio>=3%, 3, ratio>=2%, 2, TRUE, 1 ), skor ),0)} -> 5 | G10: {=iferror(LET( kode, B10, actual, XLOOKUP(kode, 'Snack Platter'!A:A, 'Snack Platter'!E:E), target, XLOOKUP(kode, 'Snack Platter'!A:A, 'Snack Platter'!D:D), ratio, actual/target, skor, IFS( ratio>10%, 5, ratio>=7.5%, 4, ratio>=5%, 3, ratio>=2.5%, 2, TRUE, 1 ), skor ),0)} -> 2 | H10: {=iferror(LET( kode, B10, actual, XLOOKUP(kode, 'Bundling Asik'!A:A, 'Bundling Asik'!E:E), target, XLOOKUP(kode, 'Bundling Asik'!A:A, 'Bundling Asik'!D:D), ratio, actual/target, skor, IFS( ratio>5%, 5, ratio>=4%, 4, ratio>=3%, 3, ratio>=2%, 2, TRUE, 1 ), skor ),0)} -> 4 | I10: {=iferror(LET( kode, B10, ratio, XLOOKUP(kode, Audit!A:A, Audit!C:C), skor, IFS( ratio>90, 5, ratio>=85, 4, ratio>=80, 3, ratio>=75, 2, TRUE, 1 ), skor ),0)} -> 4 | J10: {=iferror(LET( kode, B10, ratio, XLOOKUP(kode, 'Mistery Shopper'!A:A, 'Mistery Shopper'!C:C), skor, IFS( ratio>90%, 5, ratio>=85%, 4, ratio>=80%, 3, ratio>=75%, 2, TRUE, 1 ), skor ),0)} -> 5 | K10: {=iferror(LET( kode, B10, actual, XLOOKUP(kode, Complain!A:A, Complain!E:E), target, XLOOKUP(kode, Complain!A:A, Complain!D:D), ratio, actual/target, skor, IFS( ratio>=0.16%, 1, ratio>=0.15%, 2, ratio>=0.125%, 3, ratio>=0.1%, 4, TRUE, 5 ), skor ),0)} -> 4 | L10: =LET( nilai, C10:K10, bobot, {0.4,0.1,0.05,0.05,0.05,0.05,0.15,0.05,0.1}, SUMPRODUCT(nilai,bobot) )/5 -> 0.63
A11: Nadine | B11: Kota Wisata | C11: {=iferror(LET(kode, B11, actual, XLOOKUP(kode, Sales!A:A, Sales!E:E),target, XLOOKUP(kode, Sales!A:A, Sales!D:D),ratio, actual/target,skor, IFS(ratio>1, 5,ratio>=0.975, 4,ratio>=0.95, 3,ratio>=0.9, 2,TRUE, 1),skor),0)} -> 2 | D11: {=iferror(LET( kode, B11, actual, XLOOKUP(kode, AVG!A:A, AVG!E:E), target, XLOOKUP(kode, AVG!A:A, AVG!D:D), ratio, actual/target, skor, IFS( ratio>1, 5, ratio>=0.975, 4, ratio>=0.95, 3, ratio>=0.9, 2, TRUE, 1 ), skor ),0)} -> 5 | E11: {=iferror(LET( kode, B11, large, XLOOKUP(kode, Large!A:A, Large!E:E), small, XLOOKUP(kode, Large!A:A, Large!D:D), ratio, large/(large+small), skor, IFS( ratio<0.45, 1, ratio<=0.5, 2, ratio<=0.55, 3, ratio<=0.6, 4, TRUE, 5 ), skor ),0)} -> 5 | F11: {=iferror(LET( kode, B11, oatmilk, XLOOKUP(kode, Oatside!A:A, Oatside!E:E), drink, XLOOKUP(kode, Oatside!A:A, Oatside!D:D), ratio, oatmilk/drink, skor, IFS( ratio>5%, 5, ratio>=4%, 4, ratio>=3%, 3, ratio>=2%, 2, TRUE, 1 ), skor ),0)} -> 5 | G11: {=iferror(LET( kode, B11, actual, XLOOKUP(kode, 'Snack Platter'!A:A, 'Snack Platter'!E:E), target, XLOOKUP(kode, 'Snack Platter'!A:A, 'Snack Platter'!D:D), ratio, actual/target, skor, IFS( ratio>10%, 5, ratio>=7.5%, 4, ratio>=5%, 3, ratio>=2.5%, 2, TRUE, 1 ), skor ),0)} -> 5 | H11: {=iferror(LET( kode, B11, actual, XLOOKUP(kode, 'Bundling Asik'!A:A, 'Bundling Asik'!E:E), target, XLOOKUP(kode, 'Bundling Asik'!A:A, 'Bundling Asik'!D:D), ratio, actual/target, skor, IFS( ratio>5%, 5, ratio>=4%, 4, ratio>=3%, 3, ratio>=2%, 2, TRUE, 1 ), skor ),0)} -> 5 | I11: {=iferror(LET( kode, B11, ratio, XLOOKUP(kode, Audit!A:A, Audit!C:C), skor, IFS( ratio>90, 5, ratio>=85, 4, ratio>=80, 3, ratio>=75, 2, TRUE, 1 ), skor ),0)} -> 3 | J11: {=iferror(LET( kode, B11, ratio, XLOOKUP(kode, 'Mistery Shopper'!A:A, 'Mistery Shopper'!C:C), skor, IFS( ratio>90%, 5, ratio>=85%, 4, ratio>=80%, 3, ratio>=75%, 2, TRUE, 1 ), skor ),0)} -> 5 | K11: {=iferror(LET( kode, B11, actual, XLOOKUP(kode, Complain!A:A, Complain!E:E), target, XLOOKUP(kode, Complain!A:A, Complain!D:D), ratio, actual/target, skor, IFS( ratio>=0.16%, 1, ratio>=0.15%, 2, ratio>=0.125%, 3, ratio>=0.1%, 4, TRUE, 5 ), skor ),0)} -> 1 | L11: =LET( nilai, C11:K11, bobot, {0.4,0.1,0.05,0.05,0.05,0.05,0.15,0.05,0.1}, SUMPRODUCT(nilai,bobot) )/5 -> 0.62
A12: Risti | B12: Jatinangor | C12: {=iferror(LET(kode, B12, actual, XLOOKUP(kode, Sales!A:A, Sales!E:E),target, XLOOKUP(kode, Sales!A:A, Sales!D:D),ratio, actual/target,skor, IFS(ratio>1, 5,ratio>=0.975, 4,ratio>=0.95, 3,ratio>=0.9, 2,TRUE, 1),skor),0)} -> 1 | D12: {=iferror(LET( kode, B12, actual, XLOOKUP(kode, AVG!A:A, AVG!E:E), target, XLOOKUP(kode, AVG!A:A, AVG!D:D), ratio, actual/target, skor, IFS( ratio>1, 5, ratio>=0.975, 4, ratio>=0.95, 3, ratio>=0.9, 2, TRUE, 1 ), skor ),0)} -> 5 | E12: {=iferror(LET( kode, B12, large, XLOOKUP(kode, Large!A:A, Large!E:E), small, XLOOKUP(kode, Large!A:A, Large!D:D), ratio, large/(large+small), skor, IFS( ratio<0.45, 1, ratio<=0.5, 2, ratio<=0.55, 3, ratio<=0.6, 4, TRUE, 5 ), skor ),0)} -> 1 | F12: {=iferror(LET( kode, B12, oatmilk, XLOOKUP(kode, Oatside!A:A, Oatside!E:E), drink, XLOOKUP(kode, Oatside!A:A, Oatside!D:D), ratio, oatmilk/drink, skor, IFS( ratio>5%, 5, ratio>=4%, 4, ratio>=3%, 3, ratio>=2%, 2, TRUE, 1 ), skor ),0)} -> 5 | G12: {=iferror(LET( kode, B12, actual, XLOOKUP(kode, 'Snack Platter'!A:A, 'Snack Platter'!E:E), target, XLOOKUP(kode, 'Snack Platter'!A:A, 'Snack Platter'!D:D), ratio, actual/target, skor, IFS( ratio>10%, 5, ratio>=7.5%, 4, ratio>=5%, 3, ratio>=2.5%, 2, TRUE, 1 ), skor ),0)} -> 3 | H12: {=iferror(LET( kode, B12, actual, XLOOKUP(kode, 'Bundling Asik'!A:A, 'Bundling Asik'!E:E), target, XLOOKUP(kode, 'Bundling Asik'!A:A, 'Bundling Asik'!D:D), ratio, actual/target, skor, IFS( ratio>5%, 5, ratio>=4%, 4, ratio>=3%, 3, ratio>=2%, 2, TRUE, 1 ), skor ),0)} -> 2 | I12: {=iferror(LET( kode, B12, ratio, XLOOKUP(kode, Audit!A:A, Audit!C:C), skor, IFS( ratio>90, 5, ratio>=85, 4, ratio>=80, 3, ratio>=75, 2, TRUE, 1 ), skor ),0)} -> 5 | J12: {=iferror(LET( kode, B12, ratio, XLOOKUP(kode, 'Mistery Shopper'!A:A, 'Mistery Shopper'!C:C), skor, IFS( ratio>90%, 5, ratio>=85%, 4, ratio>=80%, 3, ratio>=75%, 2, TRUE, 1 ), skor ),0)} -> 5 | K12: {=iferror(LET( kode, B12, actual, XLOOKUP(kode, Complain!A:A, Complain!E:E), target, XLOOKUP(kode, Complain!A:A, Complain!D:D), ratio, actual/target, skor, IFS( ratio>=0.16%, 1, ratio>=0.15%, 2, ratio>=0.125%, 3, ratio>=0.1%, 4, TRUE, 5 ), skor ),0)} -> 5 | L12: =LET( nilai, C12:K12, bobot, {0.4,0.1,0.05,0.05,0.05,0.05,0.15,0.05,0.1}, SUMPRODUCT(nilai,bobot) )/5 -> 0.59
A13: Risti | B13: Buah Batu | C13: {=iferror(LET(kode, B13, actual, XLOOKUP(kode, Sales!A:A, Sales!E:E),target, XLOOKUP(kode, Sales!A:A, Sales!D:D),ratio, actual/target,skor, IFS(ratio>1, 5,ratio>=0.975, 4,ratio>=0.95, 3,ratio>=0.9, 2,TRUE, 1),skor),0)} -> 1 | D13: {=iferror(LET( kode, B13, actual, XLOOKUP(kode, AVG!A:A, AVG!E:E), target, XLOOKUP(kode, AVG!A:A, AVG!D:D), ratio, actual/target, skor, IFS( ratio>1, 5, ratio>=0.975, 4, ratio>=0.95, 3, ratio>=0.9, 2, TRUE, 1 ), skor ),0)} -> 5 | E13: {=iferror(LET( kode, B13, large, XLOOKUP(kode, Large!A:A, Large!E:E), small, XLOOKUP(kode, Large!A:A, Large!D:D), ratio, large/(large+small), skor, IFS( ratio<0.45, 1, ratio<=0.5, 2, ratio<=0.55, 3, ratio<=0.6, 4, TRUE, 5 ), skor ),0)} -> 1 | F13: {=iferror(LET( kode, B13, oatmilk, XLOOKUP(kode, Oatside!A:A, Oatside!E:E), drink, XLOOKUP(kode, Oatside!A:A, Oatside!D:D), ratio, oatmilk/drink, skor, IFS( ratio>5%, 5, ratio>=4%, 4, ratio>=3%, 3, ratio>=2%, 2, TRUE, 1 ), skor ),0)} -> 5 | G13: {=iferror(LET( kode, B13, actual, XLOOKUP(kode, 'Snack Platter'!A:A, 'Snack Platter'!E:E), target, XLOOKUP(kode, 'Snack Platter'!A:A, 'Snack Platter'!D:D), ratio, actual/target, skor, IFS( ratio>10%, 5, ratio>=7.5%, 4, ratio>=5%, 3, ratio>=2.5%, 2, TRUE, 1 ), skor ),0)} -> 1 | H13: {=iferror(LET( kode, B13, actual, XLOOKUP(kode, 'Bundling Asik'!A:A, 'Bundling Asik'!E:E), target, XLOOKUP(kode, 'Bundling Asik'!A:A, 'Bundling Asik'!D:D), ratio, actual/target, skor, IFS( ratio>5%, 5, ratio>=4%, 4, ratio>=3%, 3, ratio>=2%, 2, TRUE, 1 ), skor ),0)} -> 3 | I13: {=iferror(LET( kode, B13, ratio, XLOOKUP(kode, Audit!A:A, Audit!C:C), skor, IFS( ratio>90, 5, ratio>=85, 4, ratio>=80, 3, ratio>=75, 2, TRUE, 1 ), skor ),0)} -> 3 | J13: {=iferror(LET( kode, B13, ratio, XLOOKUP(kode, 'Mistery Shopper'!A:A, 'Mistery Shopper'!C:C), skor, IFS( ratio>90%, 5, ratio>=85%, 4, ratio>=80%, 3, ratio>=75%, 2, TRUE, 1 ), skor ),0)} -> 5 | K13: {=iferror(LET( kode, B13, actual, XLOOKUP(kode, Complain!A:A, Complain!E:E), target, XLOOKUP(kode, Complain!A:A, Complain!D:D), ratio, actual/target, skor, IFS( ratio>=0.16%, 1, ratio>=0.15%, 2, ratio>=0.125%, 3, ratio>=0.1%, 4, TRUE, 5 ), skor ),0)} -> 5 | L13: =LET( nilai, C13:K13, bobot, {0.4,0.1,0.05,0.05,0.05,0.05,0.15,0.05,0.1}, SUMPRODUCT(nilai,bobot) )/5 -> 0.52
A14: Bagas | B14: Pengumben | C14: {=iferror(LET(kode, B14, actual, XLOOKUP(kode, Sales!A:A, Sales!E:E),target, XLOOKUP(kode, Sales!A:A, Sales!D:D),ratio, actual/target,skor, IFS(ratio>1, 5,ratio>=0.975, 4,ratio>=0.95, 3,ratio>=0.9, 2,TRUE, 1),skor),0)} -> 1 | D14: {=iferror(LET( kode, B14, actual, XLOOKUP(kode, AVG!A:A, AVG!E:E), target, XLOOKUP(kode, AVG!A:A, AVG!D:D), ratio, actual/target, skor, IFS( ratio>1, 5, ratio>=0.975, 4, ratio>=0.95, 3, ratio>=0.9, 2, TRUE, 1 ), skor ),0)} -> 5 | E14: {=iferror(LET( kode, B14, large, XLOOKUP(kode, Large!A:A, Large!E:E), small, XLOOKUP(kode, Large!A:A, Large!D:D), ratio, large/(large+small), skor, IFS( ratio<0.45, 1, ratio<=0.5, 2, ratio<=0.55, 3, ratio<=0.6, 4, TRUE, 5 ), skor ),0)} -> 2 | F14: {=iferror(LET( kode, B14, oatmilk, XLOOKUP(kode, Oatside!A:A, Oatside!E:E), drink, XLOOKUP(kode, Oatside!A:A, Oatside!D:D), ratio, oatmilk/drink, skor, IFS( ratio>5%, 5, ratio>=4%, 4, ratio>=3%, 3, ratio>=2%, 2, TRUE, 1 ), skor ),0)} -> 5 | G14: {=iferror(LET( kode, B14, actual, XLOOKUP(kode, 'Snack Platter'!A:A, 'Snack Platter'!E:E), target, XLOOKUP(kode, 'Snack Platter'!A:A, 'Snack Platter'!D:D), ratio, actual/target, skor, IFS( ratio>10%, 5, ratio>=7.5%, 4, ratio>=5%, 3, ratio>=2.5%, 2, TRUE, 1 ), skor ),0)} -> 5 | H14: {=iferror(LET( kode, B14, actual, XLOOKUP(kode, 'Bundling Asik'!A:A, 'Bundling Asik'!E:E), target, XLOOKUP(kode, 'Bundling Asik'!A:A, 'Bundling Asik'!D:D), ratio, actual/target, skor, IFS( ratio>5%, 5, ratio>=4%, 4, ratio>=3%, 3, ratio>=2%, 2, TRUE, 1 ), skor ),0)} -> 5 | I14: {=iferror(LET( kode, B14, ratio, XLOOKUP(kode, Audit!A:A, Audit!C:C), skor, IFS( ratio>90, 5, ratio>=85, 4, ratio>=80, 3, ratio>=75, 2, TRUE, 1 ), skor ),0)} -> 2 | J14: {=iferror(LET( kode, B14, ratio, XLOOKUP(kode, 'Mistery Shopper'!A:A, 'Mistery Shopper'!C:C), skor, IFS( ratio>90%, 5, ratio>=85%, 4, ratio>=80%, 3, ratio>=75%, 2, TRUE, 1 ), skor ),0)} -> 5 | K14: {=iferror(LET( kode, B14, actual, XLOOKUP(kode, Complain!A:A, Complain!E:E), target, XLOOKUP(kode, Complain!A:A, Complain!D:D), ratio, actual/target, skor, IFS( ratio>=0.16%, 1, ratio>=0.15%, 2, ratio>=0.125%, 3, ratio>=0.1%, 4, TRUE, 5 ), skor ),0)} -> 3 | L14: =LET( nilai, C14:K14, bobot, {0.4,0.1,0.05,0.05,0.05,0.05,0.15,0.05,0.1}, SUMPRODUCT(nilai,bobot) )/5 -> 0.52
A15: Bagas | B15: Kalimalang | C15: {=iferror(LET(kode, B15, actual, XLOOKUP(kode, Sales!A:A, Sales!E:E),target, XLOOKUP(kode, Sales!A:A, Sales!D:D),ratio, actual/target,skor, IFS(ratio>1, 5,ratio>=0.975, 4,ratio>=0.95, 3,ratio>=0.9, 2,TRUE, 1),skor),0)} -> 1 | D15: {=iferror(LET( kode, B15, actual, XLOOKUP(kode, AVG!A:A, AVG!E:E), target, XLOOKUP(kode, AVG!A:A, AVG!D:D), ratio, actual/target, skor, IFS( ratio>1, 5, ratio>=0.975, 4, ratio>=0.95, 3, ratio>=0.9, 2, TRUE, 1 ), skor ),0)} -> 5 | E15: {=iferror(LET( kode, B15, large, XLOOKUP(kode, Large!A:A, Large!E:E), small, XLOOKUP(kode, Large!A:A, Large!D:D), ratio, large/(large+small), skor, IFS( ratio<0.45, 1, ratio<=0.5, 2, ratio<=0.55, 3, ratio<=0.6, 4, TRUE, 5 ), skor ),0)} -> 2 | F15: {=iferror(LET( kode, B15, oatmilk, XLOOKUP(kode, Oatside!A:A, Oatside!E:E), drink, XLOOKUP(kode, Oatside!A:A, Oatside!D:D), ratio, oatmilk/drink, skor, IFS( ratio>5%, 5, ratio>=4%, 4, ratio>=3%, 3, ratio>=2%, 2, TRUE, 1 ), skor ),0)} -> 5 | G15: {=iferror(LET( kode, B15, actual, XLOOKUP(kode, 'Snack Platter'!A:A, 'Snack Platter'!E:E), target, XLOOKUP(kode, 'Snack Platter'!A:A, 'Snack Platter'!D:D), ratio, actual/target, skor, IFS( ratio>10%, 5, ratio>=7.5%, 4, ratio>=5%, 3, ratio>=2.5%, 2, TRUE, 1 ), skor ),0)} -> 2 | H15: {=iferror(LET( kode, B15, actual, XLOOKUP(kode, 'Bundling Asik'!A:A, 'Bundling Asik'!E:E), target, XLOOKUP(kode, 'Bundling Asik'!A:A, 'Bundling Asik'!D:D), ratio, actual/target, skor, IFS( ratio>5%, 5, ratio>=4%, 4, ratio>=3%, 3, ratio>=2%, 2, TRUE, 1 ), skor ),0)} -> 3 | I15: {=iferror(LET( kode, B15, ratio, XLOOKUP(kode, Audit!A:A, Audit!C:C), skor, IFS( ratio>90, 5, ratio>=85, 4, ratio>=80, 3, ratio>=75, 2, TRUE, 1 ), skor ),0)} -> 2 | J15: {=iferror(LET( kode, B15, ratio, XLOOKUP(kode, 'Mistery Shopper'!A:A, 'Mistery Shopper'!C:C), skor, IFS( ratio>90%, 5, ratio>=85%, 4, ratio>=80%, 3, ratio>=75%, 2, TRUE, 1 ), skor ),0)} -> 5 | K15: {=iferror(LET( kode, B15, actual, XLOOKUP(kode, Complain!A:A, Complain!E:E), target, XLOOKUP(kode, Complain!A:A, Complain!D:D), ratio, actual/target, skor, IFS( ratio>=0.16%, 1, ratio>=0.15%, 2, ratio>=0.125%, 3, ratio>=0.1%, 4, TRUE, 5 ), skor ),0)} -> 5 | L15: =LET( nilai, C15:K15, bobot, {0.4,0.1,0.05,0.05,0.05,0.05,0.15,0.05,0.1}, SUMPRODUCT(nilai,bobot) )/5 -> 0.51
A16: Bagas | B16: Kemang Utara | C16: {=iferror(LET(kode, B16, actual, XLOOKUP(kode, Sales!A:A, Sales!E:E),target, XLOOKUP(kode, Sales!A:A, Sales!D:D),ratio, actual/target,skor, IFS(ratio>1, 5,ratio>=0.975, 4,ratio>=0.95, 3,ratio>=0.9, 2,TRUE, 1),skor),0)} -> 1 | D16: {=iferror(LET( kode, B16, actual, XLOOKUP(kode, AVG!A:A, AVG!E:E), target, XLOOKUP(kode, AVG!A:A, AVG!D:D), ratio, actual/target, skor, IFS( ratio>1, 5, ratio>=0.975, 4, ratio>=0.95, 3, ratio>=0.9, 2, TRUE, 1 ), skor ),0)} -> 5 | E16: {=iferror(LET( kode, B16, large, XLOOKUP(kode, Large!A:A, Large!E:E), small, XLOOKUP(kode, Large!A:A, Large!D:D), ratio, large/(large+small), skor, IFS( ratio<0.45, 1, ratio<=0.5, 2, ratio<=0.55, 3, ratio<=0.6, 4, TRUE, 5 ), skor ),0)} -> 1 | F16: {=iferror(LET( kode, B16, oatmilk, XLOOKUP(kode, Oatside!A:A, Oatside!E:E), drink, XLOOKUP(kode, Oatside!A:A, Oatside!D:D), ratio, oatmilk/drink, skor, IFS( ratio>5%, 5, ratio>=4%, 4, ratio>=3%, 3, ratio>=2%, 2, TRUE, 1 ), skor ),0)} -> 5 | G16: {=iferror(LET( kode, B16, actual, XLOOKUP(kode, 'Snack Platter'!A:A, 'Snack Platter'!E:E), target, XLOOKUP(kode, 'Snack Platter'!A:A, 'Snack Platter'!D:D), ratio, actual/target, skor, IFS( ratio>10%, 5, ratio>=7.5%, 4, ratio>=5%, 3, ratio>=2.5%, 2, TRUE, 1 ), skor ),0)} -> 2 | H16: {=iferror(LET( kode, B16, actual, XLOOKUP(kode, 'Bundling Asik'!A:A, 'Bundling Asik'!E:E), target, XLOOKUP(kode, 'Bundling Asik'!A:A, 'Bundling Asik'!D:D), ratio, actual/target, skor, IFS( ratio>5%, 5, ratio>=4%, 4, ratio>=3%, 3, ratio>=2%, 2, TRUE, 1 ), skor ),0)} -> 3 | I16: {=iferror(LET( kode, B16, ratio, XLOOKUP(kode, Audit!A:A, Audit!C:C), skor, IFS( ratio>90, 5, ratio>=85, 4, ratio>=80, 3, ratio>=75, 2, TRUE, 1 ), skor ),0)} -> 2 | J16: {=iferror(LET( kode, B16, ratio, XLOOKUP(kode, 'Mistery Shopper'!A:A, 'Mistery Shopper'!C:C), skor, IFS( ratio>90%, 5, ratio>=85%, 4, ratio>=80%, 3, ratio>=75%, 2, TRUE, 1 ), skor ),0)} -> 5 | K16: {=iferror(LET( kode, B16, actual, XLOOKUP(kode, Complain!A:A, Complain!E:E), target, XLOOKUP(kode, Complain!A:A, Complain!D:D), ratio, actual/target, skor, IFS( ratio>=0.16%, 1, ratio>=0.15%, 2, ratio>=0.125%, 3, ratio>=0.1%, 4, TRUE, 5 ), skor ),0)} -> 5 | L16: =LET( nilai, C16:K16, bobot, {0.4,0.1,0.05,0.05,0.05,0.05,0.15,0.05,0.1}, SUMPRODUCT(nilai,bobot) )/5 -> 0.5
A17: Ryan | B17: Pamulang | C17: {=iferror(LET(kode, B17, actual, XLOOKUP(kode, Sales!A:A, Sales!E:E),target, XLOOKUP(kode, Sales!A:A, Sales!D:D),ratio, actual/target,skor, IFS(ratio>1, 5,ratio>=0.975, 4,ratio>=0.95, 3,ratio>=0.9, 2,TRUE, 1),skor),0)} -> 1 | D17: {=iferror(LET( kode, B17, actual, XLOOKUP(kode, AVG!A:A, AVG!E:E), target, XLOOKUP(kode, AVG!A:A, AVG!D:D), ratio, actual/target, skor, IFS( ratio>1, 5, ratio>=0.975, 4, ratio>=0.95, 3, ratio>=0.9, 2, TRUE, 1 ), skor ),0)} -> 5 | E17: {=iferror(LET( kode, B17, large, XLOOKUP(kode, Large!A:A, Large!E:E), small, XLOOKUP(kode, Large!A:A, Large!D:D), ratio, large/(large+small), skor, IFS( ratio<0.45, 1, ratio<=0.5, 2, ratio<=0.55, 3, ratio<=0.6, 4, TRUE, 5 ), skor ),0)} -> 1 | F17: {=iferror(LET( kode, B17, oatmilk, XLOOKUP(kode, Oatside!A:A, Oatside!E:E), drink, XLOOKUP(kode, Oatside!A:A, Oatside!D:D), ratio, oatmilk/drink, skor, IFS( ratio>5%, 5, ratio>=4%, 4, ratio>=3%, 3, ratio>=2%, 2, TRUE, 1 ), skor ),0)} -> 4 | G17: {=iferror(LET( kode, B17, actual, XLOOKUP(kode, 'Snack Platter'!A:A, 'Snack Platter'!E:E), target, XLOOKUP(kode, 'Snack Platter'!A:A, 'Snack Platter'!D:D), ratio, actual/target, skor, IFS( ratio>10%, 5, ratio>=7.5%, 4, ratio>=5%, 3, ratio>=2.5%, 2, TRUE, 1 ), skor ),0)} -> 1 | H17: {=iferror(LET( kode, B17, actual, XLOOKUP(kode, 'Bundling Asik'!A:A, 'Bundling Asik'!E:E), target, XLOOKUP(kode, 'Bundling Asik'!A:A, 'Bundling Asik'!D:D), ratio, actual/target, skor, IFS( ratio>5%, 5, ratio>=4%, 4, ratio>=3%, 3, ratio>=2%, 2, TRUE, 1 ), skor ),0)} -> 2 | I17: {=iferror(LET( kode, B17, ratio, XLOOKUP(kode, Audit!A:A, Audit!C:C), skor, IFS( ratio>90, 5, ratio>=85, 4, ratio>=80, 3, ratio>=75, 2, TRUE, 1 ), skor ),0)} -> 3 | J17: {=iferror(LET( kode, B17, ratio, XLOOKUP(kode, 'Mistery Shopper'!A:A, 'Mistery Shopper'!C:C), skor, IFS( ratio>90%, 5, ratio>=85%, 4, ratio>=80%, 3, ratio>=75%, 2, TRUE, 1 ), skor ),0)} -> 5 | K17: {=iferror(LET( kode, B17, actual, XLOOKUP(kode, Complain!A:A, Complain!E:E), target, XLOOKUP(kode, Complain!A:A, Complain!D:D), ratio, actual/target, skor, IFS( ratio>=0.16%, 1, ratio>=0.15%, 2, ratio>=0.125%, 3, ratio>=0.1%, 4, TRUE, 5 ), skor ),0)} -> 5 | L17: =LET( nilai, C17:K17, bobot, {0.4,0.1,0.05,0.05,0.05,0.05,0.15,0.05,0.1}, SUMPRODUCT(nilai,bobot) )/5 -> 0.5
A18: Bagas | B18: Cilandak Barat | C18: {=iferror(LET(kode, B18, actual, XLOOKUP(kode, Sales!A:A, Sales!E:E),target, XLOOKUP(kode, Sales!A:A, Sales!D:D),ratio, actual/target,skor, IFS(ratio>1, 5,ratio>=0.975, 4,ratio>=0.95, 3,ratio>=0.9, 2,TRUE, 1),skor),0)} -> 1 | D18: {=iferror(LET( kode, B18, actual, XLOOKUP(kode, AVG!A:A, AVG!E:E), target, XLOOKUP(kode, AVG!A:A, AVG!D:D), ratio, actual/target, skor, IFS( ratio>1, 5, ratio>=0.975, 4, ratio>=0.95, 3, ratio>=0.9, 2, TRUE, 1 ), skor ),0)} -> 3 | E18: {=iferror(LET( kode, B18, large, XLOOKUP(kode, Large!A:A, Large!E:E), small, XLOOKUP(kode, Large!A:A, Large!D:D), ratio, large/(large+small), skor, IFS( ratio<0.45, 1, ratio<=0.5, 2, ratio<=0.55, 3, ratio<=0.6, 4, TRUE, 5 ), skor ),0)} -> 5 | F18: {=iferror(LET( kode, B18, oatmilk, XLOOKUP(kode, Oatside!A:A, Oatside!E:E), drink, XLOOKUP(kode, Oatside!A:A, Oatside!D:D), ratio, oatmilk/drink, skor, IFS( ratio>5%, 5, ratio>=4%, 4, ratio>=3%, 3, ratio>=2%, 2, TRUE, 1 ), skor ),0)} -> 5 | G18: {=iferror(LET( kode, B18, actual, XLOOKUP(kode, 'Snack Platter'!A:A, 'Snack Platter'!E:E), target, XLOOKUP(kode, 'Snack Platter'!A:A, 'Snack Platter'!D:D), ratio, actual/target, skor, IFS( ratio>10%, 5, ratio>=7.5%, 4, ratio>=5%, 3, ratio>=2.5%, 2, TRUE, 1 ), skor ),0)} -> 5 | H18: {=iferror(LET( kode, B18, actual, XLOOKUP(kode, 'Bundling Asik'!A:A, 'Bundling Asik'!E:E), target, XLOOKUP(kode, 'Bundling Asik'!A:A, 'Bundling Asik'!D:D), ratio, actual/target, skor, IFS( ratio>5%, 5, ratio>=4%, 4, ratio>=3%, 3, ratio>=2%, 2, TRUE, 1 ), skor ),0)} -> 3 | I18: {=iferror(LET( kode, B18, ratio, XLOOKUP(kode, Audit!A:A, Audit!C:C), skor, IFS( ratio>90, 5, ratio>=85, 4, ratio>=80, 3, ratio>=75, 2, TRUE, 1 ), skor ),0)} -> 3 | J18: {=iferror(LET( kode, B18, ratio, XLOOKUP(kode, 'Mistery Shopper'!A:A, 'Mistery Shopper'!C:C), skor, IFS( ratio>90%, 5, ratio>=85%, 4, ratio>=80%, 3, ratio>=75%, 2, TRUE, 1 ), skor ),0)} -> 5 | K18: {=iferror(LET( kode, B18, actual, XLOOKUP(kode, Complain!A:A, Complain!E:E), target, XLOOKUP(kode, Complain!A:A, Complain!D:D), ratio, actual/target, skor, IFS( ratio>=0.16%, 1, ratio>=0.15%, 2, ratio>=0.125%, 3, ratio>=0.1%, 4, TRUE, 5 ), skor ),0)} -> 2 | L18: =LET( nilai, C18:K18, bobot, {0.4,0.1,0.05,0.05,0.05,0.05,0.15,0.05,0.1}, SUMPRODUCT(nilai,bobot) )/5 -> 0.5
A19: Ryan | B19: Ciledug | C19: {=iferror(LET(kode, B19, actual, XLOOKUP(kode, Sales!A:A, Sales!E:E),target, XLOOKUP(kode, Sales!A:A, Sales!D:D),ratio, actual/target,skor, IFS(ratio>1, 5,ratio>=0.975, 4,ratio>=0.95, 3,ratio>=0.9, 2,TRUE, 1),skor),0)} -> 1 | D19: {=iferror(LET( kode, B19, actual, XLOOKUP(kode, AVG!A:A, AVG!E:E), target, XLOOKUP(kode, AVG!A:A, AVG!D:D), ratio, actual/target, skor, IFS( ratio>1, 5, ratio>=0.975, 4, ratio>=0.95, 3, ratio>=0.9, 2, TRUE, 1 ), skor ),0)} -> 5 | E19: {=iferror(LET( kode, B19, large, XLOOKUP(kode, Large!A:A, Large!E:E), small, XLOOKUP(kode, Large!A:A, Large!D:D), ratio, large/(large+small), skor, IFS( ratio<0.45, 1, ratio<=0.5, 2, ratio<=0.55, 3, ratio<=0.6, 4, TRUE, 5 ), skor ),0)} -> 1 | F19: {=iferror(LET( kode, B19, oatmilk, XLOOKUP(kode, Oatside!A:A, Oatside!E:E), drink, XLOOKUP(kode, Oatside!A:A, Oatside!D:D), ratio, oatmilk/drink, skor, IFS( ratio>5%, 5, ratio>=4%, 4, ratio>=3%, 3, ratio>=2%, 2, TRUE, 1 ), skor ),0)} -> 5 | G19: {=iferror(LET( kode, B19, actual, XLOOKUP(kode, 'Snack Platter'!A:A, 'Snack Platter'!E:E), target, XLOOKUP(kode, 'Snack Platter'!A:A, 'Snack Platter'!D:D), ratio, actual/target, skor, IFS( ratio>10%, 5, ratio>=7.5%, 4, ratio>=5%, 3, ratio>=2.5%, 2, TRUE, 1 ), skor ),0)} -> 1 | H19: {=iferror(LET( kode, B19, actual, XLOOKUP(kode, 'Bundling Asik'!A:A, 'Bundling Asik'!E:E), target, XLOOKUP(kode, 'Bundling Asik'!A:A, 'Bundling Asik'!D:D), ratio, actual/target, skor, IFS( ratio>5%, 5, ratio>=4%, 4, ratio>=3%, 3, ratio>=2%, 2, TRUE, 1 ), skor ),0)} -> 2 | I19: {=iferror(LET( kode, B19, ratio, XLOOKUP(kode, Audit!A:A, Audit!C:C), skor, IFS( ratio>90, 5, ratio>=85, 4, ratio>=80, 3, ratio>=75, 2, TRUE, 1 ), skor ),0)} -> 2 | J19: {=iferror(LET( kode, B19, ratio, XLOOKUP(kode, 'Mistery Shopper'!A:A, 'Mistery Shopper'!C:C), skor, IFS( ratio>90%, 5, ratio>=85%, 4, ratio>=80%, 3, ratio>=75%, 2, TRUE, 1 ), skor ),0)} -> 5 | K19: {=iferror(LET( kode, B19, actual, XLOOKUP(kode, Complain!A:A, Complain!E:E), target, XLOOKUP(kode, Complain!A:A, Complain!D:D), ratio, actual/target, skor, IFS( ratio>=0.16%, 1, ratio>=0.15%, 2, ratio>=0.125%, 3, ratio>=0.1%, 4, TRUE, 5 ), skor ),0)} -> 5 | L19: =LET( nilai, C19:K19, bobot, {0.4,0.1,0.05,0.05,0.05,0.05,0.15,0.05,0.1}, SUMPRODUCT(nilai,bobot) )/5 -> 0.48
... A31: Bagas | B31: Kayu Putih | C31: {=iferror(LET(kode, B31, actual, XLOOKUP(kode, Sales!A:A, Sales!E:E),target, XLOOKUP(kode, Sales!A:A, Sales!D:D),ratio, actual/target,skor, IFS(ratio>1, 5,ratio>=0.975, 4,ratio>=0.95, 3,ratio>=0.9, 2,TRUE, 1),skor),0)} -> 1 | D31: {=iferror(LET( kode, B31, actual, XLOOKUP(kode, AVG!A:A, AVG!E:E), target, XLOOKUP(kode, AVG!A:A, AVG!D:D), ratio, actual/target, skor, IFS( ratio>1, 5, ratio>=0.975, 4, ratio>=0.95, 3, ratio>=0.9, 2, TRUE, 1 ), skor ),0)} -> 1 | E31: {=iferror(LET( kode, B31, large, XLOOKUP(kode, Large!A:A, Large!E:E), small, XLOOKUP(kode, Large!A:A, Large!D:D), ratio, large/(large+small), skor, IFS( ratio<0.45, 1, ratio<=0.5, 2, ratio<=0.55, 3, ratio<=0.6, 4, TRUE, 5 ), skor ),0)} -> 1 | F31: {=iferror(LET( kode, B31, oatmilk, XLOOKUP(kode, Oatside!A:A, Oatside!E:E), drink, XLOOKUP(kode, Oatside!A:A, Oatside!D:D), ratio, oatmilk/drink, skor, IFS( ratio>5%, 5, ratio>=4%, 4, ratio>=3%, 3, ratio>=2%, 2, TRUE, 1 ), skor ),0)} -> 1 | G31: {=iferror(LET( kode, B31, actual, XLOOKUP(kode, 'Snack Platter'!A:A, 'Snack Platter'!E:E), target, XLOOKUP(kode, 'Snack Platter'!A:A, 'Snack Platter'!D:D), ratio, actual/target, skor, IFS( ratio>10%, 5, ratio>=7.5%, 4, ratio>=5%, 3, ratio>=2.5%, 2, TRUE, 1 ), skor ),0)} -> 1 | H31: {=iferror(LET( kode, B31, actual, XLOOKUP(kode, 'Bundling Asik'!A:A, 'Bundling Asik'!E:E), target, XLOOKUP(kode, 'Bundling Asik'!A:A, 'Bundling Asik'!D:D), ratio, actual/target, skor, IFS( ratio>5%, 5, ratio>=4%, 4, ratio>=3%, 3, ratio>=2%, 2, TRUE, 1 ), skor ),0)} -> 1 | I31: {=iferror(LET( kode, B31, ratio, XLOOKUP(kode, Audit!A:A, Audit!C:C), skor, IFS( ratio>90, 5, ratio>=85, 4, ratio>=80, 3, ratio>=75, 2, TRUE, 1 ), skor ),0)} -> 1 | J31: {=iferror(LET( kode, B31, ratio, XLOOKUP(kode, 'Mistery Shopper'!A:A, 'Mistery Shopper'!C:C), skor, IFS( ratio>90%, 5, ratio>=85%, 4, ratio>=80%, 3, ratio>=75%, 2, TRUE, 1 ), skor ),0)} -> 5 | K31: {=iferror(LET( kode, B31, actual, XLOOKUP(kode, Complain!A:A, Complain!E:E), target, XLOOKUP(kode, Complain!A:A, Complain!D:D), ratio, actual/target, skor, IFS( ratio>=0.16%, 1, ratio>=0.15%, 2, ratio>=0.125%, 3, ratio>=0.1%, 4, TRUE, 5 ), skor ),0)} -> 1 | L31: =LET( nilai, C31:K31, bobot, {0.4,0.1,0.05,0.05,0.05,0.05,0.15,0.05,0.1}, SUMPRODUCT(nilai,bobot) )/5 -> 0.24

Sheet Mar
B1: Store | C1: Net Sales | D1: AVG | E1: Large | F1: Oatside | G1: Add On Telur | H1: B. Asik | I1: Audit | J1: M. Shopper | K1: Complain | L1: Total | N1: Orang | O1: Score
A2: Bagas | B2: Setu Cipayung | C2: {=iferror(LET(kode, B2, actual, XLOOKUP(kode, Sales!A:A, Sales!G:G),target, XLOOKUP(kode, Sales!A:A, Sales!F:F),ratio, actual/target,skor, IFS(ratio>1, 5,ratio>=0.975, 4,ratio>=0.95, 3,ratio>=0.9, 2,TRUE, 1),skor),0)} -> 5 | D2: {=iferror(LET( kode, B2, actual, XLOOKUP(kode, AVG!A:A, AVG!G:G), target, XLOOKUP(kode, AVG!A:A, AVG!F:F), ratio, actual/target, skor, IFS( ratio>1, 5, ratio>=0.975, 4, ratio>=0.95, 3, ratio>=0.9, 2, TRUE, 1 ), skor ),0)} -> 5 | E2: {=iferror(LET( kode, B2, large, XLOOKUP(kode, Large!A:A, Large!G:G), small, XLOOKUP(kode, Large!A:A, Large!F:F), ratio, large/(large+small), skor, IFS( ratio<0.45, 1, ratio<=0.5, 2, ratio<=0.55, 3, ratio<=0.6, 4, TRUE, 5 ), skor ),0)} -> 1 | F2: {=iferror(LET( kode, B2, oatmilk, XLOOKUP(kode, Oatside!A:A, Oatside!G:G), drink, XLOOKUP(kode, Oatside!A:A, Oatside!F:F), ratio, oatmilk/drink, skor, IFS( ratio>5%, 5, ratio>=4%, 4, ratio>=3%, 3, ratio>=2%, 2, TRUE, 1 ), skor ),0)} -> 5 | G2: {=iferror(LET( kode, B2, actual, XLOOKUP(kode, 'Snack Platter'!A:A, 'Snack Platter'!G:G), target, XLOOKUP(kode, 'Snack Platter'!A:A, 'Snack Platter'!F:F), ratio, actual/target, skor, IFS( ratio>10%, 5, ratio>=7.5%, 4, ratio>=5%, 3, ratio>=2.5%, 2, TRUE, 1 ), skor ),0)} -> 3 | H2: {=iferror(LET( kode, B2, actual, XLOOKUP(kode, 'Bundling Asik'!A:A, 'Bundling Asik'!G:G), target, XLOOKUP(kode, 'Bundling Asik'!A:A, 'Bundling Asik'!F:F), ratio, actual/target, skor, IFS( ratio>5%, 5, ratio>=4%, 4, ratio>=3%, 3, ratio>=2%, 2, TRUE, 1 ), skor ),0)} -> 5 | I2: {=iferror(LET( kode, B2, ratio, XLOOKUP(kode, Audit!A:A, Audit!D:D), skor, IFS( ratio>90, 5, ratio>=85, 4, ratio>=80, 3, ratio>=75, 2, TRUE, 1 ), skor ),0)} -> 4 | J2: {=iferror(LET( kode, B2, ratio, XLOOKUP(kode, 'Mistery Shopper'!A:A, 'Mistery Shopper'!D:D), skor, IFS( ratio>90%, 5, ratio>=85%, 4, ratio>=80%, 3, ratio>=75%, 2, TRUE, 1 ), skor ),0)} -> 5 | K2: {=iferror(LET( kode, B2, actual, XLOOKUP(kode, Complain!A:A, Complain!G:G), target, XLOOKUP(kode, Complain!A:A, Complain!F:F), ratio, actual/target, skor, IFS( ratio>=0.16%, 1, ratio>=0.15%, 2, ratio>=0.125%, 3, ratio>=0.1%, 4, TRUE, 5 ), skor ),0)} -> 5 | L2: =LET( nilai, C2:K2, bobot, {0.4,0.1,0.05,0.05,0.05,0.05,0.15,0.05,0.1}, SUMPRODUCT(nilai,bobot) )/5 -> 0.91 | N2: Risti | O2: =averageif(A:A,N2,L:L) -> 0.846
A3: Bagas | B3: Lebak Bulus | C3: {=iferror(LET(kode, B3, actual, XLOOKUP(kode, Sales!A:A, Sales!G:G),target, XLOOKUP(kode, Sales!A:A, Sales!F:F),ratio, actual/target,skor, IFS(ratio>1, 5,ratio>=0.975, 4,ratio>=0.95, 3,ratio>=0.9, 2,TRUE, 1),skor),0)} -> 5 | D3: {=iferror(LET( kode, B3, actual, XLOOKUP(kode, AVG!A:A, AVG!G:G), target, XLOOKUP(kode, AVG!A:A, AVG!F:F), ratio, actual/target, skor, IFS( ratio>1, 5, ratio>=0.975, 4, ratio>=0.95, 3, ratio>=0.9, 2, TRUE, 1 ), skor ),0)} -> 5 | E3: {=iferror(LET( kode, B3, large, XLOOKUP(kode, Large!A:A, Large!G:G), small, XLOOKUP(kode, Large!A:A, Large!F:F), ratio, large/(large+small), skor, IFS( ratio<0.45, 1, ratio<=0.5, 2, ratio<=0.55, 3, ratio<=0.6, 4, TRUE, 5 ), skor ),0)} -> 1 | F3: {=iferror(LET( kode, B3, oatmilk, XLOOKUP(kode, Oatside!A:A, Oatside!G:G), drink, XLOOKUP(kode, Oatside!A:A, Oatside!F:F), ratio, oatmilk/drink, skor, IFS( ratio>5%, 5, ratio>=4%, 4, ratio>=3%, 3, ratio>=2%, 2, TRUE, 1 ), skor ),0)} -> 5 | G3: {=iferror(LET( kode, B3, actual, XLOOKUP(kode, 'Snack Platter'!A:A, 'Snack Platter'!G:G), target, XLOOKUP(kode, 'Snack Platter'!A:A, 'Snack Platter'!F:F), ratio, actual/target, skor, IFS( ratio>10%, 5, ratio>=7.5%, 4, ratio>=5%, 3, ratio>=2.5%, 2, TRUE, 1 ), skor ),0)} -> 2 | H3: {=iferror(LET( kode, B3, actual, XLOOKUP(kode, 'Bundling Asik'!A:A, 'Bundling Asik'!G:G), target, XLOOKUP(kode, 'Bundling Asik'!A:A, 'Bundling Asik'!F:F), ratio, actual/target, skor, IFS( ratio>5%, 5, ratio>=4%, 4, ratio>=3%, 3, ratio>=2%, 2, TRUE, 1 ), skor ),0)} -> 3 | I3: {=iferror(LET( kode, B3, ratio, XLOOKUP(kode, Audit!A:A, Audit!D:D), skor, IFS( ratio>90, 5, ratio>=85, 4, ratio>=80, 3, ratio>=75, 2, TRUE, 1 ), skor ),0)} -> 2 | J3: {=iferror(LET( kode, B3, ratio, XLOOKUP(kode, 'Mistery Shopper'!A:A, 'Mistery Shopper'!D:D), skor, IFS( ratio>90%, 5, ratio>=85%, 4, ratio>=80%, 3, ratio>=75%, 2, TRUE, 1 ), skor ),0)} -> 5 | K3: {=iferror(LET( kode, B3, actual, XLOOKUP(kode, Complain!A:A, Complain!G:G), target, XLOOKUP(kode, Complain!A:A, Complain!F:F), ratio, actual/target, skor, IFS( ratio>=0.16%, 1, ratio>=0.15%, 2, ratio>=0.125%, 3, ratio>=0.1%, 4, TRUE, 5 ), skor ),0)} -> 5 | L3: =LET( nilai, C3:K3, bobot, {0.4,0.1,0.05,0.05,0.05,0.05,0.15,0.05,0.1}, SUMPRODUCT(nilai,bobot) )/5 -> 0.82 | N3: Nadine | O3: =averageif(A:A,N3,L:L) -> 0.882
A4: Bagas | B4: Pengumben | C4: {=iferror(LET(kode, B4, actual, XLOOKUP(kode, Sales!A:A, Sales!G:G),target, XLOOKUP(kode, Sales!A:A, Sales!F:F),ratio, actual/target,skor, IFS(ratio>1, 5,ratio>=0.975, 4,ratio>=0.95, 3,ratio>=0.9, 2,TRUE, 1),skor),0)} -> 5 | D4: {=iferror(LET( kode, B4, actual, XLOOKUP(kode, AVG!A:A, AVG!G:G), target, XLOOKUP(kode, AVG!A:A, AVG!F:F), ratio, actual/target, skor, IFS( ratio>1, 5, ratio>=0.975, 4, ratio>=0.95, 3, ratio>=0.9, 2, TRUE, 1 ), skor ),0)} -> 5 | E4: {=iferror(LET( kode, B4, large, XLOOKUP(kode, Large!A:A, Large!G:G), small, XLOOKUP(kode, Large!A:A, Large!F:F), ratio, large/(large+small), skor, IFS( ratio<0.45, 1, ratio<=0.5, 2, ratio<=0.55, 3, ratio<=0.6, 4, TRUE, 5 ), skor ),0)} -> 3 | F4: {=iferror(LET( kode, B4, oatmilk, XLOOKUP(kode, Oatside!A:A, Oatside!G:G), drink, XLOOKUP(kode, Oatside!A:A, Oatside!F:F), ratio, oatmilk/drink, skor, IFS( ratio>5%, 5, ratio>=4%, 4, ratio>=3%, 3, ratio>=2%, 2, TRUE, 1 ), skor ),0)} -> 5 | G4: {=iferror(LET( kode, B4, actual, XLOOKUP(kode, 'Snack Platter'!A:A, 'Snack Platter'!G:G), target, XLOOKUP(kode, 'Snack Platter'!A:A, 'Snack Platter'!F:F), ratio, actual/target, skor, IFS( ratio>10%, 5, ratio>=7.5%, 4, ratio>=5%, 3, ratio>=2.5%, 2, TRUE, 1 ), skor ),0)} -> 5 | H4: {=iferror(LET( kode, B4, actual, XLOOKUP(kode, 'Bundling Asik'!A:A, 'Bundling Asik'!G:G), target, XLOOKUP(kode, 'Bundling Asik'!A:A, 'Bundling Asik'!F:F), ratio, actual/target, skor, IFS( ratio>5%, 5, ratio>=4%, 4, ratio>=3%, 3, ratio>=2%, 2, TRUE, 1 ), skor ),0)} -> 5 | I4: {=iferror(LET( kode, B4, ratio, XLOOKUP(kode, Audit!A:A, Audit!D:D), skor, IFS( ratio>90, 5, ratio>=85, 4, ratio>=80, 3, ratio>=75, 2, TRUE, 1 ), skor ),0)} -> 1 | J4: {=iferror(LET( kode, B4, ratio, XLOOKUP(kode, 'Mistery Shopper'!A:A, 'Mistery Shopper'!D:D), skor, IFS( ratio>90%, 5, ratio>=85%, 4, ratio>=80%, 3, ratio>=75%, 2, TRUE, 1 ), skor ),0)} -> 1 | K4: {=iferror(LET( kode, B4, actual, XLOOKUP(kode, Complain!A:A, Complain!G:G), target, XLOOKUP(kode, Complain!A:A, Complain!F:F), ratio, actual/target, skor, IFS( ratio>=0.16%, 1, ratio>=0.15%, 2, ratio>=0.125%, 3, ratio>=0.1%, 4, TRUE, 5 ), skor ),0)} -> 5 | L4: =LET( nilai, C4:K4, bobot, {0.4,0.1,0.05,0.05,0.05,0.05,0.15,0.05,0.1}, SUMPRODUCT(nilai,bobot) )/5 -> 0.82 | N4: Sohib | O4: =averageif(A:A,N4,L:L) -> 0.81
A5: Bagas | B5: Cawang | C5: {=iferror(LET(kode, B5, actual, XLOOKUP(kode, Sales!A:A, Sales!G:G),target, XLOOKUP(kode, Sales!A:A, Sales!F:F),ratio, actual/target,skor, IFS(ratio>1, 5,ratio>=0.975, 4,ratio>=0.95, 3,ratio>=0.9, 2,TRUE, 1),skor),0)} -> 5 | D5: {=iferror(LET( kode, B5, actual, XLOOKUP(kode, AVG!A:A, AVG!G:G), target, XLOOKUP(kode, AVG!A:A, AVG!F:F), ratio, actual/target, skor, IFS( ratio>1, 5, ratio>=0.975, 4, ratio>=0.95, 3, ratio>=0.9, 2, TRUE, 1 ), skor ),0)} -> 5 | E5: {=iferror(LET( kode, B5, large, XLOOKUP(kode, Large!A:A, Large!G:G), small, XLOOKUP(kode, Large!A:A, Large!F:F), ratio, large/(large+small), skor, IFS( ratio<0.45, 1, ratio<=0.5, 2, ratio<=0.55, 3, ratio<=0.6, 4, TRUE, 5 ), skor ),0)} -> 2 | F5: {=iferror(LET( kode, B5, oatmilk, XLOOKUP(kode, Oatside!A:A, Oatside!G:G), drink, XLOOKUP(kode, Oatside!A:A, Oatside!F:F), ratio, oatmilk/drink, skor, IFS( ratio>5%, 5, ratio>=4%, 4, ratio>=3%, 3, ratio>=2%, 2, TRUE, 1 ), skor ),0)} -> 2 | G5: {=iferror(LET( kode, B5, actual, XLOOKUP(kode, 'Snack Platter'!A:A, 'Snack Platter'!G:G), target, XLOOKUP(kode, 'Snack Platter'!A:A, 'Snack Platter'!F:F), ratio, actual/target, skor, IFS( ratio>10%, 5, ratio>=7.5%, 4, ratio>=5%, 3, ratio>=2.5%, 2, TRUE, 1 ), skor ),0)} -> 2 | H5: {=iferror(LET( kode, B5, actual, XLOOKUP(kode, 'Bundling Asik'!A:A, 'Bundling Asik'!G:G), target, XLOOKUP(kode, 'Bundling Asik'!A:A, 'Bundling Asik'!F:F), ratio, actual/target, skor, IFS( ratio>5%, 5, ratio>=4%, 4, ratio>=3%, 3, ratio>=2%, 2, TRUE, 1 ), skor ),0)} -> 5 | I5: {=iferror(LET( kode, B5, ratio, XLOOKUP(kode, Audit!A:A, Audit!D:D), skor, IFS( ratio>90, 5, ratio>=85, 4, ratio>=80, 3, ratio>=75, 2, TRUE, 1 ), skor ),0)} -> 1 | J5: {=iferror(LET( kode, B5, ratio, XLOOKUP(kode, 'Mistery Shopper'!A:A, 'Mistery Shopper'!D:D), skor, IFS( ratio>90%, 5, ratio>=85%, 4, ratio>=80%, 3, ratio>=75%, 2, TRUE, 1 ), skor ),0)} -> 5 | K5: {=iferror(LET( kode, B5, actual, XLOOKUP(kode, Complain!A:A, Complain!G:G), target, XLOOKUP(kode, Complain!A:A, Complain!F:F), ratio, actual/target, skor, IFS( ratio>=0.16%, 1, ratio>=0.15%, 2, ratio>=0.125%, 3, ratio>=0.1%, 4, TRUE, 5 ), skor ),0)} -> 5 | L5: =LET( nilai, C5:K5, bobot, {0.4,0.1,0.05,0.05,0.05,0.05,0.15,0.05,0.1}, SUMPRODUCT(nilai,bobot) )/5 -> 0.79 | N5: Bagas | O5: =averageif(A:A,N5,L:L) -> 0.67875
A6: Bagas | B6: Kalimalang | C6: {=iferror(LET(kode, B6, actual, XLOOKUP(kode, Sales!A:A, Sales!G:G),target, XLOOKUP(kode, Sales!A:A, Sales!F:F),ratio, actual/target,skor, IFS(ratio>1, 5,ratio>=0.975, 4,ratio>=0.95, 3,ratio>=0.9, 2,TRUE, 1),skor),0)} -> 3 | D6: {=iferror(LET( kode, B6, actual, XLOOKUP(kode, AVG!A:A, AVG!G:G), target, XLOOKUP(kode, AVG!A:A, AVG!F:F), ratio, actual/target, skor, IFS( ratio>1, 5, ratio>=0.975, 4, ratio>=0.95, 3, ratio>=0.9, 2, TRUE, 1 ), skor ),0)} -> 5 | E6: {=iferror(LET( kode, B6, large, XLOOKUP(kode, Large!A:A, Large!G:G), small, XLOOKUP(kode, Large!A:A, Large!F:F), ratio, large/(large+small), skor, IFS( ratio<0.45, 1, ratio<=0.5, 2, ratio<=0.55, 3, ratio<=0.6, 4, TRUE, 5 ), skor ),0)} -> 2 | F6: {=iferror(LET( kode, B6, oatmilk, XLOOKUP(kode, Oatside!A:A, Oatside!G:G), drink, XLOOKUP(kode, Oatside!A:A, Oatside!F:F), ratio, oatmilk/drink, skor, IFS( ratio>5%, 5, ratio>=4%, 4, ratio>=3%, 3, ratio>=2%, 2, TRUE, 1 ), skor ),0)} -> 5 | G6: {=iferror(LET( kode, B6, actual, XLOOKUP(kode, 'Snack Platter'!A:A, 'Snack Platter'!G:G), target, XLOOKUP(kode, 'Snack Platter'!A:A, 'Snack Platter'!F:F), ratio, actual/target, skor, IFS( ratio>10%, 5, ratio>=7.5%, 4, ratio>=5%, 3, ratio>=2.5%, 2, TRUE, 1 ), skor ),0)} -> 3 | H6: {=iferror(LET( kode, B6, actual, XLOOKUP(kode, 'Bundling Asik'!A:A, 'Bundling Asik'!G:G), target, XLOOKUP(kode, 'Bundling Asik'!A:A, 'Bundling Asik'!F:F), ratio, actual/target, skor, IFS( ratio>5%, 5, ratio>=4%, 4, ratio>=3%, 3, ratio>=2%, 2, TRUE, 1 ), skor ),0)} -> 5 | I6: {=iferror(LET( kode, B6, ratio, XLOOKUP(kode, Audit!A:A, Audit!D:D), skor, IFS( ratio>90, 5, ratio>=85, 4, ratio>=80, 3, ratio>=75, 2, TRUE, 1 ), skor ),0)} -> 3 | J6: {=iferror(LET( kode, B6, ratio, XLOOKUP(kode, 'Mistery Shopper'!A:A, 'Mistery Shopper'!D:D), skor, IFS( ratio>90%, 5, ratio>=85%, 4, ratio>=80%, 3, ratio>=75%, 2, TRUE, 1 ), skor ),0)} -> 5 | K6: {=iferror(LET( kode, B6, actual, XLOOKUP(kode, Complain!A:A, Complain!G:G), target, XLOOKUP(kode, Complain!A:A, Complain!F:F), ratio, actual/target, skor, IFS( ratio>=0.16%, 1, ratio>=0.15%, 2, ratio>=0.125%, 3, ratio>=0.1%, 4, TRUE, 5 ), skor ),0)} -> 5 | L6: =LET( nilai, C6:K6, bobot, {0.4,0.1,0.05,0.05,0.05,0.05,0.15,0.05,0.1}, SUMPRODUCT(nilai,bobot) )/5 -> 0.73 | N6: Ryan | O6: =averageif(A:A,N6,L:L) -> 0.57
A7: Bagas | B7: Cilandak Barat | C7: {=iferror(LET(kode, B7, actual, XLOOKUP(kode, Sales!A:A, Sales!G:G),target, XLOOKUP(kode, Sales!A:A, Sales!F:F),ratio, actual/target,skor, IFS(ratio>1, 5,ratio>=0.975, 4,ratio>=0.95, 3,ratio>=0.9, 2,TRUE, 1),skor),0)} -> 1 | D7: {=iferror(LET( kode, B7, actual, XLOOKUP(kode, AVG!A:A, AVG!G:G), target, XLOOKUP(kode, AVG!A:A, AVG!F:F), ratio, actual/target, skor, IFS( ratio>1, 5, ratio>=0.975, 4, ratio>=0.95, 3, ratio>=0.9, 2, TRUE, 1 ), skor ),0)} -> 5 | E7: {=iferror(LET( kode, B7, large, XLOOKUP(kode, Large!A:A, Large!G:G), small, XLOOKUP(kode, Large!A:A, Large!F:F), ratio, large/(large+small), skor, IFS( ratio<0.45, 1, ratio<=0.5, 2, ratio<=0.55, 3, ratio<=0.6, 4, TRUE, 5 ), skor ),0)} -> 2 | F7: {=iferror(LET( kode, B7, oatmilk, XLOOKUP(kode, Oatside!A:A, Oatside!G:G), drink, XLOOKUP(kode, Oatside!A:A, Oatside!F:F), ratio, oatmilk/drink, skor, IFS( ratio>5%, 5, ratio>=4%, 4, ratio>=3%, 3, ratio>=2%, 2, TRUE, 1 ), skor ),0)} -> 5 | G7: {=iferror(LET( kode, B7, actual, XLOOKUP(kode, 'Snack Platter'!A:A, 'Snack Platter'!G:G), target, XLOOKUP(kode, 'Snack Platter'!A:A, 'Snack Platter'!F:F), ratio, actual/target, skor, IFS( ratio>10%, 5, ratio>=7.5%, 4, ratio>=5%, 3, ratio>=2.5%, 2, TRUE, 1 ), skor ),0)} -> 5 | H7: {=iferror(LET( kode, B7, actual, XLOOKUP(kode, 'Bundling Asik'!A:A, 'Bundling Asik'!G:G), target, XLOOKUP(kode, 'Bundling Asik'!A:A, 'Bundling Asik'!F:F), ratio, actual/target, skor, IFS( ratio>5%, 5, ratio>=4%, 4, ratio>=3%, 3, ratio>=2%, 2, TRUE, 1 ), skor ),0)} -> 5 | I7: {=iferror(LET( kode, B7, ratio, XLOOKUP(kode, Audit!A:A, Audit!D:D), skor, IFS( ratio>90, 5, ratio>=85, 4, ratio>=80, 3, ratio>=75, 2, TRUE, 1 ), skor ),0)} -> 3 | J7: {=iferror(LET( kode, B7, ratio, XLOOKUP(kode, 'Mistery Shopper'!A:A, 'Mistery Shopper'!D:D), skor, IFS( ratio>90%, 5, ratio>=85%, 4, ratio>=80%, 3, ratio>=75%, 2, TRUE, 1 ), skor ),0)} -> 5 | K7: {=iferror(LET( kode, B7, actual, XLOOKUP(kode, Complain!A:A, Complain!G:G), target, XLOOKUP(kode, Complain!A:A, Complain!F:F), ratio, actual/target, skor, IFS( ratio>=0.16%, 1, ratio>=0.15%, 2, ratio>=0.125%, 3, ratio>=0.1%, 4, TRUE, 5 ), skor ),0)} -> 5 | L7: =LET( nilai, C7:K7, bobot, {0.4,0.1,0.05,0.05,0.05,0.05,0.15,0.05,0.1}, SUMPRODUCT(nilai,bobot) )/5 -> 0.59 | N7: Ismail | O7: =averageif(A:A,N7,L:L) -> 0.475
A8: Bagas | B8: Kemang Utara | C8: {=iferror(LET(kode, B8, actual, XLOOKUP(kode, Sales!A:A, Sales!G:G),target, XLOOKUP(kode, Sales!A:A, Sales!F:F),ratio, actual/target,skor, IFS(ratio>1, 5,ratio>=0.975, 4,ratio>=0.95, 3,ratio>=0.9, 2,TRUE, 1),skor),0)} -> 1 | D8: {=iferror(LET( kode, B8, actual, XLOOKUP(kode, AVG!A:A, AVG!G:G), target, XLOOKUP(kode, AVG!A:A, AVG!F:F), ratio, actual/target, skor, IFS( ratio>1, 5, ratio>=0.975, 4, ratio>=0.95, 3, ratio>=0.9, 2, TRUE, 1 ), skor ),0)} -> 5 | E8: {=iferror(LET( kode, B8, large, XLOOKUP(kode, Large!A:A, Large!G:G), small, XLOOKUP(kode, Large!A:A, Large!F:F), ratio, large/(large+small), skor, IFS( ratio<0.45, 1, ratio<=0.5, 2, ratio<=0.55, 3, ratio<=0.6, 4, TRUE, 5 ), skor ),0)} -> 1 | F8: {=iferror(LET( kode, B8, oatmilk, XLOOKUP(kode, Oatside!A:A, Oatside!G:G), drink, XLOOKUP(kode, Oatside!A:A, Oatside!F:F), ratio, oatmilk/drink, skor, IFS( ratio>5%, 5, ratio>=4%, 4, ratio>=3%, 3, ratio>=2%, 2, TRUE, 1 ), skor ),0)} -> 2 | G8: {=iferror(LET( kode, B8, actual, XLOOKUP(kode, 'Snack Platter'!A:A, 'Snack Platter'!G:G), target, XLOOKUP(kode, 'Snack Platter'!A:A, 'Snack Platter'!F:F), ratio, actual/target, skor, IFS( ratio>10%, 5, ratio>=7.5%, 4, ratio>=5%, 3, ratio>=2.5%, 2, TRUE, 1 ), skor ),0)} -> 3 | H8: {=iferror(LET( kode, B8, actual, XLOOKUP(kode, 'Bundling Asik'!A:A, 'Bundling Asik'!G:G), target, XLOOKUP(kode, 'Bundling Asik'!A:A, 'Bundling Asik'!F:F), ratio, actual/target, skor, IFS( ratio>5%, 5, ratio>=4%, 4, ratio>=3%, 3, ratio>=2%, 2, TRUE, 1 ), skor ),0)} -> 5 | I8: {=iferror(LET( kode, B8, ratio, XLOOKUP(kode, Audit!A:A, Audit!D:D), skor, IFS( ratio>90, 5, ratio>=85, 4, ratio>=80, 3, ratio>=75, 2, TRUE, 1 ), skor ),0)} -> 2 | J8: {=iferror(LET( kode, B8, ratio, XLOOKUP(kode, 'Mistery Shopper'!A:A, 'Mistery Shopper'!D:D), skor, IFS( ratio>90%, 5, ratio>=85%, 4, ratio>=80%, 3, ratio>=75%, 2, TRUE, 1 ), skor ),0)} -> 1 | K8: {=iferror(LET( kode, B8, actual, XLOOKUP(kode, Complain!A:A, Complain!G:G), target, XLOOKUP(kode, Complain!A:A, Complain!F:F), ratio, actual/target, skor, IFS( ratio>=0.16%, 1, ratio>=0.15%, 2, ratio>=0.125%, 3, ratio>=0.1%, 4, TRUE, 5 ), skor ),0)} -> 5 | L8: =LET( nilai, C8:K8, bobot, {0.4,0.1,0.05,0.05,0.05,0.05,0.15,0.05,0.1}, SUMPRODUCT(nilai,bobot) )/5 -> 0.46
A9: Bagas | B9: Kayu Putih | C9: {=iferror(LET(kode, B9, actual, XLOOKUP(kode, Sales!A:A, Sales!G:G),target, XLOOKUP(kode, Sales!A:A, Sales!F:F),ratio, actual/target,skor, IFS(ratio>1, 5,ratio>=0.975, 4,ratio>=0.95, 3,ratio>=0.9, 2,TRUE, 1),skor),0)} -> 1 | D9: {=iferror(LET( kode, B9, actual, XLOOKUP(kode, AVG!A:A, AVG!G:G), target, XLOOKUP(kode, AVG!A:A, AVG!F:F), ratio, actual/target, skor, IFS( ratio>1, 5, ratio>=0.975, 4, ratio>=0.95, 3, ratio>=0.9, 2, TRUE, 1 ), skor ),0)} -> 5 | E9: {=iferror(LET( kode, B9, large, XLOOKUP(kode, Large!A:A, Large!G:G), small, XLOOKUP(kode, Large!A:A, Large!F:F), ratio, large/(large+small), skor, IFS( ratio<0.45, 1, ratio<=0.5, 2, ratio<=0.55, 3, ratio<=0.6, 4, TRUE, 5 ), skor ),0)} -> 1 | F9: {=iferror(LET( kode, B9, oatmilk, XLOOKUP(kode, Oatside!A:A, Oatside!G:G), drink, XLOOKUP(kode, Oatside!A:A, Oatside!F:F), ratio, oatmilk/drink, skor, IFS( ratio>5%, 5, ratio>=4%, 4, ratio>=3%, 3, ratio>=2%, 2, TRUE, 1 ), skor ),0)} -> 1 | G9: {=iferror(LET( kode, B9, actual, XLOOKUP(kode, 'Snack Platter'!A:A, 'Snack Platter'!G:G), target, XLOOKUP(kode, 'Snack Platter'!A:A, 'Snack Platter'!F:F), ratio, actual/target, skor, IFS( ratio>10%, 5, ratio>=7.5%, 4, ratio>=5%, 3, ratio>=2.5%, 2, TRUE, 1 ), skor ),0)} -> 1 | H9: {=iferror(LET( kode, B9, actual, XLOOKUP(kode, 'Bundling Asik'!A:A, 'Bundling Asik'!G:G), target, XLOOKUP(kode, 'Bundling Asik'!A:A, 'Bundling Asik'!F:F), ratio, actual/target, skor, IFS( ratio>5%, 5, ratio>=4%, 4, ratio>=3%, 3, ratio>=2%, 2, TRUE, 1 ), skor ),0)} -> 4 | I9: {=iferror(LET( kode, B9, ratio, XLOOKUP(kode, Audit!A:A, Audit!D:D), skor, IFS( ratio>90, 5, ratio>=85, 4, ratio>=80, 3, ratio>=75, 2, TRUE, 1 ), skor ),0)} -> 1 | J9: {=iferror(LET( kode, B9, ratio, XLOOKUP(kode, 'Mistery Shopper'!A:A, 'Mistery Shopper'!D:D), skor, IFS( ratio>90%, 5, ratio>=85%, 4, ratio>=80%, 3, ratio>=75%, 2, TRUE, 1 ), skor ),0)} -> 1 | K9: {=iferror(LET( kode, B9, actual, XLOOKUP(kode, Complain!A:A, Complain!G:G), target, XLOOKUP(kode, Complain!A:A, Complain!F:F), ratio, actual/target, skor, IFS( ratio>=0.16%, 1, ratio>=0.15%, 2, ratio>=0.125%, 3, ratio>=0.1%, 4, TRUE, 5 ), skor ),0)} -> 1 | L9: =LET( nilai, C9:K9, bobot, {0.4,0.1,0.05,0.05,0.05,0.05,0.15,0.05,0.1}, SUMPRODUCT(nilai,bobot) )/5 -> 0.31
A10: Ismail | B10: Margorejo | C10: {=iferror(LET(kode, B10, actual, XLOOKUP(kode, Sales!A:A, Sales!G:G),target, XLOOKUP(kode, Sales!A:A, Sales!F:F),ratio, actual/target,skor, IFS(ratio>1, 5,ratio>=0.975, 4,ratio>=0.95, 3,ratio>=0.9, 2,TRUE, 1),skor),0)} -> 1 | D10: {=iferror(LET( kode, B10, actual, XLOOKUP(kode, AVG!A:A, AVG!G:G), target, XLOOKUP(kode, AVG!A:A, AVG!F:F), ratio, actual/target, skor, IFS( ratio>1, 5, ratio>=0.975, 4, ratio>=0.95, 3, ratio>=0.9, 2, TRUE, 1 ), skor ),0)} -> 3 | E10: {=iferror(LET( kode, B10, large, XLOOKUP(kode, Large!A:A, Large!G:G), small, XLOOKUP(kode, Large!A:A, Large!F:F), ratio, large/(large+small), skor, IFS( ratio<0.45, 1, ratio<=0.5, 2, ratio<=0.55, 3, ratio<=0.6, 4, TRUE, 5 ), skor ),0)} -> 1 | F10: {=iferror(LET( kode, B10, oatmilk, XLOOKUP(kode, Oatside!A:A, Oatside!G:G), drink, XLOOKUP(kode, Oatside!A:A, Oatside!F:F), ratio, oatmilk/drink, skor, IFS( ratio>5%, 5, ratio>=4%, 4, ratio>=3%, 3, ratio>=2%, 2, TRUE, 1 ), skor ),0)} -> 5 | G10: {=iferror(LET( kode, B10, actual, XLOOKUP(kode, 'Snack Platter'!A:A, 'Snack Platter'!G:G), target, XLOOKUP(kode, 'Snack Platter'!A:A, 'Snack Platter'!F:F), ratio, actual/target, skor, IFS( ratio>10%, 5, ratio>=7.5%, 4, ratio>=5%, 3, ratio>=2.5%, 2, TRUE, 1 ), skor ),0)} -> 2 | H10: {=iferror(LET( kode, B10, actual, XLOOKUP(kode, 'Bundling Asik'!A:A, 'Bundling Asik'!G:G), target, XLOOKUP(kode, 'Bundling Asik'!A:A, 'Bundling Asik'!F:F), ratio, actual/target, skor, IFS( ratio>5%, 5, ratio>=4%, 4, ratio>=3%, 3, ratio>=2%, 2, TRUE, 1 ), skor ),0)} -> 5 | I10: {=iferror(LET( kode, B10, ratio, XLOOKUP(kode, Audit!A:A, Audit!D:D), skor, IFS( ratio>90, 5, ratio>=85, 4, ratio>=80, 3, ratio>=75, 2, TRUE, 1 ), skor ),0)} -> 2 | J10: {=iferror(LET( kode, B10, ratio, XLOOKUP(kode, 'Mistery Shopper'!A:A, 'Mistery Shopper'!D:D), skor, IFS( ratio>90%, 5, ratio>=85%, 4, ratio>=80%, 3, ratio>=75%, 2, TRUE, 1 ), skor ),0)} -> 5 | K10: {=iferror(LET( kode, B10, actual, XLOOKUP(kode, Complain!A:A, Complain!G:G), target, XLOOKUP(kode, Complain!A:A, Complain!F:F), ratio, actual/target, skor, IFS( ratio>=0.16%, 1, ratio>=0.15%, 2, ratio>=0.125%, 3, ratio>=0.1%, 4, TRUE, 5 ), skor ),0)} -> 5 | L10: =LET( nilai, C10:K10, bobot, {0.4,0.1,0.05,0.05,0.05,0.05,0.15,0.05,0.1}, SUMPRODUCT(nilai,bobot) )/5 -> 0.48
A11: Ismail | B11: Citraland | C11: {=iferror(LET(kode, B11, actual, XLOOKUP(kode, Sales!A:A, Sales!G:G),target, XLOOKUP(kode, Sales!A:A, Sales!F:F),ratio, actual/target,skor, IFS(ratio>1, 5,ratio>=0.975, 4,ratio>=0.95, 3,ratio>=0.9, 2,TRUE, 1),skor),0)} -> 1 | D11: {=iferror(LET( kode, B11, actual, XLOOKUP(kode, AVG!A:A, AVG!G:G), target, XLOOKUP(kode, AVG!A:A, AVG!F:F), ratio, actual/target, skor, IFS( ratio>1, 5, ratio>=0.975, 4, ratio>=0.95, 3, ratio>=0.9, 2, TRUE, 1 ), skor ),0)} -> 4 | E11: {=iferror(LET( kode, B11, large, XLOOKUP(kode, Large!A:A, Large!G:G), small, XLOOKUP(kode, Large!A:A, Large!F:F), ratio, large/(large+small), skor, IFS( ratio<0.45, 1, ratio<=0.5, 2, ratio<=0.55, 3, ratio<=0.6, 4, TRUE, 5 ), skor ),0)} -> 3 | F11: {=iferror(LET( kode, B11, oatmilk, XLOOKUP(kode, Oatside!A:A, Oatside!G:G), drink, XLOOKUP(kode, Oatside!A:A, Oatside!F:F), ratio, oatmilk/drink, skor, IFS( ratio>5%, 5, ratio>=4%, 4, ratio>=3%, 3, ratio>=2%, 2, TRUE, 1 ), skor ),0)} -> 5 | G11: {=iferror(LET( kode, B11, actual, XLOOKUP(kode, 'Snack Platter'!A:A, 'Snack Platter'!G:G), target, XLOOKUP(kode, 'Snack Platter'!A:A, 'Snack Platter'!F:F), ratio, actual/target, skor, IFS( ratio>10%, 5, ratio>=7.5%, 4, ratio>=5%, 3, ratio>=2.5%, 2, TRUE, 1 ), skor ),0)} -> 2 | H11: {=iferror(LET( kode, B11, actual, XLOOKUP(kode, 'Bundling Asik'!A:A, 'Bundling Asik'!G:G), target, XLOOKUP(kode, 'Bundling Asik'!A:A, 'Bundling Asik'!F:F), ratio, actual/target, skor, IFS( ratio>5%, 5, ratio>=4%, 4, ratio>=3%, 3, ratio>=2%, 2, TRUE, 1 ), skor ),0)} -> 3 | I11: {=iferror(LET( kode, B11, ratio, XLOOKUP(kode, Audit!A:A, Audit!D:D), skor, IFS( ratio>90, 5, ratio>=85, 4, ratio>=80, 3, ratio>=75, 2, TRUE, 1 ), skor ),0)} -> 1 | J11: {=iferror(LET( kode, B11, ratio, XLOOKUP(kode, 'Mistery Shopper'!A:A, 'Mistery Shopper'!D:D), skor, IFS( ratio>90%, 5, ratio>=85%, 4, ratio>=80%, 3, ratio>=75%, 2, TRUE, 1 ), skor ),0)} -> 5 | K11: {=iferror(LET( kode, B11, actual, XLOOKUP(kode, Complain!A:A, Complain!G:G), target, XLOOKUP(kode, Complain!A:A, Complain!F:F), ratio, actual/target, skor, IFS( ratio>=0.16%, 1, ratio>=0.15%, 2, ratio>=0.125%, 3, ratio>=0.1%, 4, TRUE, 5 ), skor ),0)} -> 5 | L11: =LET( nilai, C11:K11, bobot, {0.4,0.1,0.05,0.05,0.05,0.05,0.15,0.05,0.1}, SUMPRODUCT(nilai,bobot) )/5 -> 0.47
A12: Nadine | B12: Kranggan | C12: {=iferror(LET(kode, B12, actual, XLOOKUP(kode, Sales!A:A, Sales!G:G),target, XLOOKUP(kode, Sales!A:A, Sales!F:F),ratio, actual/target,skor, IFS(ratio>1, 5,ratio>=0.975, 4,ratio>=0.95, 3,ratio>=0.9, 2,TRUE, 1),skor),0)} -> 5 | D12: {=iferror(LET( kode, B12, actual, XLOOKUP(kode, AVG!A:A, AVG!G:G), target, XLOOKUP(kode, AVG!A:A, AVG!F:F), ratio, actual/target, skor, IFS( ratio>1, 5, ratio>=0.975, 4, ratio>=0.95, 3, ratio>=0.9, 2, TRUE, 1 ), skor ),0)} -> 5 | E12: {=iferror(LET( kode, B12, large, XLOOKUP(kode, Large!A:A, Large!G:G), small, XLOOKUP(kode, Large!A:A, Large!F:F), ratio, large/(large+small), skor, IFS( ratio<0.45, 1, ratio<=0.5, 2, ratio<=0.55, 3, ratio<=0.6, 4, TRUE, 5 ), skor ),0)} -> 5 | F12: {=iferror(LET( kode, B12, oatmilk, XLOOKUP(kode, Oatside!A:A, Oatside!G:G), drink, XLOOKUP(kode, Oatside!A:A, Oatside!F:F), ratio, oatmilk/drink, skor, IFS( ratio>5%, 5, ratio>=4%, 4, ratio>=3%, 3, ratio>=2%, 2, TRUE, 1 ), skor ),0)} -> 5 | G12: {=iferror(LET( kode, B12, actual, XLOOKUP(kode, 'Snack Platter'!A:A, 'Snack Platter'!G:G), target, XLOOKUP(kode, 'Snack Platter'!A:A, 'Snack Platter'!F:F), ratio, actual/target, skor, IFS( ratio>10%, 5, ratio>=7.5%, 4, ratio>=5%, 3, ratio>=2.5%, 2, TRUE, 1 ), skor ),0)} -> 5 | H12: {=iferror(LET( kode, B12, actual, XLOOKUP(kode, 'Bundling Asik'!A:A, 'Bundling Asik'!G:G), target, XLOOKUP(kode, 'Bundling Asik'!A:A, 'Bundling Asik'!F:F), ratio, actual/target, skor, IFS( ratio>5%, 5, ratio>=4%, 4, ratio>=3%, 3, ratio>=2%, 2, TRUE, 1 ), skor ),0)} -> 5 | I12: {=iferror(LET( kode, B12, ratio, XLOOKUP(kode, Audit!A:A, Audit!D:D), skor, IFS( ratio>90, 5, ratio>=85, 4, ratio>=80, 3, ratio>=75, 2, TRUE, 1 ), skor ),0)} -> 4 | J12: {=iferror(LET( kode, B12, ratio, XLOOKUP(kode, 'Mistery Shopper'!A:A, 'Mistery Shopper'!D:D), skor, IFS( ratio>90%, 5, ratio>=85%, 4, ratio>=80%, 3, ratio>=75%, 2, TRUE, 1 ), skor ),0)} -> 5 | K12: {=iferror(LET( kode, B12, actual, XLOOKUP(kode, Complain!A:A, Complain!G:G), target, XLOOKUP(kode, Complain!A:A, Complain!F:F), ratio, actual/target, skor, IFS( ratio>=0.16%, 1, ratio>=0.15%, 2, ratio>=0.125%, 3, ratio>=0.1%, 4, TRUE, 5 ), skor ),0)} -> 5 | L12: =LET( nilai, C12:K12, bobot, {0.4,0.1,0.05,0.05,0.05,0.05,0.15,0.05,0.1}, SUMPRODUCT(nilai,bobot) )/5 -> 0.97
A13: Nadine | B13: Kota Wisata | C13: {=iferror(LET(kode, B13, actual, XLOOKUP(kode, Sales!A:A, Sales!G:G),target, XLOOKUP(kode, Sales!A:A, Sales!F:F),ratio, actual/target,skor, IFS(ratio>1, 5,ratio>=0.975, 4,ratio>=0.95, 3,ratio>=0.9, 2,TRUE, 1),skor),0)} -> 5 | D13: {=iferror(LET( kode, B13, actual, XLOOKUP(kode, AVG!A:A, AVG!G:G), target, XLOOKUP(kode, AVG!A:A, AVG!F:F), ratio, actual/target, skor, IFS( ratio>1, 5, ratio>=0.975, 4, ratio>=0.95, 3, ratio>=0.9, 2, TRUE, 1 ), skor ),0)} -> 5 | E13: {=iferror(LET( kode, B13, large, XLOOKUP(kode, Large!A:A, Large!G:G), small, XLOOKUP(kode, Large!A:A, Large!F:F), ratio, large/(large+small), skor, IFS( ratio<0.45, 1, ratio<=0.5, 2, ratio<=0.55, 3, ratio<=0.6, 4, TRUE, 5 ), skor ),0)} -> 5 | F13: {=iferror(LET( kode, B13, oatmilk, XLOOKUP(kode, Oatside!A:A, Oatside!G:G), drink, XLOOKUP(kode, Oatside!A:A, Oatside!F:F), ratio, oatmilk/drink, skor, IFS( ratio>5%, 5, ratio>=4%, 4, ratio>=3%, 3, ratio>=2%, 2, TRUE, 1 ), skor ),0)} -> 5 | G13: {=iferror(LET( kode, B13, actual, XLOOKUP(kode, 'Snack Platter'!A:A, 'Snack Platter'!G:G), target, XLOOKUP(kode, 'Snack Platter'!A:A, 'Snack Platter'!F:F), ratio, actual/target, skor, IFS( ratio>10%, 5, ratio>=7.5%, 4, ratio>=5%, 3, ratio>=2.5%, 2, TRUE, 1 ), skor ),0)} -> 5 | H13: {=iferror(LET( kode, B13, actual, XLOOKUP(kode, 'Bundling Asik'!A:A, 'Bundling Asik'!G:G), target, XLOOKUP(kode, 'Bundling Asik'!A:A, 'Bundling Asik'!F:F), ratio, actual/target, skor, IFS( ratio>5%, 5, ratio>=4%, 4, ratio>=3%, 3, ratio>=2%, 2, TRUE, 1 ), skor ),0)} -> 5 | I13: {=iferror(LET( kode, B13, ratio, XLOOKUP(kode, Audit!A:A, Audit!D:D), skor, IFS( ratio>90, 5, ratio>=85, 4, ratio>=80, 3, ratio>=75, 2, TRUE, 1 ), skor ),0)} -> 3 | J13: {=iferror(LET( kode, B13, ratio, XLOOKUP(kode, 'Mistery Shopper'!A:A, 'Mistery Shopper'!D:D), skor, IFS( ratio>90%, 5, ratio>=85%, 4, ratio>=80%, 3, ratio>=75%, 2, TRUE, 1 ), skor ),0)} -> 5 | K13: {=iferror(LET( kode, B13, actual, XLOOKUP(kode, Complain!A:A, Complain!G:G), target, XLOOKUP(kode, Complain!A:A, Complain!F:F), ratio, actual/target, skor, IFS( ratio>=0.16%, 1, ratio>=0.15%, 2, ratio>=0.125%, 3, ratio>=0.1%, 4, TRUE, 5 ), skor ),0)} -> 4 | L13: =LET( nilai, C13:K13, bobot, {0.4,0.1,0.05,0.05,0.05,0.05,0.15,0.05,0.1}, SUMPRODUCT(nilai,bobot) )/5 -> 0.92
A14: Nadine | B14: Lenteng Agung | C14: {=iferror(LET(kode, B14, actual, XLOOKUP(kode, Sales!A:A, Sales!G:G),target, XLOOKUP(kode, Sales!A:A, Sales!F:F),ratio, actual/target,skor, IFS(ratio>1, 5,ratio>=0.975, 4,ratio>=0.95, 3,ratio>=0.9, 2,TRUE, 1),skor),0)} -> 5 | D14: {=iferror(LET( kode, B14, actual, XLOOKUP(kode, AVG!A:A, AVG!G:G), target, XLOOKUP(kode, AVG!A:A, AVG!F:F), ratio, actual/target, skor, IFS( ratio>1, 5, ratio>=0.975, 4, ratio>=0.95, 3, ratio>=0.9, 2, TRUE, 1 ), skor ),0)} -> 5 | E14: {=iferror(LET( kode, B14, large, XLOOKUP(kode, Large!A:A, Large!G:G), small, XLOOKUP(kode, Large!A:A, Large!F:F), ratio, large/(large+small), skor, IFS( ratio<0.45, 1, ratio<=0.5, 2, ratio<=0.55, 3, ratio<=0.6, 4, TRUE, 5 ), skor ),0)} -> 3 | F14: {=iferror(LET( kode, B14, oatmilk, XLOOKUP(kode, Oatside!A:A, Oatside!G:G), drink, XLOOKUP(kode, Oatside!A:A, Oatside!F:F), ratio, oatmilk/drink, skor, IFS( ratio>5%, 5, ratio>=4%, 4, ratio>=3%, 3, ratio>=2%, 2, TRUE, 1 ), skor ),0)} -> 5 | G14: {=iferror(LET( kode, B14, actual, XLOOKUP(kode, 'Snack Platter'!A:A, 'Snack Platter'!G:G), target, XLOOKUP(kode, 'Snack Platter'!A:A, 'Snack Platter'!F:F), ratio, actual/target, skor, IFS( ratio>10%, 5, ratio>=7.5%, 4, ratio>=5%, 3, ratio>=2.5%, 2, TRUE, 1 ), skor ),0)} -> 5 | H14: {=iferror(LET( kode, B14, actual, XLOOKUP(kode, 'Bundling Asik'!A:A, 'Bundling Asik'!G:G), target, XLOOKUP(kode, 'Bundling Asik'!A:A, 'Bundling Asik'!F:F), ratio, actual/target, skor, IFS( ratio>5%, 5, ratio>=4%, 4, ratio>=3%, 3, ratio>=2%, 2, TRUE, 1 ), skor ),0)} -> 5 | I14: {=iferror(LET( kode, B14, ratio, XLOOKUP(kode, Audit!A:A, Audit!D:D), skor, IFS( ratio>90, 5, ratio>=85, 4, ratio>=80, 3, ratio>=75, 2, TRUE, 1 ), skor ),0)} -> 4 | J14: {=iferror(LET( kode, B14, ratio, XLOOKUP(kode, 'Mistery Shopper'!A:A, 'Mistery Shopper'!D:D), skor, IFS( ratio>90%, 5, ratio>=85%, 4, ratio>=80%, 3, ratio>=75%, 2, TRUE, 1 ), skor ),0)} -> 1 | K14: {=iferror(LET( kode, B14, actual, XLOOKUP(kode, Complain!A:A, Complain!G:G), target, XLOOKUP(kode, Complain!A:A, Complain!F:F), ratio, actual/target, skor, IFS( ratio>=0.16%, 1, ratio>=0.15%, 2, ratio>=0.125%, 3, ratio>=0.1%, 4, TRUE, 5 ), skor ),0)} -> 5 | L14: =LET( nilai, C14:K14, bobot, {0.4,0.1,0.05,0.05,0.05,0.05,0.15,0.05,0.1}, SUMPRODUCT(nilai,bobot) )/5 -> 0.91
A15: Nadine | B15: Pekayon | C15: {=iferror(LET(kode, B15, actual, XLOOKUP(kode, Sales!A:A, Sales!G:G),target, XLOOKUP(kode, Sales!A:A, Sales!F:F),ratio, actual/target,skor, IFS(ratio>1, 5,ratio>=0.975, 4,ratio>=0.95, 3,ratio>=0.9, 2,TRUE, 1),skor),0)} -> 5 | D15: {=iferror(LET( kode, B15, actual, XLOOKUP(kode, AVG!A:A, AVG!G:G), target, XLOOKUP(kode, AVG!A:A, AVG!F:F), ratio, actual/target, skor, IFS( ratio>1, 5, ratio>=0.975, 4, ratio>=0.95, 3, ratio>=0.9, 2, TRUE, 1 ), skor ),0)} -> 5 | E15: {=iferror(LET( kode, B15, large, XLOOKUP(kode, Large!A:A, Large!G:G), small, XLOOKUP(kode, Large!A:A, Large!F:F), ratio, large/(large+small), skor, IFS( ratio<0.45, 1, ratio<=0.5, 2, ratio<=0.55, 3, ratio<=0.6, 4, TRUE, 5 ), skor ),0)} -> 3 | F15: {=iferror(LET( kode, B15, oatmilk, XLOOKUP(kode, Oatside!A:A, Oatside!G:G), drink, XLOOKUP(kode, Oatside!A:A, Oatside!F:F), ratio, oatmilk/drink, skor, IFS( ratio>5%, 5, ratio>=4%, 4, ratio>=3%, 3, ratio>=2%, 2, TRUE, 1 ), skor ),0)} -> 4 | G15: {=iferror(LET( kode, B15, actual, XLOOKUP(kode, 'Snack Platter'!A:A, 'Snack Platter'!G:G), target, XLOOKUP(kode, 'Snack Platter'!A:A, 'Snack Platter'!F:F), ratio, actual/target, skor, IFS( ratio>10%, 5, ratio>=7.5%, 4, ratio>=5%, 3, ratio>=2.5%, 2, TRUE, 1 ), skor ),0)} -> 3 | H15: {=iferror(LET( kode, B15, actual, XLOOKUP(kode, 'Bundling Asik'!A:A, 'Bundling Asik'!G:G), target, XLOOKUP(kode, 'Bundling Asik'!A:A, 'Bundling Asik'!F:F), ratio, actual/target, skor, IFS( ratio>5%, 5, ratio>=4%, 4, ratio>=3%, 3, ratio>=2%, 2, TRUE, 1 ), skor ),0)} -> 5 | I15: {=iferror(LET( kode, B15, ratio, XLOOKUP(kode, Audit!A:A, Audit!D:D), skor, IFS( ratio>90, 5, ratio>=85, 4, ratio>=80, 3, ratio>=75, 2, TRUE, 1 ), skor ),0)} -> 2 | J15: {=iferror(LET( kode, B15, ratio, XLOOKUP(kode, 'Mistery Shopper'!A:A, 'Mistery Shopper'!D:D), skor, IFS( ratio>90%, 5, ratio>=85%, 4, ratio>=80%, 3, ratio>=75%, 2, TRUE, 1 ), skor ),0)} -> 5 | K15: {=iferror(LET( kode, B15, actual, XLOOKUP(kode, Complain!A:A, Complain!G:G), target, XLOOKUP(kode, Complain!A:A, Complain!F:F), ratio, actual/target, skor, IFS( ratio>=0.16%, 1, ratio>=0.15%, 2, ratio>=0.125%, 3, ratio>=0.1%, 4, TRUE, 5 ), skor ),0)} -> 5 | L15: =LET( nilai, C15:K15, bobot, {0.4,0.1,0.05,0.05,0.05,0.05,0.15,0.05,0.1}, SUMPRODUCT(nilai,bobot) )/5 -> 0.86
A16: Nadine | B16: Margonda | C16: {=iferror(LET(kode, B16, actual, XLOOKUP(kode, Sales!A:A, Sales!G:G),target, XLOOKUP(kode, Sales!A:A, Sales!F:F),ratio, actual/target,skor, IFS(ratio>1, 5,ratio>=0.975, 4,ratio>=0.95, 3,ratio>=0.9, 2,TRUE, 1),skor),0)} -> 5 | D16: {=iferror(LET( kode, B16, actual, XLOOKUP(kode, AVG!A:A, AVG!G:G), target, XLOOKUP(kode, AVG!A:A, AVG!F:F), ratio, actual/target, skor, IFS( ratio>1, 5, ratio>=0.975, 4, ratio>=0.95, 3, ratio>=0.9, 2, TRUE, 1 ), skor ),0)} -> 5 | E16: {=iferror(LET( kode, B16, large, XLOOKUP(kode, Large!A:A, Large!G:G), small, XLOOKUP(kode, Large!A:A, Large!F:F), ratio, large/(large+small), skor, IFS( ratio<0.45, 1, ratio<=0.5, 2, ratio<=0.55, 3, ratio<=0.6, 4, TRUE, 5 ), skor ),0)} -> 1 | F16: {=iferror(LET( kode, B16, oatmilk, XLOOKUP(kode, Oatside!A:A, Oatside!G:G), drink, XLOOKUP(kode, Oatside!A:A, Oatside!F:F), ratio, oatmilk/drink, skor, IFS( ratio>5%, 5, ratio>=4%, 4, ratio>=3%, 3, ratio>=2%, 2, TRUE, 1 ), skor ),0)} -> 5 | G16: {=iferror(LET( kode, B16, actual, XLOOKUP(kode, 'Snack Platter'!A:A, 'Snack Platter'!G:G), target, XLOOKUP(kode, 'Snack Platter'!A:A, 'Snack Platter'!F:F), ratio, actual/target, skor, IFS( ratio>10%, 5, ratio>=7.5%, 4, ratio>=5%, 3, ratio>=2.5%, 2, TRUE, 1 ), skor ),0)} -> 5 | H16: {=iferror(LET( kode, B16, actual, XLOOKUP(kode, 'Bundling Asik'!A:A, 'Bundling Asik'!G:G), target, XLOOKUP(kode, 'Bundling Asik'!A:A, 'Bundling Asik'!F:F), ratio, actual/target, skor, IFS( ratio>5%, 5, ratio>=4%, 4, ratio>=3%, 3, ratio>=2%, 2, TRUE, 1 ), skor ),0)} -> 5 | I16: {=iferror(LET( kode, B16, ratio, XLOOKUP(kode, Audit!A:A, Audit!D:D), skor, IFS( ratio>90, 5, ratio>=85, 4, ratio>=80, 3, ratio>=75, 2, TRUE, 1 ), skor ),0)} -> 2 | J16: {=iferror(LET( kode, B16, ratio, XLOOKUP(kode, 'Mistery Shopper'!A:A, 'Mistery Shopper'!D:D), skor, IFS( ratio>90%, 5, ratio>=85%, 4, ratio>=80%, 3, ratio>=75%, 2, TRUE, 1 ), skor ),0)} -> 1 | K16: {=iferror(LET( kode, B16, actual, XLOOKUP(kode, Complain!A:A, Complain!G:G), target, XLOOKUP(kode, Complain!A:A, Complain!F:F), ratio, actual/target, skor, IFS( ratio>=0.16%, 1, ratio>=0.15%, 2, ratio>=0.125%, 3, ratio>=0.1%, 4, TRUE, 5 ), skor ),0)} -> 1 | L16: =LET( nilai, C16:K16, bobot, {0.4,0.1,0.05,0.05,0.05,0.05,0.15,0.05,0.1}, SUMPRODUCT(nilai,bobot) )/5 -> 0.75
A17: Risti | B17: Ujung Berung | C17: {=iferror(LET(kode, B17, actual, XLOOKUP(kode, Sales!A:A, Sales!G:G),target, XLOOKUP(kode, Sales!A:A, Sales!F:F),ratio, actual/target,skor, IFS(ratio>1, 5,ratio>=0.975, 4,ratio>=0.95, 3,ratio>=0.9, 2,TRUE, 1),skor),0)} -> 5 | D17: {=iferror(LET( kode, B17, actual, XLOOKUP(kode, AVG!A:A, AVG!G:G), target, XLOOKUP(kode, AVG!A:A, AVG!F:F), ratio, actual/target, skor, IFS( ratio>1, 5, ratio>=0.975, 4, ratio>=0.95, 3, ratio>=0.9, 2, TRUE, 1 ), skor ),0)} -> 5 | E17: {=iferror(LET( kode, B17, large, XLOOKUP(kode, Large!A:A, Large!G:G), small, XLOOKUP(kode, Large!A:A, Large!F:F), ratio, large/(large+small), skor, IFS( ratio<0.45, 1, ratio<=0.5, 2, ratio<=0.55, 3, ratio<=0.6, 4, TRUE, 5 ), skor ),0)} -> 2 | F17: {=iferror(LET( kode, B17, oatmilk, XLOOKUP(kode, Oatside!A:A, Oatside!G:G), drink, XLOOKUP(kode, Oatside!A:A, Oatside!F:F), ratio, oatmilk/drink, skor, IFS( ratio>5%, 5, ratio>=4%, 4, ratio>=3%, 3, ratio>=2%, 2, TRUE, 1 ), skor ),0)} -> 5 | G17: {=iferror(LET( kode, B17, actual, XLOOKUP(kode, 'Snack Platter'!A:A, 'Snack Platter'!G:G), target, XLOOKUP(kode, 'Snack Platter'!A:A, 'Snack Platter'!F:F), ratio, actual/target, skor, IFS( ratio>10%, 5, ratio>=7.5%, 4, ratio>=5%, 3, ratio>=2.5%, 2, TRUE, 1 ), skor ),0)} -> 5 | H17: {=iferror(LET( kode, B17, actual, XLOOKUP(kode, 'Bundling Asik'!A:A, 'Bundling Asik'!G:G), target, XLOOKUP(kode, 'Bundling Asik'!A:A, 'Bundling Asik'!F:F), ratio, actual/target, skor, IFS( ratio>5%, 5, ratio>=4%, 4, ratio>=3%, 3, ratio>=2%, 2, TRUE, 1 ), skor ),0)} -> 5 | I17: {=iferror(LET( kode, B17, ratio, XLOOKUP(kode, Audit!A:A, Audit!D:D), skor, IFS( ratio>90, 5, ratio>=85, 4, ratio>=80, 3, ratio>=75, 2, TRUE, 1 ), skor ),0)} -> 4 | J17: {=iferror(LET( kode, B17, ratio, XLOOKUP(kode, 'Mistery Shopper'!A:A, 'Mistery Shopper'!D:D), skor, IFS( ratio>90%, 5, ratio>=85%, 4, ratio>=80%, 3, ratio>=75%, 2, TRUE, 1 ), skor ),0)} -> 5 | K17: {=iferror(LET( kode, B17, actual, XLOOKUP(kode, Complain!A:A, Complain!G:G), target, XLOOKUP(kode, Complain!A:A, Complain!F:F), ratio, actual/target, skor, IFS( ratio>=0.16%, 1, ratio>=0.15%, 2, ratio>=0.125%, 3, ratio>=0.1%, 4, TRUE, 5 ), skor ),0)} -> 5 | L17: =LET( nilai, C17:K17, bobot, {0.4,0.1,0.05,0.05,0.05,0.05,0.15,0.05,0.1}, SUMPRODUCT(nilai,bobot) )/5 -> 0.94
A18: Risti | B18: Metro | C18: {=iferror(LET(kode, B18, actual, XLOOKUP(kode, Sales!A:A, Sales!G:G),target, XLOOKUP(kode, Sales!A:A, Sales!F:F),ratio, actual/target,skor, IFS(ratio>1, 5,ratio>=0.975, 4,ratio>=0.95, 3,ratio>=0.9, 2,TRUE, 1),skor),0)} -> 5 | D18: {=iferror(LET( kode, B18, actual, XLOOKUP(kode, AVG!A:A, AVG!G:G), target, XLOOKUP(kode, AVG!A:A, AVG!F:F), ratio, actual/target, skor, IFS( ratio>1, 5, ratio>=0.975, 4, ratio>=0.95, 3, ratio>=0.9, 2, TRUE, 1 ), skor ),0)} -> 5 | E18: {=iferror(LET( kode, B18, large, XLOOKUP(kode, Large!A:A, Large!G:G), small, XLOOKUP(kode, Large!A:A, Large!F:F), ratio, large/(large+small), skor, IFS( ratio<0.45, 1, ratio<=0.5, 2, ratio<=0.55, 3, ratio<=0.6, 4, TRUE, 5 ), skor ),0)} -> 1 | F18: {=iferror(LET( kode, B18, oatmilk, XLOOKUP(kode, Oatside!A:A, Oatside!G:G), drink, XLOOKUP(kode, Oatside!A:A, Oatside!F:F), ratio, oatmilk/drink, skor, IFS( ratio>5%, 5, ratio>=4%, 4, ratio>=3%, 3, ratio>=2%, 2, TRUE, 1 ), skor ),0)} -> 5 | G18: {=iferror(LET( kode, B18, actual, XLOOKUP(kode, 'Snack Platter'!A:A, 'Snack Platter'!G:G), target, XLOOKUP(kode, 'Snack Platter'!A:A, 'Snack Platter'!F:F), ratio, actual/target, skor, IFS( ratio>10%, 5, ratio>=7.5%, 4, ratio>=5%, 3, ratio>=2.5%, 2, TRUE, 1 ), skor ),0)} -> 3 | H18: {=iferror(LET( kode, B18, actual, XLOOKUP(kode, 'Bundling Asik'!A:A, 'Bundling Asik'!G:G), target, XLOOKUP(kode, 'Bundling Asik'!A:A, 'Bundling Asik'!F:F), ratio, actual/target, skor, IFS( ratio>5%, 5, ratio>=4%, 4, ratio>=3%, 3, ratio>=2%, 2, TRUE, 1 ), skor ),0)} -> 5 | I18: {=iferror(LET( kode, B18, ratio, XLOOKUP(kode, Audit!A:A, Audit!D:D), skor, IFS( ratio>90, 5, ratio>=85, 4, ratio>=80, 3, ratio>=75, 2, TRUE, 1 ), skor ),0)} -> 4 | J18: {=iferror(LET( kode, B18, ratio, XLOOKUP(kode, 'Mistery Shopper'!A:A, 'Mistery Shopper'!D:D), skor, IFS( ratio>90%, 5, ratio>=85%, 4, ratio>=80%, 3, ratio>=75%, 2, TRUE, 1 ), skor ),0)} -> 5 | K18: {=iferror(LET( kode, B18, actual, XLOOKUP(kode, Complain!A:A, Complain!G:G), target, XLOOKUP(kode, Complain!A:A, Complain!F:F), ratio, actual/target, skor, IFS( ratio>=0.16%, 1, ratio>=0.15%, 2, ratio>=0.125%, 3, ratio>=0.1%, 4, TRUE, 5 ), skor ),0)} -> 5 | L18: =LET( nilai, C18:K18, bobot, {0.4,0.1,0.05,0.05,0.05,0.05,0.15,0.05,0.1}, SUMPRODUCT(nilai,bobot) )/5 -> 0.91
A19: Risti | B19: Kiara Artha | C19: {=iferror(LET(kode, B19, actual, XLOOKUP(kode, Sales!A:A, Sales!G:G),target, XLOOKUP(kode, Sales!A:A, Sales!F:F),ratio, actual/target,skor, IFS(ratio>1, 5,ratio>=0.975, 4,ratio>=0.95, 3,ratio>=0.9, 2,TRUE, 1),skor),0)} -> 5 | D19: {=iferror(LET( kode, B19, actual, XLOOKUP(kode, AVG!A:A, AVG!G:G), target, XLOOKUP(kode, AVG!A:A, AVG!F:F), ratio, actual/target, skor, IFS( ratio>1, 5, ratio>=0.975, 4, ratio>=0.95, 3, ratio>=0.9, 2, TRUE, 1 ), skor ),0)} -> 5 | E19: {=iferror(LET( kode, B19, large, XLOOKUP(kode, Large!A:A, Large!G:G), small, XLOOKUP(kode, Large!A:A, Large!F:F), ratio, large/(large+small), skor, IFS( ratio<0.45, 1, ratio<=0.5, 2, ratio<=0.55, 3, ratio<=0.6, 4, TRUE, 5 ), skor ),0)} -> 1 | F19: {=iferror(LET( kode, B19, oatmilk, XLOOKUP(kode, Oatside!A:A, Oatside!G:G), drink, XLOOKUP(kode, Oatside!A:A, Oatside!F:F), ratio, oatmilk/drink, skor, IFS( ratio>5%, 5, ratio>=4%, 4, ratio>=3%, 3, ratio>=2%, 2, TRUE, 1 ), skor ),0)} -> 5 | G19: {=iferror(LET( kode, B19, actual, XLOOKUP(kode, 'Snack Platter'!A:A, 'Snack Platter'!G:G), target, XLOOKUP(kode, 'Snack Platter'!A:A, 'Snack Platter'!F:F), ratio, actual/target, skor, IFS( ratio>10%, 5, ratio>=7.5%, 4, ratio>=5%, 3, ratio>=2.5%, 2, TRUE, 1 ), skor ),0)} -> 4 | H19: {=iferror(LET( kode, B19, actual, XLOOKUP(kode, 'Bundling Asik'!A:A, 'Bundling Asik'!G:G), target, XLOOKUP(kode, 'Bundling Asik'!A:A, 'Bundling Asik'!F:F), ratio, actual/target, skor, IFS( ratio>5%, 5, ratio>=4%, 4, ratio>=3%, 3, ratio>=2%, 2, TRUE, 1 ), skor ),0)} -> 5 | I19: {=iferror(LET( kode, B19, ratio, XLOOKUP(kode, Audit!A:A, Audit!D:D), skor, IFS( ratio>90, 5, ratio>=85, 4, ratio>=80, 3, ratio>=75, 2, TRUE, 1 ), skor ),0)} -> 3 | J19: {=iferror(LET( kode, B19, ratio, XLOOKUP(kode, 'Mistery Shopper'!A:A, 'Mistery Shopper'!D:D), skor, IFS( ratio>90%, 5, ratio>=85%, 4, ratio>=80%, 3, ratio>=75%, 2, TRUE, 1 ), skor ),0)} -> 5 | K19: {=iferror(LET( kode, B19, actual, XLOOKUP(kode, Complain!A:A, Complain!G:G), target, XLOOKUP(kode, Complain!A:A, Complain!F:F), ratio, actual/target, skor, IFS( ratio>=0.16%, 1, ratio>=0.15%, 2, ratio>=0.125%, 3, ratio>=0.1%, 4, TRUE, 5 ), skor ),0)} -> 5 | L19: =LET( nilai, C19:K19, bobot, {0.4,0.1,0.05,0.05,0.05,0.05,0.15,0.05,0.1}, SUMPRODUCT(nilai,bobot) )/5 -> 0.89
... A31: Sohib | B31: Ciumbuleuit | C31: {=iferror(LET(kode, B31, actual, XLOOKUP(kode, Sales!A:A, Sales!G:G),target, XLOOKUP(kode, Sales!A:A, Sales!F:F),ratio, actual/target,skor, IFS(ratio>1, 5,ratio>=0.975, 4,ratio>=0.95, 3,ratio>=0.9, 2,TRUE, 1),skor),0)} -> 3 | D31: {=iferror(LET( kode, B31, actual, XLOOKUP(kode, AVG!A:A, AVG!G:G), target, XLOOKUP(kode, AVG!A:A, AVG!F:F), ratio, actual/target, skor, IFS( ratio>1, 5, ratio>=0.975, 4, ratio>=0.95, 3, ratio>=0.9, 2, TRUE, 1 ), skor ),0)} -> 4 | E31: {=iferror(LET( kode, B31, large, XLOOKUP(kode, Large!A:A, Large!G:G), small, XLOOKUP(kode, Large!A:A, Large!F:F), ratio, large/(large+small), skor, IFS( ratio<0.45, 1, ratio<=0.5, 2, ratio<=0.55, 3, ratio<=0.6, 4, TRUE, 5 ), skor ),0)} -> 1 | F31: {=iferror(LET( kode, B31, oatmilk, XLOOKUP(kode, Oatside!A:A, Oatside!G:G), drink, XLOOKUP(kode, Oatside!A:A, Oatside!F:F), ratio, oatmilk/drink, skor, IFS( ratio>5%, 5, ratio>=4%, 4, ratio>=3%, 3, ratio>=2%, 2, TRUE, 1 ), skor ),0)} -> 5 | G31: {=iferror(LET( kode, B31, actual, XLOOKUP(kode, 'Snack Platter'!A:A, 'Snack Platter'!G:G), target, XLOOKUP(kode, 'Snack Platter'!A:A, 'Snack Platter'!F:F), ratio, actual/target, skor, IFS( ratio>10%, 5, ratio>=7.5%, 4, ratio>=5%, 3, ratio>=2.5%, 2, TRUE, 1 ), skor ),0)} -> 2 | H31: {=iferror(LET( kode, B31, actual, XLOOKUP(kode, 'Bundling Asik'!A:A, 'Bundling Asik'!G:G), target, XLOOKUP(kode, 'Bundling Asik'!A:A, 'Bundling Asik'!F:F), ratio, actual/target, skor, IFS( ratio>5%, 5, ratio>=4%, 4, ratio>=3%, 3, ratio>=2%, 2, TRUE, 1 ), skor ),0)} -> 5 | I31: {=iferror(LET( kode, B31, ratio, XLOOKUP(kode, Audit!A:A, Audit!D:D), skor, IFS( ratio>90, 5, ratio>=85, 4, ratio>=80, 3, ratio>=75, 2, TRUE, 1 ), skor ),0)} -> 3 | J31: {=iferror(LET( kode, B31, ratio, XLOOKUP(kode, 'Mistery Shopper'!A:A, 'Mistery Shopper'!D:D), skor, IFS( ratio>90%, 5, ratio>=85%, 4, ratio>=80%, 3, ratio>=75%, 2, TRUE, 1 ), skor ),0)} -> 5 | K31: {=iferror(LET( kode, B31, actual, XLOOKUP(kode, Complain!A:A, Complain!G:G), target, XLOOKUP(kode, Complain!A:A, Complain!F:F), ratio, actual/target, skor, IFS( ratio>=0.16%, 1, ratio>=0.15%, 2, ratio>=0.125%, 3, ratio>=0.1%, 4, TRUE, 5 ), skor ),0)} -> 5 | L31: =LET( nilai, C31:K31, bobot, {0.4,0.1,0.05,0.05,0.05,0.05,0.15,0.05,0.1}, SUMPRODUCT(nilai,bobot) )/5 -> 0.69

Sheet Sales
A1: STORE | B1: JAN | D1: FEB | F1: MAR | H1: APR | J1: MAY | L1: JUNE
A2: FILTER | B2: TARGET | C2: ACH | D2: TARGET | E2: ACH | F2: TARGET | G2: ACH | H2: TARGET | I2: ACH | J2: TARGET | K2: ACH | L2: TARGET | M2: ACH
A3: Bintaro | B3: 275000000 | C3: 113030114 | D3: 115000000 | E3: 87754076 | F3: 110000000 | G3: 102866336
A4: Buah Batu | B4: 320000000 | C4: 296807050 | D4: 305000000 | E4: 252449540 | F4: 350000000 | G4: 356629312
A5: Cawang | B5: 245000000 | C5: 210611522 | D5: 230000000 | E5: 160425281 | F5: 240000000 | G5: 245953493
A6: Cilandak Barat | B6: 105000000 | C6: 84712958 | D6: 100000000 | E6: 66837271 | F6: 105000000 | G6: 81675734
A7: Ciledug | B7: 330000000 | C7: 329784772 | D7: 310000000 | E7: 256663268 | F7: 340000000 | G7: 354749572
A8: Cimahi | B8: 340000000 | C8: 335336105 | D8: 260000000 | E8: 290748668 | F8: 280000000 | G8: 405351490
A9: Ciputat Jombang | B9: 210000000 | C9: 187113298 | D9: 195000000 | E9: 146615274 | F9: 230000000 | G9: 229863427
A10: Ciputat Juanda | B10: 185000000 | C10: 138853818 | D10: 175000000 | E10: 122437518 | F10: 210000000 | G10: 132713419
A11: Citraland | B11: 225000000 | C11: 189346845 | D11: 210000000 | E11: 154378504 | F11: 230000000 | G11: 190746962
A12: Ciumbuleuit | B12: 282000000 | C12: 228555370 | D12: 225000000 | E12: 183473662 | F12: 270000000 | G12: 256835476
A13: Jatinangor | B13: 225000000 | C13: 153420086 | D13: 240000000 | E13: 153550620 | F13: 320000000 | G13: 263235458
A14: Kalimalang | B14: 425000000 | C14: 420660123 | D14: 430000000 | E14: 322598069 | F14: 450000000 | G14: 435204393
... A32: Ujung Berung | B32: 275000000 | C32: 266147448 | D32: 220000000 | E32: 222853058 | F32: 270000000 | G32: 337834900

Sheet AVG
A1: STORE | B1: JAN | D1: FEB | F1: MAR | H1: APR | J1: MAY | L1: JUNE
A2: FILTER | B2: TARGET | C2: ACH | D2: TARGET | E2: ACH | F2: TARGET | G2: ACH | H2: TARGET | I2: ACH | J2: TARGET | K2: ACH | L2: TARGET | M2: ACH
A3: Bintaro | B3: 55000 | C3: 46343 | D3: 55000 | E3: 45468 | F3: 55000 | G3: 53548
A4: Buah Batu | B4: 55000 | C4: 56309 | D4: 55000 | E4: 55084 | F4: 55000 | G4: 68072
A5: Cawang | B5: 55000 | C5: 54478 | D5: 55000 | E5: 55568 | F5: 55000 | G5: 70534
A6: Cilandak Barat | B6: 55000 | C6: 52227 | D6: 55000 | E6: 53257 | F6: 55000 | G6: 57276
A7: Ciledug | B7: 55000 | C7: 59917 | D7: 55000 | E7: 60893 | F7: 55000 | G7: 69682
A8: Cimahi | B8: 55000 | C8: 55492 | D8: 55000 | E8: 56434 | F8: 55000 | G8: 63277
A9: Ciputat Jombang | B9: 55000 | C9: 51947 | D9: 55000 | E9: 49734 | F9: 55000 | G9: 62243
A10: Ciputat Juanda | B10: 55000 | C10: 49082 | D10: 55000 | E10: 50511 | F10: 55000 | G10: 56402
A11: Citraland | B11: 55000 | C11: 47420 | D11: 55000 | E11: 48516 | F11: 55000 | G11: 54313
A12: Ciumbuleuit | B12: 55000 | C12: 46999 | D12: 55000 | E12: 48706 | F12: 55000 | G12: 53686
A13: Jatinangor | B13: 55000 | C13: 59053 | D13: 55000 | E13: 60004 | F13: 55000 | G13: 78648
A14: Kalimalang | B14: 55000 | C14: 56785 | D14: 55000 | E14: 59203 | F14: 55000 | G14: 71544
... A32: Ujung Berung | B32: 55000 | C32: 56102 | D32: 55000 | E32: 57083 | F32: 55000 | G32: 65958

Sheet Large
A1: STORE | B1: JAN | D1: FEB | F1: MAR | H1: APR | J1: MAY | L1: JUNE | Q1: Store | R1: 45992 | S1: 46023
A2: FILTER | B2: SMALL | C2: LARGE | D2: SMALL | E2: LARGE | F2: SMALL | G2: LARGE | H2: SMALL | I2: LARGE | J2: SMALL | K2: LARGE | L2: SMALL | M2: LARGE | P2: Trainer | Q2: Buah Batu | R2: 4269 | S2: 4107
A3: Bintaro | B3: =IFERROR(XLOOKUP(A:A,Q:Q,S:S),0) -> 1601 | C3: 1039 | D3: 1141 | E3: 826 | F3: 1417 | G3: 1125 | N3: =C3/ sum(B3:C3) -> 0.39356061 | P3: Jehan | Q3: Cimahi | R3: 4879 | S3: 4030
A4: Buah Batu | B4: =IFERROR(XLOOKUP(A:A,Q:Q,S:S),0) -> 4107 | C4: 2848 | D4: 3412 | E4: 2477 | F4: 4776 | G4: 3426 | N4: =C4/ sum(B4:C4) -> 0.40948958 | P4: Jehan | Q4: Citraland | R4: 3742 | S4: 3240
A5: Cawang | B5: =IFERROR(XLOOKUP(A:A,Q:Q,S:S),0) -> 2915 | C5: 2244 | D5: 2297 | E5: 1477 | F5: 2973 | G5: 2515 | N5: =C5/ sum(B5:C5) -> 0.43496802 | P5: Jehan | Q5: Ciumbuleuit | R5: 3279 | S5: 2780
A6: Cilandak Barat | B6: =IFERROR(XLOOKUP(A:A,Q:Q,S:S),0) -> 858 | C6: 872 | D6: 529 | E6: 849 | F6: 941 | G6: 903 | N6: =C6/ sum(B6:C6) -> 0.50404624 | P6: Jehan | Q6: Jatinangor | R6: 2060 | S6: 1708
A7: Ciledug | B7: =IFERROR(XLOOKUP(A:A,Q:Q,S:S),0) -> 4081 | C7: 3320 | D7: 3339 | E7: 2496 | F7: 4704 | G7: 3730 | N7: =C7/ sum(B7:C7) -> 0.44858803 | P7: Jehan | Q7: Kiara Artha | R7: 2868 | S7: 2864
A8: Cimahi | B8: =IFERROR(XLOOKUP(A:A,Q:Q,S:S),0) -> 4030 | C8: 2801 | D8: 3543 | E8: 2364 | F8: 5981 | G8: 3862 | N8: =C8/ sum(B8:C8) -> 0.41004245 | P8: Jehan | Q8: Margorejo | R8: 1288 | S8: 1087
A9: Ciputat Jombang | B9: =IFERROR(XLOOKUP(A:A,Q:Q,S:S),0) -> 2584 | C9: 1514 | D9: 2097 | E9: 1331 | F9: 3333 | G9: 2103 | N9: =C9/ sum(B9:C9) -> 0.36944851 | P9: Jehan | Q9: Melong | R9: 1939 | S9: 1756
A10: Ciputat Juanda | B10: =IFERROR(XLOOKUP(A:A,Q:Q,S:S),0) -> 1817 | C10: 1493 | D10: 1364 | E10: 1467 | F10: 1604 | G10: 1600 | N10: =C10/ sum(B10:C10) -> 0.4510574 | P10: Jehan | Q10: Metro | R10: 1649 | S10: 1612
A11: Citraland | B11: =IFERROR(XLOOKUP(A:A,Q:Q,S:S),0) -> 3240 | C11: 2117 | D11: 2521 | E11: 1819 | F11: 2565 | G11: 2935 | N11: =C11/ sum(B11:C11) -> 0.39518387 | P11: Jehan | Q11: Peta | R11: 4279 | S11: 3750
A12: Ciumbuleuit | B12: =IFERROR(XLOOKUP(A:A,Q:Q,S:S),0) -> 2780 | C12: 2449 | D12: 2258 | E12: 1950 | F12: 4210 | G12: 2561 | N12: =C12/ sum(B12:C12) -> 0.46834959 | P12: Randi | Q12: Ujung Berung | R12: 3496 | S12: 3024
A13: Jatinangor | B13: =IFERROR(XLOOKUP(A:A,Q:Q,S:S),0) -> 1708 | C13: 1332 | D13: 1740 | E13: 1194 | F13: 2578 | G13: 2615 | N13: =C13/ sum(B13:C13) -> 0.43815789 | P13: Randi | Q13: Bintaro | R13: 1709 | S13: 1601
A14: Kalimalang | B14: =IFERROR(XLOOKUP(A:A,Q:Q,S:S),0) -> 5474 | C14: 4312 | D14: 3808 | E14: 3311 | F14: 5374 | G14: 4490 | N14: =C14/ sum(B14:C14) -> 0.44062947 | P14: Randi | Q14: Cawang | R14: 3301 | S14: 2915
... A30: Peta | B30: =IFERROR(XLOOKUP(A:A,Q:Q,S:S),0) -> 3750 | C30: 2598 | D30: 3031 | E30: 2324 | F30: 5351 | G30: 3702 | N30: =C30/ sum(B30:C30) -> 0.40926276 | P30: Randi | Q30: Pengumben | R30: 2924 | S30: 2574
A31: Setu Cipayung | B31: =IFERROR(XLOOKUP(A:A,Q:Q,S:S),0) -> 2921 | C31: 2142 | D31: 2129 | E31: 1701 | F31: 3226 | G31: 2359 | N31: =C31/ sum(B31:C31) -> 0.42306933 | Q31: Setu Cipayung | R31: 2887 | S31: 2921
A32: Ujung Berung | B32: =IFERROR(XLOOKUP(A:A,Q:Q,S:S),0) -> 3024 | C32: 2663 | D32: 2466 | E32: 2161 | F32: 3752 | G32: 3381 | N32: =C32/ sum(B32:C32) -> 0.46826095

Sheet Oatside
A1: STORE | B1: JAN | D1: FEB | F1: MAR | H1: APR | J1: MAY | L1: JUNE
A2: FILTER | B2: ITEM DRINK | C2: OATSIDE | D2: ITEM DRINK | E2: OATSIDE | F2: ITEM DRINK | G2: OATSIDE | H2: ITEM DRINK | I2: OATSIDE | J2: ITEM DRINK | K2: OATSIDE | L2: ITEM DRINK | M2: OATSIDE
A3: Bintaro | B3: 3349 | C3: 107 | D3: 1279 | E3: 154 | F3: 1721 | G3: 71
A4: Buah Batu | B4: 8448 | C4: 630 | D4: 3634 | E4: 802 | F4: 4501 | G4: 1541
A5: Cawang | B5: 5686 | C5: 392 | D5: 2577 | E5: 181 | F5: 3738 | G5: 85
A6: Cilandak Barat | B6: 2297 | C6: 180 | D6: 859 | E6: 189 | F6: 1060 | G6: 192
A7: Ciledug | B7: 9350 | C7: 135 | D7: 4176 | E7: 288 | F7: 5829 | G7: 222
A8: Cimahi | B8: 8448 | C8: 1108 | D8: 3531 | E8: 879 | F8: 5860 | G8: 1236
A9: Ciputat Jombang | B9: 5217 | C9: 173 | D9: 2224 | E9: 176 | F9: 3560 | G9: 128
A10: Ciputat Juanda | B10: 4228 | C10: 105 | D10: 1844 | E10: 247 | F10: 2031 | G10: 203
A11: Citraland | B11: 6256 | C11: 10 | D11: 2510 | E11: 127 | F11: 2937 | G11: 345
A12: Ciumbuleuit | B12: 6625 | C12: 496 | D12: 2312 | E12: 731 | F12: 4186 | G12: 520
A13: Jatinangor | B13: 3668 | C13: 630 | D13: 1805 | E13: 528 | F13: 2996 | G13: 706
A14: Kalimalang | B14: 11468 | C14: 87 | D14: 4502 | E14: 437 | F14: 6166 | G14: 812
... A32: Ujung Berung | B32: 6157 | C32: 1545 | D32: 2666 | E32: 1215 | F32: 3517 | G32: 1962

Sheet Snack Platter
A1: STORE | B1: JAN | D1: FEB | F1: MAR | H1: APR | J1: MAY | L1: JUNE
A2: FILTER | B2: ALL SNACK | C2: SNACK PLAT | D2: MEALS | E2: TELUR | F2: Meals | G2: Telur | H2: ALL SNACK | I2: SNACK PLAT | J2: ALL SNACK | K2: SNACK PLAT | L2: ALL SNACK | M2: SNACK PLAT
A3: Bintaro | B3: 511 | C3: 14 | D3: 363 | E3: 3 | F3: 485 | G3: 14
A4: Buah Batu | B4: 1305 | C4: 26 | D4: 1010 | E4: 16 | F4: 1938 | G4: 143
A5: Cawang | B5: 884 | C5: 27 | D5: 862 | E5: 23 | F5: 1869 | G5: 50
A6: Cilandak Barat | B6: 400 | C6: 16 | D6: 296 | E6: 91 | F6: 537 | G6: 78
A7: Ciledug | B7: 1888 | C7: 46 | D7: 935 | E7: 9 | F7: 1848 | G7: 8
A8: Cimahi | B8: 1540 | C8: 46 | D8: 1109 | E8: 53 | F8: 1971 | G8: 91
A9: Ciputat Jombang | B9: 984 | C9: 38 | D9: 710 | E9: 21 | F9: 1348 | G9: 25
A10: Ciputat Juanda | B10: 652 | C10: 19 | D10: 533 | E10: 10 | F10: 705 | G10: 36
A11: Citraland | B11: 759 | C11: 15 | D11: 587 | E11: 4 | F11: 723 | G11: 35
A12: Ciumbuleuit | B12: 915 | C12: 12 | D12: 658 | E12: 25 | F12: 1278 | G12: 56
A13: Jatinangor | B13: 669 | C13: 22 | D13: 938 | E13: 63 | F13: 2149 | G13: 223
A14: Kalimalang | B14: 1882 | C14: 32 | D14: 1725 | E14: 68 | F14: 2804 | G14: 197
... A32: Ujung Berung | B32: 1343 | C32: 43 | D32: 968 | E32: 108 | F32: 1755 | G32: 453

Sheet Bundling Asik
B1: JAN | D1: FEB | F1: MAR | H1: APR | J1: MAY | L1: JUNE | O1: Outlet | P1: 46082 | Q1: Transaksi
A2: FILTER | B2: TOTAL ITEM | C2: B. ASIK | D2: TOTAL ITEM | E2: B. ASIK | F2: TOTAL ITEM | G2: B. ASIK | H2: TOTAL ITEM | I2: B. ASIK | J2: TOTAL ITEM | K2: B. ASIK | L2: TOTAL ITEM | M2: B. ASIK | O2: Bintaro | P2: 34 | Q2: 564
A3: Bintaro | B3: 1026 | C3: 19 | D3: 363 | E3: 25 | F3: 564 | G3: 34 | O3: Buah Batu | P3: 115 | Q3: 1423
A4: Buah Batu | B4: 2280 | C4: 22 | D4: 1010 | E4: 32 | F4: 1423 | G4: 115 | O4: Cawang | P4: 69 | Q4: 816
A5: Cawang | B5: 1475 | C5: 29 | D5: 862 | E5: 9 | F5: 816 | G5: 69 | O5: Cilandak Barat | P5: 33 | Q5: 382
A6: Cilandak Barat | B6: 838 | C6: 6 | D6: 296 | E6: 11 | F6: 382 | G6: 33 | O6: Ciledug | P6: 91 | Q6: 1468
A7: Ciledug | B7: 2624 | C7: 46 | D7: 935 | E7: 28 | F7: 1468 | G7: 91 | O7: Cimahi | P7: 52 | Q7: 1794
A8: Cimahi | B8: 2749 | C8: 39 | D8: 1109 | E8: 29 | F8: 1794 | G8: 52 | O8: Ciputat Jombang | P8: 63 | Q8: 829
A9: Ciputat Jombang | B9: 1578 | C9: 47 | D9: 710 | E9: 21 | F9: 829 | G9: 63 | O9: Ciputat Juanda | P9: 58 | Q9: 580
A10: Ciputat Juanda | B10: 1090 | C10: 21 | D10: 533 | E10: 13 | F10: 580 | G10: 58 | O10: Citraland | P10: 39 | Q10: 1051
A11: Citraland | B11: 1655 | C11: 4 | D11: 587 | E11: 13 | F11: 1051 | G11: 39 | O11: Ciumbuleuit | P11: 68 | Q11: 1234
A12: Ciumbuleuit | B12: 1829 | C12: 37 | D12: 658 | E12: 40 | F12: 1234 | G12: 68 | O12: Jatinangor | P12: 153 | Q12: 782
A13: Jatinangor | B13: 1247 | C13: 27 | D13: 938 | E13: 25 | F13: 782 | G13: 153 | O13: Kalimalang | P13: 188 | Q13: 1774
A14: Kalimalang | B14: 3486 | C14: 46 | D14: 1725 | E14: 55 | F14: 1774 | G14: 188 | O14: Karawaci | P14: 30 | Q14: 629
... A31: Setu Cipayung | B31: 1806 | C31: 27 | D31: 753 | E31: 21 | F31: 1081 | G31: 56 | O31: Ujung Berung | P31: 140 | Q31: 1431
A32: Ujung Berung | B32: 2322 | C32: 51 | D32: 968 | E32: 36 | F32: 1431 | G32: 140

Sheet YoY
A1: STORE | B1: JAN | D1: FEB | F1: MAR | H1: APR | J1: MAY | L1: JUNE
A2: FILTER | B2: 2025 | C2: 2026 | D2: 2025 | E2: 2026 | F2: 2025 | G2: 2026 | H2: 2025 | I2: 2026 | J2: 2025 | K2: 2026 | L2: 2025 | M2: 2026
A3: Bintaro | B3: 136367571 | C3: 113030114 | D3: 115507235 | E3: 87754076 | F3: 101119234 | G3: 102866336
A4: Buah Batu | B4: 328789030 | C4: 296807051 | D4: 287166989 | E4: 252449540 | F4: 336800056 | G4: 356629312
A5: Cawang | C5: 210611522 | G5: 245953493
A6: Cilandak Barat | B6: 111337964 | C6: 84712958 | D6: 103970626 | E6: 66837271 | F6: 110321748 | G6: 81675734
A7: Ciledug | B7: 421061254 | C7: 329784772 | D7: 358453829 | E7: 256663268 | F7: 426503977 | G7: 354749572
A8: Cimahi | B8: 317406381 | C8: 335336106 | D8: 254452824 | E8: 290748668 | F8: 276079827 | G8: 405351490
A9: Ciputat Jombang | B9: 23694198 | C9: 187113299 | D9: 273192797 | E9: 146615274 | F9: 295961404 | G9: 229863427
A10: Ciputat Juanda | C10: 138853819 | G10: 132713419
A11: Citraland | B11: 187168362 | C11: 189346846 | D11: 178784592 | E11: 154378504 | F11: 173299549 | G11: 190746962
A12: Ciumbuleuit | B12: 281577547 | C12: 228555370 | D12: 203141870 | E12: 183473662 | F12: 259696848 | G12: 256835476
A13: Jatinangor | B13: 208957014 | C13: 153420087 | D13: 215689559 | E13: 153550620 | F13: 286903614 | G13: 263235458
A14: Kalimalang | B14: 569893012 | C14: 420660123 | D14: 464579144 | E14: 322598069 | F14: 518819837 | G14: 435204393
A15: Karawaci | C15: 158190542 | G15: 161600861
A16: Kayu Putih | B16: 147106184 | C16: 143275207 | D16: 126733566 | E16: 109437921 | F16: 143999146 | G16: 129865728
A17: Kemang Utara | B17: 398866500 | C17: 332121353 | D17: 338613861 | E17: 271302970 | F17: 452307368 | G17: 343698942
A18: Kiara Artha | B18: 214855590 | C18: 199659047 | D18: 176218223 | E18: 153898884 | F18: 247155599 | G18: 278330487
A19: Kota Wisata | B19: 216386403 | C19: 172679392 | D19: 159451279 | E19: 145140653 | F19: 199788228 | G19: 197593377
A20: Kranggan | C20: 314527882 | G20: 358869179
A21: Lebak Bulus | B21: 228789958 | C21: 138339449 | D21: 209591143 | E21: 111143970 | F21: 246882574 | G21: 151572220
A22: Lenteng Agung | B22: 209771000 | C22: 220771426 | D22: 186904784 | E22: 192467933 | F22: 221642092 | G22: 248550222
A23: Margonda | B23: 267506383 | C23: 242197237 | D23: 213184416 | E23: 218770351 | F23: 284104333 | G23: 305020918
A24: Margorejo | B24: 71463196 | C24: 69736127 | D24: 66457693 | E24: 59904150 | F24: 59267180 | G24: 67622328
A25: Melong | B25: 121800050 | C25: 146659741 | D25: 109240418 | E25: 133582293 | F25: 129677847 | G25: 188395447
A26: Metro | C26: 146225635 | F26: 125791583 | G26: 190446310
A27: Pamulang | B27: 448712209 | C27: 173049992 | D27: 480197163 | E27: 130144779 | F27: 506123623 | G27: 224242619
A28: Pekayon | B28: 265942893 | C28: 225520618 | D28: 206077549 | E28: 180999366 | F28: 258242922 | G28: 262226490
A29: Pengumben | B29: 303277791 | C29: 208003840 | D29: 245080626 | E29: 176047584 | F29: 296700667 | G29: 252184133
A30: Peta | C30: 299781882 | F30: 362482444 | G30: 389392101
A31: Setu Cipayung | C31: 217597885 | G31: 237591106
A32: Ujung Berung | B32: 234377443 | C32: 266147449 | D32: 209755450 | E32: 222853058 | F32: 268774315 | G32: 337834900

Sheet Waste & Spoil
A1: STORE | B1: JAN | D1: FEB | F1: MAR | H1: APR | J1: MAY | L1: JUNE
A2: FILTER | B2: LOG | C2: Nominal | D2: LOG | E2: Nominal | F2: LOG | G2: Nominal | H2: LOG | I2: Nominal | J2: LOG | K2: Nominal | L2: LOG | M2: Nominal
A3: Bintaro | B3: 3 | C3: 1278572.4 | D3: 22 | E3: 1322167.2 | F3: 6 | G3: 806365
A4: Buah Batu | B4: 10 | C4: 1439620 | D4: 26 | E4: 1347403 | F4: 39 | G4: 2499663.5
A5: Cawang | B5: 15 | C5: 1512762 | D5: 27 | E5: 3359368.9 | F5: 18 | G5: 1948225.7
A6: Cilandak Barat | B6: 23 | C6: 2275570 | D6: 22 | E6: 4030685 | F6: 29 | G6: 1547206
A7: Ciledug | B7: 14 | C7: 3283850 | D7: 10 | E7: 2300593 | F7: 12 | G7: 3193516
A8: Cimahi | B8: 7 | C8: 648845 | D8: 10 | E8: 562927 | F8: 13 | G8: 4782
A9: Ciputat Jombang | B9: 11 | C9: 3277052 | D9: 13 | E9: 3990994 | F9: 11 | G9: 3336260
A10: Ciputat Juanda | B10: 12 | C10: 1705817.5 | D10: 14 | E10: 1637134.4 | F10: 19 | G10: 1302792.8
A11: Citraland | B11: 0 | D11: 8 | E11: 912452 | F11: 15 | G11: 2023304
A12: Ciumbuleuit | B12: 2 | C12: 3449940 | D12: 30 | E12: 3631506 | F12: 25 | G12: 1861025
A13: Jatinangor | B13: 11 | C13: 3371687 | D13: 25 | E13: 2905539.4 | F13: 10 | G13: 3313680
A14: Kalimalang | B14: 24 | C14: 2568650 | D14: 6 | E14: 1348814 | F14: 23 | G14: 1786094
A15: Karawaci | B15: 11 | C15: 4043917 | D15: 19 | E15: 7446893.3 | F15: 21 | G15: 4628499.6
A16: Kayu Putih | B16: 19 | C16: 2337719 | D16: 13 | E16: 1527848.2 | F16: 14 | G16: 1904354
A17: Kemang Utara | B17: 21 | C17: 5830750 | D17: 6 | E17: 3076032 | F17: 11 | G17: 1483273
A18: Kiara Artha | B18: 29 | C18: 3941034 | D18: 30 | E18: 3569233.5 | F18: 25 | G18: 3280764
A19: Kota Wisata | B19: 6 | C19: 1669966 | D19: 15 | E19: 1444873 | F19: 7 | G19: 1659544
A20: Kranggan | B20: 15 | C20: 3238482.1 | D20: 17 | E20: 3319472 | F20: 13 | G20: 3914577
A21: Lebak Bulus | B21: 20 | C21: 4802463 | D21: 0 | E21: 0 | F21: 12 | G21: 4251372
A22: Lenteng Agung | B22: 24 | C22: 2388562 | D22: 29 | E22: 2512001 | F22: 27 | G22: 3156110
A23: Margonda | B23: 30 | C23: 3487462 | D23: 18 | E23: 2818146 | F23: 28 | G23: 3267877
A24: Margorejo | B24: 0 | D24: 25 | E24: 2009998 | F24: 19 | G24: 2336921
A25: Melong | B25: 28 | C25: 1019760 | D25: 13 | E25: 604376 | F25: 33 | G25: 735700
A26: Metro | B26: 10 | C26: 2234045 | D26: 3 | E26: 2361495 | F26: 11 | G26: 1858742
A27: Pamulang | B27: 12 | C27: 2242198 | D27: 23 | E27: 2287952 | F27: 16 | G27: 1932706
A28: Pekayon | B28: 5 | C28: 1928321 | D28: 5 | E28: 1572844 | F28: 4 | G28: 1596874
A29: Pengumben | B29: 5 | C29: 910089 | D29: 6 | E29: 876283 | F29: 8 | G29: 862126
A30: Peta | B30: 14 | C30: 2645386 | D30: 15 | E30: 1754551 | F30: 17 | G30: 2356860
A31: Setu Cipayung | B31: 10 | C31: 1125848 | D31: 7 | E31: 1491486 | F31: 6 | G31: 1741650
A32: Ujung Berung | B32: 4 | C32: 2435140 | D32: 7 | E32: 2295763 | F32: 7 | G32: 2295763

Sheet HPP
A1: STORE | B1: JAN | E1: FEB | G1: MAR | I1: APR | K1: MAY | M1: JUNE
A2: FILTER | B2: Gross Sales | C2: HPP | D2: % HPP | E2: Gross Sales | F2: HPP | G2: Gross Sales | H2: HPP | I2: Gross Sales | J2: HPP | K2: Gross Sales | L2: HPP | M2: Gross Sales | N2: HPP
A3: Margorejo | B3: 72955697 | C3: 36656056 | D3: =C3/B3 -> 0.50244268 | E3: Rp62,515,471 | F3: Rp38,954,405 | G3: 71579739 | H3: 35962908
A4: Pamulang | B4: 177250971 | C4: 88166322 | D4: =C4/B4 -> 0.49740953 | E4: Rp136,834,830 | F4: Rp74,104,456 | G4: 253544544 | H4: 107878170
A5: Ciumbuleuit | B5: 242624723 | C5: 118174990 | D5: =C5/B5 -> 0.48706904 | E5: Rp196,565,708 | F5: Rp100,180,733 | G5: 276302354 | H5: 130255734
A6: Lenteng Agung | B6: 226598964 | C6: 110291299 | D6: =C6/B6 -> 0.48672464 | E6: Rp204,873,145 | F6: Rp91,740,625 | G6: 277178187 | H6: 113281069
A7: Pengumben | B7: 211490006 | C7: 101706155 | D7: =C7/B7 -> 0.48090289 | E7: Rp184,417,138 | F7: Rp89,193,908 | G7: 288517805 | H7: 116031483
A8: Ciputat Juanda | B8: 145741256 | C8: 69920652 | D8: =C8/B8 -> 0.47975881 | E8: Rp133,943,230 | F8: Rp56,597,407 | G8: 143766637 | H8: 60282446
A9: Kayu Putih | B9: 146155608 | C9: 69957761 | D9: =C9/B9 -> 0.47865259 | E9: Rp113,545,202 | F9: Rp60,580,833 | G9: 142032305 | H9: 71087315
A10: Lebak Bulus | B10: 140197587 | C10: 66583598 | D10: =C10/B10 -> 0.47492685 | E10: Rp115,998,752 | F10: Rp51,264,765 | G10: 160326262 | H10: 64128323
A11: Jatinangor | B11: 163085837 | C11: 77284891 | D11: =C11/B11 -> 0.47389088 | E11: Rp167,022,088 | F11: Rp74,280,552 | G11: 308111195 | H11: 119063899
A12: Ciledug | B12: 331089547 | C12: 156619357 | D12: =C12/B12 -> 0.47304229 | E12: Rp263,796,689 | F12: Rp126,697,071 | G12: 382818881 | H12: 177587509
A13: Cilandak Barat | B13: 87433146 | C13: 41318613 | D13: =C13/B13 -> 0.47257379 | E13: Rp70,193,821 | F13: Rp36,226,153 | G13: 93177038 | H13: 37616650
A14: Kalimalang | B14: 427922298 | C14: 201377149 | D14: =C14/B14 -> 0.47059279 | E14: Rp338,384,468 | F14: Rp159,841,955 | G14: 486165153 | H14: 201535654
... A32: Citraland | B32: 196894389 | C32: 87873248 | D32: =C32/B32 -> 0.44629635 | E32: Rp160,818,127 | F32: Rp80,123,741 | G32: 198429092 | H32: 89311820

Sheet Audit
A1: STORE | B1: JAN | C1: FEB | D1: MAR | E1: APR | F1: MAY | G1: JUNE
A2: Bintaro | B2: 75.55 | C2: 78.48 | D2: 74.12
A3: Buah Batu | B3: 70.88 | C3: 82.59 | D3: 76.35
A4: Cawang | B4: 78.76 | C4: 74.79 | D4: 71.46
A5: Cilandak Barat | B5: 76.86 | C5: 82.94 | D5: 83.63
A6: Ciledug | B6: 79.5 | C6: 77.86 | D6: 72.56
A7: Cimahi | B7: 82.59 | C7: 86.28 | D7: 87.07
A8: Ciputat Jombang | B8: 85.38 | C8: 79.68 | D8: 73.83
A9: Ciputat Juanda | B9: 84.63 | C9: 78.49 | D9: 79.06
A10: Citraland | B10: 69.45 | C10: 57.82 | D10: 69.04
A11: Ciumbuleuit | B11: 78.84 | C11: 80.72 | D11: 80.56
A12: Jatinangor | B12: 89.73 | C12: 93.33 | D12: 91.7
A13: Kalimalang | B13: 82 | C13: 79.54 | D13: 80.66
... A31: Ujung Berung | B31: 86.03 | C31: 88.21 | D31: 88.72

Sheet Mistery Shopper
A1: STORE | B1: JAN | C1: FEB | D1: MAR | E1: APR | F1: MAY | G1: JUNE
A2: Ciledug | B2: 5 | C2: 5 | D2: 4.25
A3: Citraland | B3: 5 | C3: 5 | D3: 4.8
A4: Kayu Putih | B4: 5 | C4: 5 | D4: 0
A5: Kemang Utara | B5: 5 | C5: 5 | D5: 0
A6: Kota Wisata | B6: 5 | C6: 5 | D6: 5
A7: Kranggan | B7: 5 | C7: 5 | D7: 5
A8: Margonda | B8: 5 | C8: 5 | D8: 0
A9: Margorejo | B9: 5 | C9: 5 | D9: 5
A10: Pekayon | B10: 5 | C10: 5 | D10: 5
A11: Pengumben | B11: 5 | C11: 5 | D11: 0
A12: Karawaci | B12: 4.95 | C12: 5 | D12: 4.95
A13: Kalimalang | B13: 4.9 | C13: 5 | D13: 5
... A31: Peta | B31: 4.31 | C31: 3.36 | D31: 3.69

Sheet LOG Complain
A1: Tanggal (MM/DD/YYYY) | B1: Month | C1: Store | D1: Nomor Komplain | E1: Tanggal Terjadi Komplain | F1: Tanggal Penyelesaian Komplain | G1: SLA
A2: 46023 | B2: =text(A2,"MMM") -> Jan | C2: Pengumben | D2: 3354 | E2: 46024 | F2: 46028 | G2: =F2-E2 -> 4
A3: 46023 | B3: =text(A3,"MMM") -> Jan | C3: Ciledug | D3: 3355 | E3: 46024 | F3: 46028 | G3: =F3-E3 -> 4
A4: 46023 | B4: =text(A4,"MMM") -> Jan | C4: Kota Wisata | D4: 3356 | E4: 46029 | F4: 46029 | G4: =F4-E4 -> 0
A5: 46023 | B5: =text(A5,"MMM") -> Jan | C5: Kota Wisata | D5: 3357 | E5: 46028 | F5: 46031 | G5: =F5-E5 -> 3
A6: 46023 | B6: =text(A6,"MMM") -> Jan | C6: Kota Wisata | D6: 3358 | E6: 46028 | F6: 46031 | G6: =F6-E6 -> 3
A7: 46023 | B7: =text(A7,"MMM") -> Jan | C7: Kota Wisata | D7: 3359 | E7: 46028 | F7: 46031 | G7: =F7-E7 -> 3
A8: 46023 | B8: =text(A8,"MMM") -> Jan | C8: Kota Wisata | D8: 3360 | E8: 46028 | F8: 46031 | G8: =F8-E8 -> 3
A9: 46024 | B9: =text(A9,"MMM") -> Jan | C9: Ciledug | D9: 3361 | E9: 46024 | F9: 46028 | G9: =F9-E9 -> 4
A10: 46024 | B10: =text(A10,"MMM") -> Jan | C10: Kalimalang | D10: 3362 | E10: 46024 | F10: 46028 | G10: =F10-E10 -> 4
A11: 46024 | B11: =text(A11,"MMM") -> Jan | C11: Kalimalang | D11: 3363 | E11: 46024 | F11: 46028 | G11: =F11-E11 -> 4
A12: 46024 | B12: =text(A12,"MMM") -> Jan | C12: Kalimalang | D12: 3364 | E12: 46024 | F12: 46028 | G12: =F12-E12 -> 4
A13: 46024 | B13: =text(A13,"MMM") -> Jan | C13: Kota Wisata | D13: 3365 | E13: 46024 | F13: 46028 | G13: =F13-E13 -> 4
... A285: 46082 | B285: =text(A285,"MMM") -> Mar | C285: Citraland | D285: 3639 | E285: 46084 | F285: 46088 | G285: =F285-E285 -> 4
A286: 46082 | B286: =text(A286,"MMM") -> Mar | C286: Ciumbuleuit | D286: 3640 | E286: 46084 | G286: =F286-E286 -> -46084
A287: 46083 | B287: =text(A287,"MMM") -> Mar | C287: Peta | D287: 3641 | E287: 46084 | F287: 46088 | G287: =F287-E287 -> 4
A288: 46083 | B288: =text(A288,"MMM") -> Mar | C288: Lenteng Agung | D288: 3642 | E288: 46084 | F288: 46088 | G288: =F288-E288 -> 4
A289: 46083 | B289: =text(A289,"MMM") -> Mar | C289: Margonda | D289: 3643 | E289: 46084 | F289: 46088 | G289: =F289-E289 -> 4
A290: 46083 | B290: =text(A290,"MMM") -> Mar | C290: Margonda | D290: 3644 | E290: 46084 | F290: 46088 | G290: =F290-E290 -> 4
A291: 46084 | B291: =text(A291,"MMM") -> Mar | C291: Buah Batu | D291: 3645 | E291: 46084 | F291: 46088 | G291: =F291-E291 -> 4
A292: 46084 | B292: =text(A292,"MMM") -> Mar | C292: Buah Batu | D292: 3646 | E292: 46084 | F292: 46088 | G292: =F292-E292 -> 4
A293: 46084 | B293: =text(A293,"MMM") -> Mar | C293: Ciputat Jombang | D293: 3647 | E293: 46084 | F293: 46088 | G293: =F293-E293 -> 4
A294: 46085 | B294: =text(A294,"MMM") -> Mar | C294: Citraland | D294: 3648 | E294: 46091 | F294: 46096 | G294: =F294-E294 -> 5
A295: 46085 | B295: =text(A295,"MMM") -> Mar | C295: Buah Batu | D295: 3649 | E295: 46091 | F295: 46096 | G295: =F295-E295 -> 5
A296: 46085 | B296: =text(A296,"MMM") -> Mar | C296: Ujung Berung Baru | D296: 3650 | E296: 46084 | F296: 46096 | G296: =F296-E296 -> 12
A297: 46085 | B297: =text(A297,"MMM") -> Mar | C297: Ujung Berung Baru | D297: 3651 | E297: 46091 | F297: 46096 | G297: =F297-E297 -> 5
A298: 46085 | B298: =text(A298,"MMM") -> Mar | C298: Ujung Berung Baru | D298: 3652 | E298: 46091 | F298: 46096 | G298: =F298-E298 -> 5
... A336: 46091 | B336: =text(A336,"MMM") -> Mar | C336: Peta | D336: 3691 | E336: 46098 | F336: 46103 | G336: =F336-E336 -> 5
A337: 46093 | B337: =text(A337,"MMM") -> Mar | C337: Jatinangor | D337: 3692 | E337: 46098 | G337: =F337-E337 -> -46098
A338: 46093 | B338: =text(A338,"MMM") -> Mar | C338: Peta | D338: 3693 | E338: 46098 | F338: 46103 | G338: =F338-E338 -> 5
A339: 46093 | B339: =text(A339,"MMM") -> Mar | C339: Setu Cipayung | D339: 3694 | E339: 46098 | F339: 46103 | G339: =F339-E339 -> 5
A340: 46095 | B340: =text(A340,"MMM") -> Mar | C340: Kayu Putih | D340: 3695 | E340: 46098 | F340: 46103 | G340: =F340-E340 -> 5
A341: 46095 | B341: =text(A341,"MMM") -> Mar | C341: Kayu Putih | D341: 3696 | E341: 46098 | F341: 46103 | G341: =F341-E341 -> 5
A342: 46095 | B342: =text(A342,"MMM") -> Mar | C342: Kayu Putih | D342: 3697 | E342: 46098 | F342: 46103 | G342: =F342-E342 -> 5
A343: 46095 | B343: =text(A343,"MMM") -> Mar | C343: Kayu Putih | D343: 3698 | E343: 46098 | F343: 46103 | G343: =F343-E343 -> 5
A344: 46095 | B344: =text(A344,"MMM") -> Mar | C344: Kayu Putih | D344: 3699 | E344: 46098 | F344: 46103 | G344: =F344-E344 -> 5
A345: 46095 | B345: =text(A345,"MMM") -> Mar | C345: Kayu Putih | D345: 3700 | E345: 46098 | F345: 46103 | G345: =F345-E345 -> 5
A346: 46095 | B346: =text(A346,"MMM") -> Mar | C346: Kayu Putih | D346: 3701 | E346: 46098 | F346: 46103 | G346: =F346-E346 -> 5
A347: 46096 | B347: =text(A347,"MMM") -> Mar | C347: Kayu Putih | D347: 3702 | E347: 46098 | F347: 46103 | G347: =F347-E347 -> 5
A348: 46096 | B348: =text(A348,"MMM") -> Mar | C348: Kayu Putih | D348: 3703 | E348: 46098 | F348: 46103 | G348: =F348-E348 -> 5
A349: 46096 | B349: =text(A349,"MMM") -> Mar | C349: Kayu Putih | D349: 3704 | E349: 46098 | F349: 46103 | G349: =F349-E349 -> 5
... A361: 46096 | B361: =text(A361,"MMM") -> Mar | C361: Kayu Putih | D361: 3716 | E361: 46098 | F361: 46103 | G361: =F361-E361 -> 5
A362: 46096 | B362: =text(A362,"MMM") -> Mar | C362: Kayu Putih | D362: 3717 | E362: 46098 | F362: 46103
A363: 46096 | B363: =text(A363,"MMM") -> Mar | C363: Kayu Putih | D363: 3718 | E363: 46098 | F363: 46103
A364: 46096 | B364: =text(A364,"MMM") -> Mar | C364: Kalimalang | D364: 3719 | E364: 46098 | F364: 46103
A365: 46096 | B365: =text(A365,"MMM") -> Mar | C365: Lebak Bulus | D365: 3720 | E365: 46098 | F365: 46103
A366: 46096 | B366: =text(A366,"MMM") -> Mar | C366: Pamulang | D366: 3721 | E366: 46098 | F366: 46103
A367: 46096 | B367: =text(A367,"MMM") -> Mar | C367: Pamulang | D367: 3722 | E367: 46098 | F367: 46103
A368: 46096 | B368: =text(A368,"MMM") -> Mar | C368: Pamulang | D368: 3723 | E368: 46098 | F368: 46103
A369: 46096 | B369: =text(A369,"MMM") -> Mar | C369: Margonda | D369: 3724 | E369: 46098 | F369: 46103
A370: 46096 | B370: =text(A370,"MMM") -> Mar | C370: Margonda | D370: 3725 | E370: 46098 | F370: 46103
A371: 46096 | B371: =text(A371,"MMM") -> Mar | C371: Margonda | D371: 3726 | E371: 46098 | F371: 46103
A372: 46096 | B372: =text(A372,"MMM") -> Mar | C372: Setu Cipayung | D372: 3727 | E372: 46098 | F372: 46103
A373: 46096 | B373: =text(A373,"MMM") -> Mar | C373: Kayu Putih | D373: 3728 | E373: 46098 | F373: 46103
... A455: 46112 | B455: =text(A455,"MMM") -> Mar | C455: Peta | D455: 3812 | E455: 46113 | F455: 46115

Sheet Complain
A1: STORE | B1: JAN | D1: FEB | F1: MAR | H1: APR | J1: MAY | L1: JUNE
A2: FILTER | B2: TRX | C2: COMPLAIN | D2: TRX | E2: COMPLAIN | F2: TRX | G2: COMPLAIN | H2: TRX | I2: COMPLAIN | J2: TRX | K2: COMPLAIN | L2: TRX | M2: COMPLAIN
A3: Bintaro | B3: 2439 | C3: 3 | D3: 1930 | E3: 2 | F3: 1921 | G3: 4
A4: Buah Batu | B4: 5271 | C4: 4 | D4: 4583 | E4: 1 | F4: 5239 | G4: 6
A5: Cawang | B5: 3866 | C5: 5 | D5: 2887 | E5: 1 | F5: 3487 | G5: 0
A6: Cilandak Barat | B6: 1622 | C6: 1 | D6: 1255 | E6: 2 | F6: 1426 | G6: 0
A7: Ciledug | B7: 5504 | C7: 4 | D7: 4215 | E7: 0 | F7: 5091 | G7: 1
A8: Cimahi | B8: 6043 | C8: 0 | D8: 5152 | E8: 5 | F8: 6406 | G8: 0
A9: Ciputat Jombang | B9: 3602 | C9: 2 | D9: 2948 | E9: 1 | F9: 3693 | G9: 5
A10: Ciputat Juanda | B10: 2829 | C10: 2 | D10: 2424 | E10: 7 | F10: 2353 | G10: 7
A11: Citraland | B11: 3993 | C11: 4 | D11: 3182 | E11: 1 | F11: 3512 | G11: 3
A12: Ciumbuleuit | B12: 4863 | C12: 0 | D12: 3767 | E12: 1 | F12: 4784 | G12: 2
A13: Jatinangor | B13: 2598 | C13: 1 | D13: 2559 | E13: 0 | F13: 3347 | G13: 1
A14: Kalimalang | B14: 7408 | C14: 8 | D14: 5449 | E14: 4 | F14: 6083 | G14: 4
... A32: Ujung Berung | B32: 4744 | C32: 7 | D32: 3904 | E32: 1 | F32: 5122 | G32: 1
C33: =SUM(C3:C32) -> 76 | E33: 78 | G33: =SUM(G3:G32) -> 117

Sheet Retention
A1: STORE | B1: JAN | D1: FEB | F1: MAR | H1: APR | J1: MAY | L1: JUNE
A2: FILTER | B2: TOTAL | C2: RESIGN | D2: TOTAL | E2: RESIGN | F2: TOTAL | G2: RESIGN | H2: TOTAL | I2: RESIGN | J2: TOTAL | K2: RESIGN | L2: TOTAL | M2: RESIGN
A3: Bintaro | B3: 6 | C3: 1 | D3: 7 | E3: 0 | F3: 9 | G3: 2
A4: Buah Batu | B4: 17 | C4: 1 | D4: 17 | E4: 0 | F4: 15 | G4: 5
A5: Cawang | B5: 13 | C5: 0 | D5: 12 | E5: 0 | F5: 10 | G5: 3
A6: Cilandak Barat | B6: 10 | C6: 0 | D6: 8 | E6: 1 | F6: 7 | G6: 0
A7: Ciledug | B7: 14 | C7: 1 | D7: 14 | E7: 2 | F7: 12 | G7: 0
A8: Cimahi | B8: 15 | C8: 1 | D8: 15 | E8: 2 | F8: 15 | G8: 1
A9: Ciputat Jombang | B9: 11 | C9: 0 | D9: 11 | E9: 1 | F9: 11 | G9: 1
A10: Ciputat Juanda | B10: 13 | C10: 0 | D10: 13 | E10: 1 | F10: 11 | G10: 1
A11: Citraland | B11: 13 | C11: 0 | D11: 12 | E11: 2 | F11: 12 | G11: 0
A12: Ciumbuleuit | B12: 13 | C12: 3 | D12: 12 | E12: 1 | F12: 12 | G12: 3
A13: Jatinangor | B13: 13 | C13: 1 | D13: 14 | E13: 2 | F13: 13 | G13: 0
A14: Kalimalang | B14: 15 | C14: 0 | D14: 18 | E14: 0 | F14: 18 | G14: 3
... A32: Ujung Berung | B32: 14 | C32: 1 | D32: 15 | E32: 2 | F32: 15 | G32: 2

Sheet Daily Sales
A1: Tanggal | B1: Day | C1: Bintaro | D1: Buah Batu | E1: Cawang | F1: Cilandak Barat | G1: Ciledug | H1: Cimahi | I1: Jombang | J1: Juanda | K1: Citraland | L1: Ciumbuleuit | M1: Jatinangor | N1: Kalimalang | O1: Karawaci | P1: Kayu Putih | Q1: Kemang Utara | R1: Kiara Artha | S1: Kota Wisata | T1: Kranggan | U1: Lebak Bulus | V1: Lenteng Agung | W1: Margonda | X1: Margorejo | Y1: Melong | Z1: Metro | AA1: Pamulang | AB1: Pekayon | AC1: Pengumben | AD1: Peta | AE1: Setu Cipayung | AF1: Ujung Berung
A2: 46023 | B2: =text(A2,"DDDD") -> Thursday | C2: 0 | D2: 0 | E2: 1 | F2: 0 | G2: 1 | H2: 1 | I2: 1 | J2: 0 | K2: 1 | L2: 0 | M2: 0 | N2: 1 | O2: 0 | P2: 0 | Q2: 1 | R2: 1 | S2: 1 | T2: 1 | U2: 1 | V2: 0 | W2: 0 | X2: 0 | Y2: 1 | Z2: 0 | AA2: 1 | AB2: 1 | AC2: 1 | AD2: 1 | AE2: 0 | AF2: 1
A3: 46024 | B3: =text(A3,"DDDD") -> Friday | C3: 0 | D3: 0 | E3: 0 | F3: 0 | G3: 0 | H3: 1 | I3: 0 | J3: 0 | K3: 0 | L3: 0 | M3: 0 | N3: 0 | O3: 0 | P3: 0 | Q3: 0 | R3: 1 | S3: 0 | T3: 0 | U3: 1 | V3: 0 | W3: 0 | X3: 0 | Y3: 1 | Z3: 0 | AA3: 0 | AB3: 0 | AC3: 0 | AD3: 0 | AE3: 0 | AF3: 0
A4: 46025 | B4: =text(A4,"DDDD") -> Saturday | C4: 0 | D4: 0 | E4: 1 | F4: 0 | G4: 1 | H4: 0 | I4: 0 | J4: 0 | K4: 0 | L4: 1 | M4: 0 | N4: 0 | O4: 0 | P4: 0 | Q4: 0 | R4: 1 | S4: 1 | T4: 0 | U4: 1 | V4: 0 | W4: 1 | X4: 0 | Y4: 0 | Z4: 0 | AA4: 1 | AB4: 1 | AC4: 0 | AD4: 0 | AE4: 0 | AF4: 0
A5: 46026 | B5: =text(A5,"DDDD") -> Sunday | C5: 0 | D5: 0 | E5: 0 | F5: 0 | G5: 0 | H5: 0 | I5: 0 | J5: 0 | K5: 0 | L5: 1 | M5: 0 | N5: 0 | O5: 0 | P5: 0 | Q5: 0 | R5: 1 | S5: 1 | T5: 0 | U5: 0 | V5: 0 | W5: 0 | X5: 0 | Y5: 0 | Z5: 0 | AA5: 0 | AB5: 1 | AC5: 0 | AD5: 0 | AE5: 0 | AF5: 0
A6: 46027 | B6: =text(A6,"DDDD") -> Monday | C6: 0 | D6: 1 | E6: 1 | F6: 1 | G6: 1 | H6: 1 | I6: 0 | J6: 0 | K6: 1 | L6: 0 | M6: 0 | N6: 0 | O6: 0 | P6: 0 | Q6: 0 | R6: 1 | S6: 0 | T6: 0 | U6: 1 | V6: 0 | W6: 0 | X6: 0 | Y6: 0 | Z6: 0 | AA6: 0 | AB6: 0 | AC6: 0 | AD6: 1 | AE6: 1 | AF6: 1
A7: 46028 | B7: =text(A7,"DDDD") -> Tuesday | C7: 0 | D7: 1 | E7: 1 | F7: 0 | G7: 1 | H7: 1 | I7: 0 | J7: 0 | K7: 1 | L7: 1 | M7: 0 | N7: 1 | O7: 0 | P7: 0 | Q7: 1 | R7: 0 | S7: 0 | T7: 1 | U7: 1 | V7: 1 | W7: 1 | X7: 0 | Y7: 1 | Z7: 1 | AA7: 0 | AB7: 0 | AC7: 0 | AD7: 1 | AE7: 1 | AF7: 1
A8: 46029 | B8: =text(A8,"DDDD") -> Wednesday | C8: 0 | D8: 0 | E8: 0 | F8: 0 | G8: 1 | H8: 1 | I8: 0 | J8: 0 | K8: 0 | L8: 0 | M8: 0 | N8: 1 | O8: 0 | P8: 0 | Q8: 0 | R8: 0 | S8: 0 | T8: 0 | U8: 0 | V8: 0 | W8: 0 | X8: 0 | Y8: 1 | Z8: 1 | AA8: 0 | AB8: 0 | AC8: 0 | AD8: 1 | AE8: 0 | AF8: 1
A9: 46030 | B9: =text(A9,"DDDD") -> Thursday | C9: 0 | D9: 0 | E9: 0 | F9: 1 | G9: 0 | H9: 1 | I9: 0 | J9: 0 | K9: 0 | L9: 1 | M9: 0 | N9: 1 | O9: 0 | P9: 0 | Q9: 0 | R9: 0 | S9: 0 | T9: 0 | U9: 0 | V9: 1 | W9: 0 | X9: 0 | Y9: 1 | Z9: 1 | AA9: 1 | AB9: 0 | AC9: 0 | AD9: 0 | AE9: 1 | AF9: 1
A10: 46031 | B10: =text(A10,"DDDD") -> Friday | C10: 0 | D10: 0 | E10: 1 | F10: 0 | G10: 0 | H10: 1 | I10: 1 | J10: 0 | K10: 0 | L10: 0 | M10: 0 | N10: 1 | O10: 0 | P10: 0 | Q10: 1 | R10: 1 | S10: 1 | T10: 1 | U10: 1 | V10: 0 | W10: 0 | X10: 0 | Y10: 1 | Z10: 0 | AA10: 1 | AB10: 0 | AC10: 1 | AD10: 0 | AE10: 0 | AF10: 0
A11: 46032 | B11: =text(A11,"DDDD") -> Saturday | C11: 0 | D11: 1 | E11: 1 | F11: 0 | G11: 1 | H11: 0 | I11: 1 | J11: 1 | K11: 0 | L11: 0 | M11: 0 | N11: 1 | O11: 1 | P11: 1 | Q11: 1 | R11: 1 | S11: 1 | T11: 1 | U11: 0 | V11: 0 | W11: 0 | X11: 0 | Y11: 0 | Z11: 0 | AA11: 1 | AB11: 1 | AC11: 1 | AD11: 0 | AE11: 1 | AF11: 0
A12: 46033 | B12: =text(A12,"DDDD") -> Sunday | C12: 0 | D12: 1 | E12: 0 | F12: 0 | G12: 1 | H12: 1 | I12: 0 | J12: 0 | K12: 0 | L12: 0 | M12: 0 | N12: 1 | O12: 0 | P12: 0 | Q12: 1 | R12: 1 | S12: 1 | T12: 0 | U12: 0 | V12: 0 | W12: 0 | X12: 0 | Y12: 0 | Z12: 0 | AA12: 0 | AB12: 0 | AC12: 1 | AD12: 0 | AE12: 0 | AF12: 0
A13: 46034 | B13: =text(A13,"DDDD") -> Monday | C13: 0 | D13: 0 | E13: 0 | F13: 0 | G13: 0 | H13: 1 | I13: 0 | J13: 0 | K13: 0 | L13: 0 | M13: 0 | N13: 0 | O13: 0 | P13: 0 | Q13: 0 | R13: 0 | S13: 0 | T13: 0 | U13: 0 | V13: 0 | W13: 0 | X13: 0 | Y13: 0 | Z13: 0 | AA13: 0 | AB13: 0 | AC13: 1 | AD13: 0 | AE13: 0 | AF13: 0
... A91: 46112 | B91: =text(A91,"DDDD") -> Tuesday | C91: 0 | D91: 1 | E91: 1 | F91: 0 | G91: 1 | H91: 1 | I91: 0 | J91: 0 | K91: 1 | L91: 1 | M91: 1 | N91: 0 | O91: 0 | P91: 0 | Q91: 1 | R91: 1 | S91: 0 | T91: 1 | U91: 0 | V91: 1 | W91: 0 | X91: 1 | Y91: 1 | Z91: 1 | AA91: 0 | AB91: 0 | AC91: 1 | AD91: 1 | AE91: 1 | AF91: 1
A92: 46113 | B92: =text(A92,"DDDD") -> Wednesday
A93: 46114 | B93: =text(A93,"DDDD") -> Thursday
A94: 46115 | B94: =text(A94,"DDDD") -> Friday
A95: 46116 | B95: =text(A95,"DDDD") -> Saturday
A96: 46117 | B96: =text(A96,"DDDD") -> Sunday
A97: 46118 | B97: =text(A97,"DDDD") -> Monday
A98: 46119 | B98: =text(A98,"DDDD") -> Tuesday
A99: 46120 | B99: =text(A99,"DDDD") -> Wednesday
A100: 46121 | B100: =text(A100,"DDDD") -> Thursday
A101: 46122 | B101: =text(A101,"DDDD") -> Friday
A102: 46123 | B102: =text(A102,"DDDD") -> Saturday
A103: 46124 | B103: =text(A103,"DDDD") -> Sunday
... A182: 46203 | B182: =text(A182,"DDDD") -> Tuesday

Sheet SLA Complain
A1: STORE | B1: JAN | C1: FEB | D1: MAR | E1: APR | F1: MAY | G1: JUN
A2: Bintaro | B2: =AVERAGEIFS('LOG Complain'!$G$1:$G$497,'LOG Complain'!$C$1:$C$497,$A2,'LOG Complain'!$B$1:$B$497,B$1) -> #DIV/0! | C2: =AVERAGEIFS('LOG Complain'!$G:$G,'LOG Complain'!$C:$C,$A2,'LOG Complain'!$B:$B,C$1) -> #DIV/0! | D2: =AVERAGEIFS('LOG Complain'!$G:$G,'LOG Complain'!$C:$C,$A2,'LOG Complain'!$B:$B,D$1) -> #DIV/0! | E2: =AVERAGEIFS('LOG Complain'!$G:$G,'LOG Complain'!$C:$C,$A2,'LOG Complain'!$B:$B,E$1) -> #DIV/0! | F2: =AVERAGEIFS('LOG Complain'!$G:$G,'LOG Complain'!$C:$C,$A2,'LOG Complain'!$B:$B,F$1) -> #DIV/0! | G2: =AVERAGEIFS('LOG Complain'!$G:$G,'LOG Complain'!$C:$C,$A2,'LOG Complain'!$B:$B,G$1) -> #DIV/0!
A3: Buah Batu | B3: =AVERAGEIFS('LOG Complain'!$G:$G,'LOG Complain'!$C:$C,$A3,'LOG Complain'!$B:$B,B$1) -> #DIV/0! | C3: =AVERAGEIFS('LOG Complain'!$G:$G,'LOG Complain'!$C:$C,$A3,'LOG Complain'!$B:$B,C$1) -> #DIV/0! | D3: =AVERAGEIFS('LOG Complain'!$G:$G,'LOG Complain'!$C:$C,$A3,'LOG Complain'!$B:$B,D$1) -> #DIV/0! | E3: =AVERAGEIFS('LOG Complain'!$G:$G,'LOG Complain'!$C:$C,$A3,'LOG Complain'!$B:$B,E$1) -> #DIV/0! | F3: =AVERAGEIFS('LOG Complain'!$G:$G,'LOG Complain'!$C:$C,$A3,'LOG Complain'!$B:$B,F$1) -> #DIV/0! | G3: =AVERAGEIFS('LOG Complain'!$G:$G,'LOG Complain'!$C:$C,$A3,'LOG Complain'!$B:$B,G$1) -> #DIV/0!
A4: Cawang | B4: =AVERAGEIFS('LOG Complain'!$G:$G,'LOG Complain'!$C:$C,$A4,'LOG Complain'!$B:$B,B$1) -> #DIV/0! | C4: =AVERAGEIFS('LOG Complain'!$G:$G,'LOG Complain'!$C:$C,$A4,'LOG Complain'!$B:$B,C$1) -> #DIV/0! | D4: =AVERAGEIFS('LOG Complain'!$G:$G,'LOG Complain'!$C:$C,$A4,'LOG Complain'!$B:$B,D$1) -> #DIV/0! | E4: =AVERAGEIFS('LOG Complain'!$G:$G,'LOG Complain'!$C:$C,$A4,'LOG Complain'!$B:$B,E$1) -> #DIV/0! | F4: =AVERAGEIFS('LOG Complain'!$G:$G,'LOG Complain'!$C:$C,$A4,'LOG Complain'!$B:$B,F$1) -> #DIV/0! | G4: =AVERAGEIFS('LOG Complain'!$G:$G,'LOG Complain'!$C:$C,$A4,'LOG Complain'!$B:$B,G$1) -> #DIV/0!
A5: Cilandak Barat | B5: =AVERAGEIFS('LOG Complain'!$G:$G,'LOG Complain'!$C:$C,$A5,'LOG Complain'!$B:$B,B$1) -> #DIV/0! | C5: =AVERAGEIFS('LOG Complain'!$G:$G,'LOG Complain'!$C:$C,$A5,'LOG Complain'!$B:$B,C$1) -> #DIV/0! | D5: =AVERAGEIFS('LOG Complain'!$G:$G,'LOG Complain'!$C:$C,$A5,'LOG Complain'!$B:$B,D$1) -> #DIV/0! | E5: =AVERAGEIFS('LOG Complain'!$G:$G,'LOG Complain'!$C:$C,$A5,'LOG Complain'!$B:$B,E$1) -> #DIV/0! | F5: =AVERAGEIFS('LOG Complain'!$G:$G,'LOG Complain'!$C:$C,$A5,'LOG Complain'!$B:$B,F$1) -> #DIV/0! | G5: =AVERAGEIFS('LOG Complain'!$G:$G,'LOG Complain'!$C:$C,$A5,'LOG Complain'!$B:$B,G$1) -> #DIV/0!
A6: Ciledug | B6: =AVERAGEIFS('LOG Complain'!$G:$G,'LOG Complain'!$C:$C,$A6,'LOG Complain'!$B:$B,B$1) -> #DIV/0! | C6: =AVERAGEIFS('LOG Complain'!$G:$G,'LOG Complain'!$C:$C,$A6,'LOG Complain'!$B:$B,C$1) -> #DIV/0! | D6: =AVERAGEIFS('LOG Complain'!$G:$G,'LOG Complain'!$C:$C,$A6,'LOG Complain'!$B:$B,D$1) -> #DIV/0! | E6: =AVERAGEIFS('LOG Complain'!$G:$G,'LOG Complain'!$C:$C,$A6,'LOG Complain'!$B:$B,E$1) -> #DIV/0! | F6: =AVERAGEIFS('LOG Complain'!$G:$G,'LOG Complain'!$C:$C,$A6,'LOG Complain'!$B:$B,F$1) -> #DIV/0! | G6: =AVERAGEIFS('LOG Complain'!$G:$G,'LOG Complain'!$C:$C,$A6,'LOG Complain'!$B:$B,G$1) -> #DIV/0!
A7: Cimahi | B7: =AVERAGEIFS('LOG Complain'!$G:$G,'LOG Complain'!$C:$C,$A7,'LOG Complain'!$B:$B,B$1) -> #DIV/0! | C7: =AVERAGEIFS('LOG Complain'!$G:$G,'LOG Complain'!$C:$C,$A7,'LOG Complain'!$B:$B,C$1) -> #DIV/0! | D7: =AVERAGEIFS('LOG Complain'!$G:$G,'LOG Complain'!$C:$C,$A7,'LOG Complain'!$B:$B,D$1) -> #DIV/0! | E7: =AVERAGEIFS('LOG Complain'!$G:$G,'LOG Complain'!$C:$C,$A7,'LOG Complain'!$B:$B,E$1) -> #DIV/0! | F7: =AVERAGEIFS('LOG Complain'!$G:$G,'LOG Complain'!$C:$C,$A7,'LOG Complain'!$B:$B,F$1) -> #DIV/0! | G7: =AVERAGEIFS('LOG Complain'!$G:$G,'LOG Complain'!$C:$C,$A7,'LOG Complain'!$B:$B,G$1) -> #DIV/0!
A8: Ciputat Jombang | B8: =AVERAGEIFS('LOG Complain'!$G:$G,'LOG Complain'!$C:$C,$A8,'LOG Complain'!$B:$B,B$1) -> #DIV/0! | C8: =AVERAGEIFS('LOG Complain'!$G:$G,'LOG Complain'!$C:$C,$A8,'LOG Complain'!$B:$B,C$1) -> #DIV/0! | D8: =AVERAGEIFS('LOG Complain'!$G:$G,'LOG Complain'!$C:$C,$A8,'LOG Complain'!$B:$B,D$1) -> #DIV/0! | E8: =AVERAGEIFS('LOG Complain'!$G:$G,'LOG Complain'!$C:$C,$A8,'LOG Complain'!$B:$B,E$1) -> #DIV/0! | F8: =AVERAGEIFS('LOG Complain'!$G:$G,'LOG Complain'!$C:$C,$A8,'LOG Complain'!$B:$B,F$1) -> #DIV/0! | G8: =AVERAGEIFS('LOG Complain'!$G:$G,'LOG Complain'!$C:$C,$A8,'LOG Complain'!$B:$B,G$1) -> #DIV/0!
A9: Ciputat Juanda | B9: =AVERAGEIFS('LOG Complain'!$G:$G,'LOG Complain'!$C:$C,$A9,'LOG Complain'!$B:$B,B$1) -> #DIV/0! | C9: =AVERAGEIFS('LOG Complain'!$G:$G,'LOG Complain'!$C:$C,$A9,'LOG Complain'!$B:$B,C$1) -> #DIV/0! | D9: =AVERAGEIFS('LOG Complain'!$G:$G,'LOG Complain'!$C:$C,$A9,'LOG Complain'!$B:$B,D$1) -> #DIV/0! | E9: =AVERAGEIFS('LOG Complain'!$G:$G,'LOG Complain'!$C:$C,$A9,'LOG Complain'!$B:$B,E$1) -> #DIV/0! | F9: =AVERAGEIFS('LOG Complain'!$G:$G,'LOG Complain'!$C:$C,$A9,'LOG Complain'!$B:$B,F$1) -> #DIV/0! | G9: =AVERAGEIFS('LOG Complain'!$G:$G,'LOG Complain'!$C:$C,$A9,'LOG Complain'!$B:$B,G$1) -> #DIV/0!
A10: Citraland | B10: =AVERAGEIFS('LOG Complain'!$G:$G,'LOG Complain'!$C:$C,$A10,'LOG Complain'!$B:$B,B$1) -> #DIV/0! | C10: =AVERAGEIFS('LOG Complain'!$G:$G,'LOG Complain'!$C:$C,$A10,'LOG Complain'!$B:$B,C$1) -> #DIV/0! | D10: =AVERAGEIFS('LOG Complain'!$G:$G,'LOG Complain'!$C:$C,$A10,'LOG Complain'!$B:$B,D$1) -> #DIV/0! | E10: =AVERAGEIFS('LOG Complain'!$G:$G,'LOG Complain'!$C:$C,$A10,'LOG Complain'!$B:$B,E$1) -> #DIV/0! | F10: =AVERAGEIFS('LOG Complain'!$G:$G,'LOG Complain'!$C:$C,$A10,'LOG Complain'!$B:$B,F$1) -> #DIV/0! | G10: =AVERAGEIFS('LOG Complain'!$G:$G,'LOG Complain'!$C:$C,$A10,'LOG Complain'!$B:$B,G$1) -> #DIV/0!
A11: Ciumbuleuit | B11: =AVERAGEIFS('LOG Complain'!$G:$G,'LOG Complain'!$C:$C,$A11,'LOG Complain'!$B:$B,B$1) -> #DIV/0! | C11: =AVERAGEIFS('LOG Complain'!$G:$G,'LOG Complain'!$C:$C,$A11,'LOG Complain'!$B:$B,C$1) -> #DIV/0! | D11: =AVERAGEIFS('LOG Complain'!$G:$G,'LOG Complain'!$C:$C,$A11,'LOG Complain'!$B:$B,D$1) -> #DIV/0! | E11: =AVERAGEIFS('LOG Complain'!$G:$G,'LOG Complain'!$C:$C,$A11,'LOG Complain'!$B:$B,E$1) -> #DIV/0! | F11: =AVERAGEIFS('LOG Complain'!$G:$G,'LOG Complain'!$C:$C,$A11,'LOG Complain'!$B:$B,F$1) -> #DIV/0! | G11: =AVERAGEIFS('LOG Complain'!$G:$G,'LOG Complain'!$C:$C,$A11,'LOG Complain'!$B:$B,G$1) -> #DIV/0!
A12: Jatinangor | B12: =AVERAGEIFS('LOG Complain'!$G:$G,'LOG Complain'!$C:$C,$A12,'LOG Complain'!$B:$B,B$1) -> #DIV/0! | C12: =AVERAGEIFS('LOG Complain'!$G:$G,'LOG Complain'!$C:$C,$A12,'LOG Complain'!$B:$B,C$1) -> #DIV/0! | D12: =AVERAGEIFS('LOG Complain'!$G:$G,'LOG Complain'!$C:$C,$A12,'LOG Complain'!$B:$B,D$1) -> #DIV/0! | E12: =AVERAGEIFS('LOG Complain'!$G:$G,'LOG Complain'!$C:$C,$A12,'LOG Complain'!$B:$B,E$1) -> #DIV/0! | F12: =AVERAGEIFS('LOG Complain'!$G:$G,'LOG Complain'!$C:$C,$A12,'LOG Complain'!$B:$B,F$1) -> #DIV/0! | G12: =AVERAGEIFS('LOG Complain'!$G:$G,'LOG Complain'!$C:$C,$A12,'LOG Complain'!$B:$B,G$1) -> #DIV/0!
A13: Kalimalang | B13: =AVERAGEIFS('LOG Complain'!$G:$G,'LOG Complain'!$C:$C,$A13,'LOG Complain'!$B:$B,B$1) -> #DIV/0! | C13: =AVERAGEIFS('LOG Complain'!$G:$G,'LOG Complain'!$C:$C,$A13,'LOG Complain'!$B:$B,C$1) -> #DIV/0! | D13: =AVERAGEIFS('LOG Complain'!$G:$G,'LOG Complain'!$C:$C,$A13,'LOG Complain'!$B:$B,D$1) -> #DIV/0! | E13: =AVERAGEIFS('LOG Complain'!$G:$G,'LOG Complain'!$C:$C,$A13,'LOG Complain'!$B:$B,E$1) -> #DIV/0! | F13: =AVERAGEIFS('LOG Complain'!$G:$G,'LOG Complain'!$C:$C,$A13,'LOG Complain'!$B:$B,F$1) -> #DIV/0! | G13: =AVERAGEIFS('LOG Complain'!$G:$G,'LOG Complain'!$C:$C,$A13,'LOG Complain'!$B:$B,G$1) -> #DIV/0!
A14: Karawaci | B14: =AVERAGEIFS('LOG Complain'!$G:$G,'LOG Complain'!$C:$C,$A14,'LOG Complain'!$B:$B,B$1) -> #DIV/0! | C14: =AVERAGEIFS('LOG Complain'!$G:$G,'LOG Complain'!$C:$C,$A14,'LOG Complain'!$B:$B,C$1) -> #DIV/0! | D14: =AVERAGEIFS('LOG Complain'!$G:$G,'LOG Complain'!$C:$C,$A14,'LOG Complain'!$B:$B,D$1) -> #DIV/0! | E14: =AVERAGEIFS('LOG Complain'!$G:$G,'LOG Complain'!$C:$C,$A14,'LOG Complain'!$B:$B,E$1) -> #DIV/0! | F14: =AVERAGEIFS('LOG Complain'!$G:$G,'LOG Complain'!$C:$C,$A14,'LOG Complain'!$B:$B,F$1) -> #DIV/0! | G14: =AVERAGEIFS('LOG Complain'!$G:$G,'LOG Complain'!$C:$C,$A14,'LOG Complain'!$B:$B,G$1) -> #DIV/0!
... A31: Ujung Berung | B31: =AVERAGEIFS('LOG Complain'!$G:$G,'LOG Complain'!$C:$C,$A31,'LOG Complain'!$B:$B,B$1) -> #DIV/0! | C31: =AVERAGEIFS('LOG Complain'!$G:$G,'LOG Complain'!$C:$C,$A31,'LOG Complain'!$B:$B,C$1) -> #DIV/0! | D31: =AVERAGEIFS('LOG Complain'!$G:$G,'LOG Complain'!$C:$C,$A31,'LOG Complain'!$B:$B,D$1) -> #DIV/0! | E31: =AVERAGEIFS('LOG Complain'!$G:$G,'LOG Complain'!$C:$C,$A31,'LOG Complain'!$B:$B,E$1) -> #DIV/0! | F31: =AVERAGEIFS('LOG Complain'!$G:$G,'LOG Complain'!$C:$C,$A31,'LOG Complain'!$B:$B,F$1) -> #DIV/0! | G31: =AVERAGEIFS('LOG Complain'!$G:$G,'LOG Complain'!$C:$C,$A31,'LOG Complain'!$B:$B,G$1) -> #DIV/0!
